Workbook

Sheet Read me
A1: UX Health Check - Criteria Library
A2: v1.51 - 24 October 2026 - for NZ Government agencies (see the Version tab for change history)
A4: Purpose
A5: What this is | B5: A library of self-assessment criteria for a 'UX health check' of a website or application, covering accessibility, usability, content, brand, security and privacy, reliability and service levels, support, legal obligations, content management and measurement. Each row is designed to become one question in the app, with its scoring weight, report recommendation and source.
A6: Intended use | B6: Source of truth for the app's question bank and scoring. The 'Criteria (simple)' tab is the proposed basis for the app; the full 'Criteria' tab is the detailed reference set. Export either to CSV or JSON to seed the app.
A7: Status | B7: Released as v1.00 for review and piloting. Weights, critical flags and wording should be validated with practitioners (accessibility, security, service owners) and tested on 2-3 real services before formal use.
A9: Tabs
A10: Criteria | B10: Detailed set: 96 criteria. Columns A-N are the library. Columns P-V are a test harness: enter answers in the yellow Test answer column to see how the scoring behaves. Columns W-X hold a short-labelled supporting link for each criterion, shown with its recommendation in the report.
A11: Scoring | B11: Scoring for the detailed set: parameters, category weights out of 100, overall score, critical-failure cap, rating band and the top 5 key recommendations.
A12: Criteria (simple) | B12: Simple set: only the criteria with weight 3 (the highest-importance criteria) - 19 questions across all 10 categories. Shows only the question, category, critical flag, recommendation, source, NZ status and applicability - no evidence prompts or weights. Text is pulled live from the Criteria tab by ID, so wording edits flow through. Answer in the yellow Answer column.
A13: Scoring (simple) | B13: Scores the simple set out of 100, using the same method as the detailed set. Its parameters and category points are separate, so the simple model can be tuned without affecting the detailed one.
A14: Materiality | B14: Separate assessment of how much the application matters - to its users and to the organisation - on a 5-point scale (1 Immaterial to 5 Critical), from 10 factor questions. It is not part of the UX health score and is reported separately.
A15: Service tiers | B15: Proposed service tier definitions (Platinum, Gold, Silver, Bronze) with availability, support, incident, recovery, monitoring and health check expectations. The suggested tier follows from the materiality rating.
A16: Report (simple) | B16: Preview of the output report for the simple set: UX health score and rating, materiality rating and service tier shown separately, key recommendations and category results. The app's report should follow this layout.
A17: Sources | B17: Every standard, law, guide and tool referenced, with version/status, a live link checked on 24 October 2026, how the link was checked, and licence notes for reusing wording.
A18: Version | B18: Version history. Each release has one row recording what changed, how the framework was developed and why.
A20: Editing legend
A21: Yellow cells | B21: Inputs you can change - answers, answer point values, critical cap, rating thresholds, category points.
A22: Grey cells | B22: Formulas - do not overwrite.
A23: Sample answers | B23: The answer columns on both criteria tabs are pre-filled with illustrative sample answers so the scoring can be seen working. They do not describe any real service. Clear or replace them.
A24: Simple set membership | B24: The 13 rows in Criteria (simple) were selected because their weight is 3. If you change a weight on the Criteria tab, add or remove the matching ID on Criteria (simple) by hand - membership is not automatic.
A26: Criteria columns
A27: ID | B27: Stable key for the app (category prefix + number). Don't reuse IDs for different criteria.
A28: Category / Sub-category | B28: Ten categories (see Scoring tab) with sub-categories for grouping in the report.
A29: Question | B29: Worded for a self-assessor. Answered Yes / Partial / No / N/A.
A30: Evidence prompt | B30: What the assessor should be able to show (detailed set only).
A31: Weight (1-3) | B31: Relative importance within its category: 3 = high, 2 = medium, 1 = low. Weight 3 rows form the simple set.
A32: Critical (Y/N) | B32: A 'No' on any critical criterion caps the overall score. Partial does not trigger the cap.
A33: Recommendation | B33: Text shown in the report when the answer is Partial or No.
A34: Source / Source version | B34: Where the criterion comes from, so it can be updated when the source changes.
A35: NZ status | B35: Mandatory (NZ) = required by NZ law or an all-of-government standard for mandated organisations. Recommended (NZ) = NZ Government guidance, draft standards or expected practice. Good practice = international practice with no NZ mandate.
A36: Applies to | B36: All, Public-facing, Transactional, Authenticated, Uses media, Uses CMS, Uses AI. The app can use this to hide irrelevant questions; otherwise answer N/A.
A37: Review notes | B37: Known upcoming changes, licence cautions and interpretation notes.
A39: Scoring model (both sets)
A40: Answer points | B40: Yes = 1, Partial = 0.5, No = 0. N/A and blank answers are excluded from both earned and available points.
A41: Category score | B41: (points earned) / (points available) x category points. Categories with no applicable answers are excluded and the rest are rescaled to 100.
A42: Overall score | B42: Sum of category scores, out of 100. If any critical criterion is answered No, the overall score is capped (default 60).
A43: Points lost | B43: For each Partial or No, the points it cost the overall score. Used to rank key recommendations (critical failures always rank first).
A45: Important caveats
A46: Changing NZ standards | B46: The Web Accessibility Standard 1.2 (WCAG 2.2 AA) is expected to be replaced by the Digital Accessibility Standard (based on EN 301 549) in early 2027. The Digital Service Design Standard is being refreshed, and Web Usability Standard requirements are expected to become guidance within it. A bill to repeal the Plain Language Act 2022 was before Parliament at the time of release. Affected rows are flagged in Review notes.
A47: Mandated organisations | B47: 'Mandatory (NZ)' standards apply to the organisations each standard mandates (for the Web Standards, public service departments and non-public service departments in the Executive branch). Crown entities and local government may not be mandated. Legislation applies according to its own scope.
A48: Automated testing | B48: Automated accessibility tools find only a subset of WCAG issues. Accessibility assessment should include manual and assistive technology testing.
A49: Not legal advice | B49: Legal and regulatory references identify relevant obligations; agencies should confirm applicability with their own legal and privacy advisors.
A50: Reusing wording | B50: All questions and recommendations are original wording written for this library. OWASP ASVS is referenced by chapter ID only, with no ASVS text reproduced. Check the Sources tab before copying text from any source into the app.
A51: Links | B51: All links on the Sources tab were checked against live pages on 24 October 2026. Re-check before publishing in the app.

Sheet Criteria
A1: ID | B1: Category | C1: Sub-category | D1: Question | E1: Answer type | F1: Evidence prompt | G1: Weight (1-3) | H1: Critical (Y/N) | I1: Recommendation (shown if Partial/No) | J1: Source | K1: Source version | L1: NZ status | M1: Applies to | N1: Review notes | P1: Test answer | Q1: Answer points | R1: Weighted earned | S1: Weighted available | T1: Report recommendation | U1: Points lost | V1: Rank key | W1: Supporting link label | X1: Supporting link
A2: ACC-01 | B2: Accessibility | C2: Conformance | D2: Has the service been assessed against WCAG 2.2 Level AA in the last 12 months, including manual testing (not automated tools alone)? | E2: Yes / Partial / No / N/A | F2: Dated accessibility audit report covering the service's key pages and complete processes, with manual test results. | G2: 3 | H2: Y | I2: Commission or complete a WCAG 2.2 AA assessment that includes manual and assistive technology testing, covering every page in each complete process, and repeat it at least annually or after major change. | J2: NZ Government Web Accessibility Standard; WCAG 2.2 | K2: WAS 1.2 (from 17 Mar 2025); WCAG 2.2 AA | L2: Mandatory (NZ) | M2: All | N2: Draft Digital Accessibility Standard (DAS), based on EN 301 549, expected to replace WAS in early 2027. Review wording when DAS is final. | P2: Yes | Q2: =IF(P2="Yes",Scoring!$C$6,IF(P2="Partial",Scoring!$C$7,IF(P2="No",Scoring!$C$8,""))) -> 1 | R2: =IF(Q2="",0,G2*Q2) -> 3 | S2: =IF(Q2="",0,G2) -> 3 | T2: =IF(OR(P2="Partial",P2="No"),I2,"") | U2: =IF(Q2="",0,(1-Q2)*G2/SUMIFS($S$2:$S$97,$B$2:$B$97,B2)*INDEX(Scoring!$C$18:$C$27,MATCH(B2,Scoring!$B$18:$B$27,0))) -> 0 | V2: =IF(U2>0,U2+IF(AND(H2="Y",P2="No"),1000,0)+ROW()/100000,0) -> 0 | W2: NZ Web Accessibility Standard 1.2 | X2: https://www.digital.govt.nz/standards-and-guidance/nz-government-web-standards/web-accessibility-standard-1-2
A3: ACC-02 | B3: Accessibility | C3: Assistive technology | D3: Have the service's key tasks been tested end to end with screen readers on both desktop and mobile (for example NVDA or JAWS, VoiceOver, TalkBack)? | E3: Yes / Partial / No / N/A | F3: Test scripts and results per screen reader/browser combination, dated, with issues logged. | G3: 3 | H3: N | I3: Test every key task with at least one desktop and one mobile screen reader, ideally including blind and low vision users, and fix issues that stop tasks being completed. | J3: WCAG 2.2 SC 4.1.2, 1.3.1; W3C WCAG-EM | K3: WCAG 2.2; WCAG-EM 2.0 (Jul 2026) | L3: Recommended (NZ) | M3: All | P3: Yes | Q3: =IF(P3="Yes",Scoring!$C$6,IF(P3="Partial",Scoring!$C$7,IF(P3="No",Scoring!$C$8,""))) -> 1 | R3: =IF(Q3="",0,G3*Q3) -> 3 | S3: =IF(Q3="",0,G3) -> 3 | T3: =IF(OR(P3="Partial",P3="No"),I3,"") | U3: =IF(Q3="",0,(1-Q3)*G3/SUMIFS($S$2:$S$97,$B$2:$B$97,B3)*INDEX(Scoring!$C$18:$C$27,MATCH(B3,Scoring!$B$18:$B$27,0))) -> 0 | V3: =IF(U3>0,U3+IF(AND(H3="Y",P3="No"),1000,0)+ROW()/100000,0) -> 0 | W3: W3C accessibility evaluation methodology | X3: https://www.w3.org/WAI/test-evaluate/conformance/wcag-em/
A4: ACC-03 | B4: Accessibility | C4: Perceivable | D4: Do all images, icons, charts and other non-text content have appropriate text alternatives (or are marked as decorative)? | E4: Yes / Partial / No / N/A | F4: Audit findings for SC 1.1.1; content guidance requiring alt text; CMS alt text field usage. | G4: 2 | H4: N | I4: Provide meaningful text alternatives for informative images, icons and charts, mark decorative images so screen readers skip them, and provide data tables for complex charts. | J4: WCAG 2.2 SC 1.1.1 | K4: WCAG 2.2 A | L4: Mandatory (NZ) | M4: All | P4: Partial | Q4: =IF(P4="Yes",Scoring!$C$6,IF(P4="Partial",Scoring!$C$7,IF(P4="No",Scoring!$C$8,""))) -> 0.5 | R4: =IF(Q4="",0,G4*Q4) -> 1 | S4: =IF(Q4="",0,G4) -> 2 | T4: =IF(OR(P4="Partial",P4="No"),I4,"") -> Provide meaningful text alternatives for informative images, icons and charts, mark decorative images so screen readers skip them, and provide data tables for complex charts. | U4: =IF(Q4="",0,(1-Q4)*G4/SUMIFS($S$2:$S$97,$B$2:$B$97,B4)*INDEX(Scoring!$C$18:$C$27,MATCH(B4,Scoring!$B$18:$B$27,0))) -> 0.60606061 | V4: =IF(U4>0,U4+IF(AND(H4="Y",P4="No"),1000,0)+ROW()/100000,0) -> 0.60610061 | W4: WCAG 2.2 quick reference | X4: https://www.w3.org/WAI/WCAG22/quickref/
A5: ACC-04 | B5: Accessibility | C5: Perceivable | D5: Is page structure conveyed programmatically - meaningful page titles, headings, landmarks, lists, table headers and form labels? | E5: Yes / Partial / No / N/A | F5: Audit findings for SC 1.3.1, 2.4.2, 2.4.6; screen reader heading/landmark navigation test. | G5: 2 | H5: N | I5: Use semantic HTML (headings, landmarks, lists, labelled controls) and unique, descriptive page titles so screen reader users can understand and navigate the structure. | J5: WCAG 2.2 SC 1.3.1, 2.4.2, 2.4.6 | K5: WCAG 2.2 A/AA | L5: Mandatory (NZ) | M5: All | P5: Yes | Q5: =IF(P5="Yes",Scoring!$C$6,IF(P5="Partial",Scoring!$C$7,IF(P5="No",Scoring!$C$8,""))) -> 1 | R5: =IF(Q5="",0,G5*Q5) -> 2 | S5: =IF(Q5="",0,G5) -> 2 | T5: =IF(OR(P5="Partial",P5="No"),I5,"") | U5: =IF(Q5="",0,(1-Q5)*G5/SUMIFS($S$2:$S$97,$B$2:$B$97,B5)*INDEX(Scoring!$C$18:$C$27,MATCH(B5,Scoring!$B$18:$B$27,0))) -> 0 | V5: =IF(U5>0,U5+IF(AND(H5="Y",P5="No"),1000,0)+ROW()/100000,0) -> 0 | W5: WCAG 2.2 quick reference | X5: https://www.w3.org/WAI/WCAG22/quickref/
A6: ACC-05 | B6: Accessibility | C6: Operable | D6: Can every function be used with a keyboard alone, with no keyboard traps, a logical focus order, and a visible focus indicator that is not hidden by other content? | E6: Yes / Partial / No / N/A | F6: Keyboard-only test of each key task; audit findings for SC 2.1.1, 2.1.2, 2.4.3, 2.4.7, 2.4.11. | G6: 3 | H6: Y | I6: Make all functionality keyboard operable, remove keyboard traps, keep focus order logical and ensure the focus indicator is always visible and not obscured by sticky headers, banners or overlays. | J6: WCAG 2.2 SC 2.1.1, 2.1.2, 2.4.3, 2.4.7, 2.4.11 | K6: WCAG 2.2 A/AA | L6: Mandatory (NZ) | M6: All | P6: Partial | Q6: =IF(P6="Yes",Scoring!$C$6,IF(P6="Partial",Scoring!$C$7,IF(P6="No",Scoring!$C$8,""))) -> 0.5 | R6: =IF(Q6="",0,G6*Q6) -> 1.5 | S6: =IF(Q6="",0,G6) -> 3 | T6: =IF(OR(P6="Partial",P6="No"),I6,"") -> Make all functionality keyboard operable, remove keyboard traps, keep focus order logical and ensure the focus indicator is always visible and not obscured by sticky headers, banners or overlays. | U6: =IF(Q6="",0,(1-Q6)*G6/SUMIFS($S$2:$S$97,$B$2:$B$97,B6)*INDEX(Scoring!$C$18:$C$27,MATCH(B6,Scoring!$B$18:$B$27,0))) -> 0.90909091 | V6: =IF(U6>0,U6+IF(AND(H6="Y",P6="No"),1000,0)+ROW()/100000,0) -> 0.90915091 | W6: WCAG 2.2 quick reference | X6: https://www.w3.org/WAI/WCAG22/quickref/
A7: ACC-06 | B7: Accessibility | C7: Low vision | D7: Do text, icons, form borders and focus indicators meet WCAG contrast ratios (4.5:1 for normal text, 3:1 for large text and non-text elements)? | E7: Yes / Partial / No / N/A | F7: Contrast check results for brand palette and UI components; audit findings for SC 1.4.3 and 1.4.11. | G7: 2 | H7: N | I7: Check all text and interface components against WCAG contrast ratios and adjust colour tokens in the design system so every combination in use passes. | J7: WCAG 2.2 SC 1.4.3, 1.4.11 | K7: WCAG 2.2 AA | L7: Mandatory (NZ) | M7: All | P7: Yes | Q7: =IF(P7="Yes",Scoring!$C$6,IF(P7="Partial",Scoring!$C$7,IF(P7="No",Scoring!$C$8,""))) -> 1 | R7: =IF(Q7="",0,G7*Q7) -> 2 | S7: =IF(Q7="",0,G7) -> 2 | T7: =IF(OR(P7="Partial",P7="No"),I7,"") | U7: =IF(Q7="",0,(1-Q7)*G7/SUMIFS($S$2:$S$97,$B$2:$B$97,B7)*INDEX(Scoring!$C$18:$C$27,MATCH(B7,Scoring!$B$18:$B$27,0))) -> 0 | V7: =IF(U7>0,U7+IF(AND(H7="Y",P7="No"),1000,0)+ROW()/100000,0) -> 0 | W7: WCAG 2.2 quick reference | X7: https://www.w3.org/WAI/WCAG22/quickref/
A8: ACC-07 | B8: Accessibility | C8: Low vision | D8: Does content remain usable when text is resized to 200% and when zoomed to 400% (320 CSS pixels wide) without loss of content or horizontal scrolling? | E8: Yes / Partial / No / N/A | F8: Zoom and reflow test results on key pages; audit findings for SC 1.4.4, 1.4.10, 1.4.12. | G8: 2 | H8: N | I8: Use responsive layouts and relative units so content reflows at 400% zoom and text spacing can be increased without content being cut off or overlapping. | J8: WCAG 2.2 SC 1.4.4, 1.4.10, 1.4.12 | K8: WCAG 2.2 AA | L8: Mandatory (NZ) | M8: All | P8: Partial | Q8: =IF(P8="Yes",Scoring!$C$6,IF(P8="Partial",Scoring!$C$7,IF(P8="No",Scoring!$C$8,""))) -> 0.5 | R8: =IF(Q8="",0,G8*Q8) -> 1 | S8: =IF(Q8="",0,G8) -> 2 | T8: =IF(OR(P8="Partial",P8="No"),I8,"") -> Use responsive layouts and relative units so content reflows at 400% zoom and text spacing can be increased without content being cut off or overlapping. | U8: =IF(Q8="",0,(1-Q8)*G8/SUMIFS($S$2:$S$97,$B$2:$B$97,B8)*INDEX(Scoring!$C$18:$C$27,MATCH(B8,Scoring!$B$18:$B$27,0))) -> 0.60606061 | V8: =IF(U8>0,U8+IF(AND(H8="Y",P8="No"),1000,0)+ROW()/100000,0) -> 0.60614061 | W8: WCAG 2.2 quick reference | X8: https://www.w3.org/WAI/WCAG22/quickref/
A9: ACC-08 | B9: Accessibility | C9: Perceivable | D9: Is information never conveyed by colour alone (for example error states, required fields, chart series, status indicators)? | E9: Yes / Partial / No / N/A | F9: Audit findings for SC 1.4.1; review of status and error patterns. | G9: 1 | H9: N | I9: Pair colour with text, icons or patterns so information is still available to people who cannot perceive colour differences. | J9: WCAG 2.2 SC 1.4.1 | K9: WCAG 2.2 A | L9: Mandatory (NZ) | M9: All | P9: Yes | Q9: =IF(P9="Yes",Scoring!$C$6,IF(P9="Partial",Scoring!$C$7,IF(P9="No",Scoring!$C$8,""))) -> 1 | R9: =IF(Q9="",0,G9*Q9) -> 1 | S9: =IF(Q9="",0,G9) -> 1 | T9: =IF(OR(P9="Partial",P9="No"),I9,"") | U9: =IF(Q9="",0,(1-Q9)*G9/SUMIFS($S$2:$S$97,$B$2:$B$97,B9)*INDEX(Scoring!$C$18:$C$27,MATCH(B9,Scoring!$B$18:$B$27,0))) -> 0 | V9: =IF(U9>0,U9+IF(AND(H9="Y",P9="No"),1000,0)+ROW()/100000,0) -> 0 | W9: WCAG 2.2 quick reference | X9: https://www.w3.org/WAI/WCAG22/quickref/
A10: ACC-09 | B10: Accessibility | C10: Forms | D10: Do forms have visible labels and instructions, identify errors in text, suggest corrections, and announce status messages to assistive technology? | E10: Yes / Partial / No / N/A | F10: Audit findings for SC 3.3.1, 3.3.2, 3.3.3, 4.1.3; screen reader test of form errors. | G10: 2 | H10: N | I10: Give every field a visible label and clear instructions, describe errors in text next to the field and in a summary, suggest how to fix them, and announce status changes to screen readers. | J10: WCAG 2.2 SC 3.3.1, 3.3.2, 3.3.3, 4.1.3 | K10: WCAG 2.2 A/AA | L10: Mandatory (NZ) | M10: Transactional | P10: Yes | Q10: =IF(P10="Yes",Scoring!$C$6,IF(P10="Partial",Scoring!$C$7,IF(P10="No",Scoring!$C$8,""))) -> 1 | R10: =IF(Q10="",0,G10*Q10) -> 2 | S10: =IF(Q10="",0,G10) -> 2 | T10: =IF(OR(P10="Partial",P10="No"),I10,"") | U10: =IF(Q10="",0,(1-Q10)*G10/SUMIFS($S$2:$S$97,$B$2:$B$97,B10)*INDEX(Scoring!$C$18:$C$27,MATCH(B10,Scoring!$B$18:$B$27,0))) -> 0 | V10: =IF(U10>0,U10+IF(AND(H10="Y",P10="No"),1000,0)+ROW()/100000,0) -> 0 | W10: WCAG 2.2 quick reference | X10: https://www.w3.org/WAI/WCAG22/quickref/
A11: ACC-10 | B11: Accessibility | C11: Forms | D11: Does sign-in avoid cognitive function tests (such as remembering or transcribing codes without paste or password manager support), and does the service avoid asking for the same information twice? | E11: Yes / Partial / No / N/A | F11: Audit findings for SC 3.3.7 and 3.3.8 (new in WCAG 2.2); sign-in flow review. | G11: 2 | H11: N | I11: Allow paste and password managers, offer alternatives to puzzles or memory tests at sign-in, and auto-fill or let users select information they have already given. | J11: WCAG 2.2 SC 3.3.7, 3.3.8 | K11: WCAG 2.2 A/AA | L11: Mandatory (NZ) | M11: Authenticated | P11: Partial | Q11: =IF(P11="Yes",Scoring!$C$6,IF(P11="Partial",Scoring!$C$7,IF(P11="No",Scoring!$C$8,""))) -> 0.5 | R11: =IF(Q11="",0,G11*Q11) -> 1 | S11: =IF(Q11="",0,G11) -> 2 | T11: =IF(OR(P11="Partial",P11="No"),I11,"") -> Allow paste and password managers, offer alternatives to puzzles or memory tests at sign-in, and auto-fill or let users select information they have already given. | U11: =IF(Q11="",0,(1-Q11)*G11/SUMIFS($S$2:$S$97,$B$2:$B$97,B11)*INDEX(Scoring!$C$18:$C$27,MATCH(B11,Scoring!$B$18:$B$27,0))) -> 0.60606061 | V11: =IF(U11>0,U11+IF(AND(H11="Y",P11="No"),1000,0)+ROW()/100000,0) -> 0.60617061 | W11: WCAG 2.2 quick reference | X11: https://www.w3.org/WAI/WCAG22/quickref/
A12: ACC-11 | B12: Accessibility | C12: Mobile | D12: Are touch targets large enough (at least 24 by 24 CSS pixels or adequately spaced), and can actions that use dragging or multi-point gestures also be done with a single tap? | E12: Yes / Partial / No / N/A | F12: Audit findings for SC 2.5.7, 2.5.8; mobile device testing. | G12: 1 | H12: N | I12: Size and space interactive targets to at least 24 by 24 CSS pixels and provide single-pointer alternatives for drag and gesture interactions. | J12: WCAG 2.2 SC 2.5.7, 2.5.8 | K12: WCAG 2.2 AA | L12: Mandatory (NZ) | M12: All | P12: Yes | Q12: =IF(P12="Yes",Scoring!$C$6,IF(P12="Partial",Scoring!$C$7,IF(P12="No",Scoring!$C$8,""))) -> 1 | R12: =IF(Q12="",0,G12*Q12) -> 1 | S12: =IF(Q12="",0,G12) -> 1 | T12: =IF(OR(P12="Partial",P12="No"),I12,"") | U12: =IF(Q12="",0,(1-Q12)*G12/SUMIFS($S$2:$S$97,$B$2:$B$97,B12)*INDEX(Scoring!$C$18:$C$27,MATCH(B12,Scoring!$B$18:$B$27,0))) -> 0 | V12: =IF(U12>0,U12+IF(AND(H12="Y",P12="No"),1000,0)+ROW()/100000,0) -> 0 | W12: WCAG 2.2 quick reference | X12: https://www.w3.org/WAI/WCAG22/quickref/
A13: ACC-12 | B13: Accessibility | C13: Media | D13: Do videos and audio have captions, transcripts and (where needed) audio description? | E13: Yes / Partial / No / N/A | F13: Media inventory showing captions, transcripts and audio description status. | G13: 1 | H13: N | I13: Provide captions and transcripts for all prerecorded media and audio description where visual information is not otherwise conveyed, noting the specific exceptions in the Web Accessibility Standard. | J13: WCAG 2.2 SC 1.2.1, 1.2.2, 1.2.5; WAS 1.2 exceptions | K13: WCAG 2.2 A/AA; WAS 1.2 | L13: Mandatory (NZ) | M13: Uses media | N13: WAS 1.2 modifies some media requirements (e.g. live captions, audio description). Check current exceptions. | P13: Partial | Q13: =IF(P13="Yes",Scoring!$C$6,IF(P13="Partial",Scoring!$C$7,IF(P13="No",Scoring!$C$8,""))) -> 0.5 | R13: =IF(Q13="",0,G13*Q13) -> 0.5 | S13: =IF(Q13="",0,G13) -> 1 | T13: =IF(OR(P13="Partial",P13="No"),I13,"") -> Provide captions and transcripts for all prerecorded media and audio description where visual information is not otherwise conveyed, noting the specific exceptions in the Web Accessibility Standard. | U13: =IF(Q13="",0,(1-Q13)*G13/SUMIFS($S$2:$S$97,$B$2:$B$97,B13)*INDEX(Scoring!$C$18:$C$27,MATCH(B13,Scoring!$B$18:$B$27,0))) -> 0.3030303 | V13: =IF(U13>0,U13+IF(AND(H13="Y",P13="No"),1000,0)+ROW()/100000,0) -> 0.3031603 | W13: WCAG 2.2 quick reference | X13: https://www.w3.org/WAI/WCAG22/quickref/
A14: ACC-13 | B14: Accessibility | C14: Documents | D14: Are PDFs, Word and other documents published by the service accessible, or accompanied by an accessible HTML alternative? | E14: Yes / Partial / No / N/A | F14: Document inventory with accessibility status; publishing guidance. | G14: 2 | H14: N | I14: Publish key content as HTML first; where documents are needed, make them accessible (tagged, structured, with alt text) or provide an accessible alternative. | J14: NZ Government Web Accessibility Guide (accessibility-supported technologies); draft DAS | K14: WAS 1.2; DAS draft (Jul 2026) | L14: Mandatory (NZ) | M14: All | N14: Draft DAS extends scope beyond websites to documents, emails and mobile apps. | P14: Yes | Q14: =IF(P14="Yes",Scoring!$C$6,IF(P14="Partial",Scoring!$C$7,IF(P14="No",Scoring!$C$8,""))) -> 1 | R14: =IF(Q14="",0,G14*Q14) -> 2 | S14: =IF(Q14="",0,G14) -> 2 | T14: =IF(OR(P14="Partial",P14="No"),I14,"") | U14: =IF(Q14="",0,(1-Q14)*G14/SUMIFS($S$2:$S$97,$B$2:$B$97,B14)*INDEX(Scoring!$C$18:$C$27,MATCH(B14,Scoring!$B$18:$B$27,0))) -> 0 | V14: =IF(U14>0,U14+IF(AND(H14="Y",P14="No"),1000,0)+ROW()/100000,0) -> 0 | W14: NZ Digital Accessibility Standard (draft) | X14: https://www.digital.govt.nz/standards-and-guidance/nz-government-web-standards/digital-accessibility-standard
A15: ACC-14 | B15: Accessibility | C15: Process | D15: Is automated accessibility testing built into the design, build and release process (for example axe-core, Pa11y or CWAC) so detectable errors are caught before release? | E15: Yes / Partial / No / N/A | F15: CI/CD configuration or test reports; CWAC scan results for the service. | G15: 2 | H15: N | I15: Add automated accessibility checks to the build pipeline and content publishing workflow, and treat new automatically detectable errors as release blockers. | J15: GCDO guidance on CWAC and automated testing | K15: CWAC (open source) | L15: Recommended (NZ) | M15: All | N15: Automated tests detect only a subset of WCAG issues; never use as the sole evidence for ACC-01. CWAC is open source (GPL-3.0). | P15: Yes | Q15: =IF(P15="Yes",Scoring!$C$6,IF(P15="Partial",Scoring!$C$7,IF(P15="No",Scoring!$C$8,""))) -> 1 | R15: =IF(Q15="",0,G15*Q15) -> 2 | S15: =IF(Q15="",0,G15) -> 2 | T15: =IF(OR(P15="Partial",P15="No"),I15,"") | U15: =IF(Q15="",0,(1-Q15)*G15/SUMIFS($S$2:$S$97,$B$2:$B$97,B15)*INDEX(Scoring!$C$18:$C$27,MATCH(B15,Scoring!$B$18:$B$27,0))) -> 0 | V15: =IF(U15>0,U15+IF(AND(H15="Y",P15="No"),1000,0)+ROW()/100000,0) -> 0 | W15: CWAC accessibility checker (GitHub) | X15: https://github.com/GOVTNZ/cwac
A16: ACC-15 | B16: Accessibility | C16: Reporting | D16: Is there a published accessibility statement giving conformance status, known issues, alternatives and how to report a problem, and a risk assessment and management plan for any non-conformance? | E16: Yes / Partial / No / N/A | F16: Accessibility statement URL; risk assessment and management plan. | G16: 2 | H16: N | I16: Publish and maintain an accessibility statement, and document a risk assessment and management plan for any areas that do not yet conform, with dates for fixes. | J16: Web Accessibility Standard 1.2 s4 (assessment and reporting, incl. risk assessment and management plan) | K16: WAS 1.2 | L16: Mandatory (NZ) | M16: Public-facing | P16: Yes | Q16: =IF(P16="Yes",Scoring!$C$6,IF(P16="Partial",Scoring!$C$7,IF(P16="No",Scoring!$C$8,""))) -> 1 | R16: =IF(Q16="",0,G16*Q16) -> 2 | S16: =IF(Q16="",0,G16) -> 2 | T16: =IF(OR(P16="Partial",P16="No"),I16,"") | U16: =IF(Q16="",0,(1-Q16)*G16/SUMIFS($S$2:$S$97,$B$2:$B$97,B16)*INDEX(Scoring!$C$18:$C$27,MATCH(B16,Scoring!$B$18:$B$27,0))) -> 0 | V16: =IF(U16>0,U16+IF(AND(H16="Y",P16="No"),1000,0)+ROW()/100000,0) -> 0 | W16: NZ Web Accessibility Standard 1.2 | X16: https://www.digital.govt.nz/standards-and-guidance/nz-government-web-standards/web-accessibility-standard-1-2
A17: ACC-16 | B17: Accessibility | C17: Inclusion | D17: Have disabled people (including blind and low vision users) been included in user research and usability testing for this service? | E17: Yes / Partial / No / N/A | F17: Research plans and participant summaries showing disabled participants and assistive technology used. | G17: 2 | H17: N | I17: Recruit disabled people, including assistive technology users, into research and usability testing at each major stage of design and change. | J17: Digital Service Design Standard; AU Digital Service Standard 2.0 criterion 3 (leave no one behind) | K17: DSDS 2018 (refresh underway); AU DSS 2.0 | L17: Recommended (NZ) | M17: All | P17: Partial | Q17: =IF(P17="Yes",Scoring!$C$6,IF(P17="Partial",Scoring!$C$7,IF(P17="No",Scoring!$C$8,""))) -> 0.5 | R17: =IF(Q17="",0,G17*Q17) -> 1 | S17: =IF(Q17="",0,G17) -> 2 | T17: =IF(OR(P17="Partial",P17="No"),I17,"") -> Recruit disabled people, including assistive technology users, into research and usability testing at each major stage of design and change. | U17: =IF(Q17="",0,(1-Q17)*G17/SUMIFS($S$2:$S$97,$B$2:$B$97,B17)*INDEX(Scoring!$C$18:$C$27,MATCH(B17,Scoring!$B$18:$B$27,0))) -> 0.60606061 | V17: =IF(U17>0,U17+IF(AND(H17="Y",P17="No"),1000,0)+ROW()/100000,0) -> 0.60623061 | W17: GOV.UK: making services more inclusive | X17: https://www.gov.uk/service-manual/design/making-your-service-more-inclusive
A18: ACC-17 | B18: Accessibility | C18: Maturity | D18: Does the organisation have accessibility roles, training, and accessibility requirements in procurement and vendor contracts that apply to this service? | E18: Yes / Partial / No / N/A | F18: Role descriptions, training records, contract clauses requiring WCAG 2.2 AA. | G18: 1 | H18: N | I18: Assign accessibility accountability, train designers, developers and content authors, and include accessibility conformance requirements and acceptance testing in vendor contracts. | J18: W3C Accessibility Maturity Model | K18: W3C Group Note (Nov 2025) | L18: Good practice | M18: All | P18: Yes | Q18: =IF(P18="Yes",Scoring!$C$6,IF(P18="Partial",Scoring!$C$7,IF(P18="No",Scoring!$C$8,""))) -> 1 | R18: =IF(Q18="",0,G18*Q18) -> 1 | S18: =IF(Q18="",0,G18) -> 1 | T18: =IF(OR(P18="Partial",P18="No"),I18,"") | U18: =IF(Q18="",0,(1-Q18)*G18/SUMIFS($S$2:$S$97,$B$2:$B$97,B18)*INDEX(Scoring!$C$18:$C$27,MATCH(B18,Scoring!$B$18:$B$27,0))) -> 0 | V18: =IF(U18>0,U18+IF(AND(H18="Y",P18="No"),1000,0)+ROW()/100000,0) -> 0 | W18: W3C Accessibility Maturity Model | X18: https://www.w3.org/TR/maturity-model/
A19: UXD-01 | B19: Usability and design | C19: Responsive design | D19: Is the service responsive or adaptive, so content and controls scale and reflow correctly across phone, tablet and desktop screen sizes and orientations? | E19: Yes / Partial / No / N/A | F19: Device/browser test matrix results; analytics showing device mix. | G19: 3 | H19: Y | I19: Ensure the application is adaptive, so content and objects scale to the user's screen size and orientation, and test key tasks on the devices your users actually use. | J19: OMB M-23-22 (design pillar); WCAG 2.2 SC 1.3.4, 1.4.10 | K19: M-23-22 (2023); WCAG 2.2 | L19: Good practice | M19: All | P19: Partial | Q19: =IF(P19="Yes",Scoring!$C$6,IF(P19="Partial",Scoring!$C$7,IF(P19="No",Scoring!$C$8,""))) -> 0.5 | R19: =IF(Q19="",0,G19*Q19) -> 1.5 | S19: =IF(Q19="",0,G19) -> 3 | T19: =IF(OR(P19="Partial",P19="No"),I19,"") -> Ensure the application is adaptive, so content and objects scale to the user's screen size and orientation, and test key tasks on the devices your users actually use. | U19: =IF(Q19="",0,(1-Q19)*G19/SUMIFS($S$2:$S$97,$B$2:$B$97,B19)*INDEX(Scoring!$C$18:$C$27,MATCH(B19,Scoring!$B$18:$B$27,0))) -> 0.97826087 | V19: =IF(U19>0,U19+IF(AND(H19="Y",P19="No"),1000,0)+ROW()/100000,0) -> 0.97845087 | W19: GOV.UK: services that work on mobile | X19: https://www.gov.uk/service-manual/technology/working-with-mobile-technology
A20: UXD-02 | B20: Usability and design | C20: User research | D20: Has research with real users of this service (not proxies) informed its design or changes in the last 12 months? | E20: Yes / Partial / No / N/A | F20: Research reports, insights repository, decisions traced to research. | G20: 3 | H20: N | I20: Run regular user research with people who use the service, including those who struggle, and record how findings change the service. | J20: GOV.UK Service Standard point 1; AU DSS 2.0 criterion 2; Digital Service Design Standard | K20: GOV.UK SS (2019); AU DSS 2.0 | L20: Recommended (NZ) | M20: All | P20: Yes | Q20: =IF(P20="Yes",Scoring!$C$6,IF(P20="Partial",Scoring!$C$7,IF(P20="No",Scoring!$C$8,""))) -> 1 | R20: =IF(Q20="",0,G20*Q20) -> 3 | S20: =IF(Q20="",0,G20) -> 3 | T20: =IF(OR(P20="Partial",P20="No"),I20,"") | U20: =IF(Q20="",0,(1-Q20)*G20/SUMIFS($S$2:$S$97,$B$2:$B$97,B20)*INDEX(Scoring!$C$18:$C$27,MATCH(B20,Scoring!$B$18:$B$27,0))) -> 0 | V20: =IF(U20>0,U20+IF(AND(H20="Y",P20="No"),1000,0)+ROW()/100000,0) -> 0 | W20: GOV.UK: understand users and needs | X20: https://www.gov.uk/service-manual/service-standard/point-1-understand-user-needs
A21: UXD-03 | B21: Usability and design | C21: Usability testing | D21: Have the service's key tasks been usability tested with representative users, with task success and problem areas measured? | E21: Yes / Partial / No / N/A | F21: Usability test reports with task completion rates and severity-rated issues. | G21: 2 | H21: N | I21: Usability test the most important tasks with representative users at least annually and after significant change, and fix high-severity issues first. | J21: GOV.UK Service Standard point 4; ISO 9241-11 | K21: GOV.UK SS; ISO 9241-11:2018 | L21: Good practice | M21: All | P21: Partial | Q21: =IF(P21="Yes",Scoring!$C$6,IF(P21="Partial",Scoring!$C$7,IF(P21="No",Scoring!$C$8,""))) -> 0.5 | R21: =IF(Q21="",0,G21*Q21) -> 1 | S21: =IF(Q21="",0,G21) -> 2 | T21: =IF(OR(P21="Partial",P21="No"),I21,"") -> Usability test the most important tasks with representative users at least annually and after significant change, and fix high-severity issues first. | U21: =IF(Q21="",0,(1-Q21)*G21/SUMIFS($S$2:$S$97,$B$2:$B$97,B21)*INDEX(Scoring!$C$18:$C$27,MATCH(B21,Scoring!$B$18:$B$27,0))) -> 0.65217391 | V21: =IF(U21>0,U21+IF(AND(H21="Y",P21="No"),1000,0)+ROW()/100000,0) -> 0.65238391 | W21: GOV.UK: make the service simple | X21: https://www.gov.uk/service-manual/service-standard/point-4-make-the-service-simple-to-use
A22: UXD-04 | B22: Usability and design | C22: Heuristics | D22: Has the service been reviewed against recognised usability heuristics (for example Nielsen's 10 usability heuristics) in the last 12 months? | E22: Yes / Partial / No / N/A | F22: Heuristic review findings with severity ratings. | G22: 1 | H22: N | I22: Complete a heuristic review against Nielsen's 10 usability heuristics and add findings to the improvement backlog. | J22: Nielsen's 10 usability heuristics (NN/g) | K22: 1994, updated 2020 | L22: Good practice | M22: All | N22: Reuse heuristic names and concepts; write your own descriptions rather than copying NN/g text. | P22: Yes | Q22: =IF(P22="Yes",Scoring!$C$6,IF(P22="Partial",Scoring!$C$7,IF(P22="No",Scoring!$C$8,""))) -> 1 | R22: =IF(Q22="",0,G22*Q22) -> 1 | S22: =IF(Q22="",0,G22) -> 1 | T22: =IF(OR(P22="Partial",P22="No"),I22,"") | U22: =IF(Q22="",0,(1-Q22)*G22/SUMIFS($S$2:$S$97,$B$2:$B$97,B22)*INDEX(Scoring!$C$18:$C$27,MATCH(B22,Scoring!$B$18:$B$27,0))) -> 0 | V22: =IF(U22>0,U22+IF(AND(H22="Y",P22="No"),1000,0)+ROW()/100000,0) -> 0 | W22: NN/g: running a heuristic evaluation | X22: https://www.nngroup.com/articles/how-to-conduct-a-heuristic-evaluation/
A23: UXD-05 | B23: Usability and design | C23: Feedback | D23: Does the service always tell users what is happening - loading, saving, submitting - and give clear confirmation of what has been done and what happens next? | E23: Yes / Partial / No / N/A | F23: Screens for loading, success and confirmation states; confirmation messages/emails. | G23: 2 | H23: N | I23: Show clear progress and loading states, and give a confirmation page and message with a reference number and what happens next for every completed transaction. | J23: Nielsen heuristic 1 (visibility of system status) | L23: Good practice | M23: All | P23: Yes | Q23: =IF(P23="Yes",Scoring!$C$6,IF(P23="Partial",Scoring!$C$7,IF(P23="No",Scoring!$C$8,""))) -> 1 | R23: =IF(Q23="",0,G23*Q23) -> 2 | S23: =IF(Q23="",0,G23) -> 2 | T23: =IF(OR(P23="Partial",P23="No"),I23,"") | U23: =IF(Q23="",0,(1-Q23)*G23/SUMIFS($S$2:$S$97,$B$2:$B$97,B23)*INDEX(Scoring!$C$18:$C$27,MATCH(B23,Scoring!$B$18:$B$27,0))) -> 0 | V23: =IF(U23>0,U23+IF(AND(H23="Y",P23="No"),1000,0)+ROW()/100000,0) -> 0 | W23: NN/g: 10 usability heuristics | X23: https://www.nngroup.com/articles/ten-usability-heuristics/
A24: UXD-06 | B24: Usability and design | C24: Findability | D24: Can users find what they need - clear navigation, labels in users' language, and site search that returns relevant results? | E24: Yes / Partial / No / N/A | F24: Tree test or findability results; search analytics (top queries, zero-result searches). | G24: 2 | H24: N | I24: Structure navigation around user tasks, test it with users, and monitor search queries to improve labels and results. | J24: OMB M-23-22 (search pillar); Nielsen heuristic 2 | K24: M-23-22 | L24: Good practice | M24: All | P24: Partial | Q24: =IF(P24="Yes",Scoring!$C$6,IF(P24="Partial",Scoring!$C$7,IF(P24="No",Scoring!$C$8,""))) -> 0.5 | R24: =IF(Q24="",0,G24*Q24) -> 1 | S24: =IF(Q24="",0,G24) -> 2 | T24: =IF(OR(P24="Partial",P24="No"),I24,"") -> Structure navigation around user tasks, test it with users, and monitor search queries to improve labels and results. | U24: =IF(Q24="",0,(1-Q24)*G24/SUMIFS($S$2:$S$97,$B$2:$B$97,B24)*INDEX(Scoring!$C$18:$C$27,MATCH(B24,Scoring!$B$18:$B$27,0))) -> 0.65217391 | V24: =IF(U24>0,U24+IF(AND(H24="Y",P24="No"),1000,0)+ROW()/100000,0) -> 0.65241391 | W24: NN/g: 10 usability heuristics | X24: https://www.nngroup.com/articles/ten-usability-heuristics/
A25: UXD-07 | B25: Usability and design | C25: Errors | D25: Does the service prevent errors and help users recover - confirming destructive actions, saving progress, and explaining errors in plain language? | E25: Yes / Partial / No / N/A | F25: Error message inventory; save-and-return feature; confirmation patterns. | G25: 2 | H25: N | I25: Prevent common errors with good defaults and validation, let users save and return to long forms, and write error messages that say what went wrong and how to fix it. | J25: Nielsen heuristics 3, 5 and 9 | L25: Good practice | M25: Transactional | P25: Yes | Q25: =IF(P25="Yes",Scoring!$C$6,IF(P25="Partial",Scoring!$C$7,IF(P25="No",Scoring!$C$8,""))) -> 1 | R25: =IF(Q25="",0,G25*Q25) -> 2 | S25: =IF(Q25="",0,G25) -> 2 | T25: =IF(OR(P25="Partial",P25="No"),I25,"") | U25: =IF(Q25="",0,(1-Q25)*G25/SUMIFS($S$2:$S$97,$B$2:$B$97,B25)*INDEX(Scoring!$C$18:$C$27,MATCH(B25,Scoring!$B$18:$B$27,0))) -> 0 | V25: =IF(U25>0,U25+IF(AND(H25="Y",P25="No"),1000,0)+ROW()/100000,0) -> 0 | W25: NN/g: 10 usability heuristics | X25: https://www.nngroup.com/articles/ten-usability-heuristics/
A26: UXD-08 | B26: Usability and design | C26: Design system | D26: Is the service built using an established design system or pattern library (organisation or shared government) rather than one-off components? | E26: Yes / Partial / No / N/A | F26: Design system name and version; component usage audit. | G26: 2 | H26: N | I26: Use and contribute to a shared design system so components are tested, accessible and consistent across the organisation's services. | J26: GOV.UK Service Standard point 13; AU DSS 2.0 criterion 6 (don't reinvent the wheel) | L26: Good practice | M26: All | P26: No | Q26: =IF(P26="Yes",Scoring!$C$6,IF(P26="Partial",Scoring!$C$7,IF(P26="No",Scoring!$C$8,""))) -> 0 | R26: =IF(Q26="",0,G26*Q26) -> 0 | S26: =IF(Q26="",0,G26) -> 2 | T26: =IF(OR(P26="Partial",P26="No"),I26,"") -> Use and contribute to a shared design system so components are tested, accessible and consistent across the organisation's services. | U26: =IF(Q26="",0,(1-Q26)*G26/SUMIFS($S$2:$S$97,$B$2:$B$97,B26)*INDEX(Scoring!$C$18:$C$27,MATCH(B26,Scoring!$B$18:$B$27,0))) -> 1.3043478 | V26: =IF(U26>0,U26+IF(AND(H26="Y",P26="No"),1000,0)+ROW()/100000,0) -> 1.3046078 | W26: GOV.UK: reuse common components, patterns | X26: https://www.gov.uk/service-manual/service-standard/point-13-use-common-standards-components-patterns
A27: UXD-09 | B27: Usability and design | C27: Whole journey | D27: Has the end-to-end user journey been mapped, including offline steps, other agencies and hand-offs, and are pain points across channels addressed? | E27: Yes / Partial / No / N/A | F27: Journey or service blueprint; list of cross-channel issues and actions. | G27: 2 | H27: N | I27: Map the full journey across channels and organisations and design the digital service to work smoothly with the steps before and after it. | J27: GOV.UK Service Standard points 2 and 3; AU DSS 2.0 criterion 4 (connect services) | L27: Good practice | M27: All | P27: Yes | Q27: =IF(P27="Yes",Scoring!$C$6,IF(P27="Partial",Scoring!$C$7,IF(P27="No",Scoring!$C$8,""))) -> 1 | R27: =IF(Q27="",0,G27*Q27) -> 2 | S27: =IF(Q27="",0,G27) -> 2 | T27: =IF(OR(P27="Partial",P27="No"),I27,"") | U27: =IF(Q27="",0,(1-Q27)*G27/SUMIFS($S$2:$S$97,$B$2:$B$97,B27)*INDEX(Scoring!$C$18:$C$27,MATCH(B27,Scoring!$B$18:$B$27,0))) -> 0 | V27: =IF(U27>0,U27+IF(AND(H27="Y",P27="No"),1000,0)+ROW()/100000,0) -> 0 | W27: GOV.UK: solve a whole problem | X27: https://www.gov.uk/service-manual/service-standard/point-2-solve-a-whole-problem
A28: UXD-10 | B28: Usability and design | C28: Performance | D28: Do pages load and respond quickly on typical NZ mobile connections and devices, with front-end performance (for example Core Web Vitals) monitored? | E28: Yes / Partial / No / N/A | F28: Lighthouse or real-user monitoring results for key pages. | G28: 2 | H28: N | I28: Set performance budgets, monitor real-user performance (for example Core Web Vitals) and optimise key pages for mobile devices and slower connections. | J28: Google Core Web Vitals; OMB M-23-22 | L28: Good practice | M28: All | P28: Yes | Q28: =IF(P28="Yes",Scoring!$C$6,IF(P28="Partial",Scoring!$C$7,IF(P28="No",Scoring!$C$8,""))) -> 1 | R28: =IF(Q28="",0,G28*Q28) -> 2 | S28: =IF(Q28="",0,G28) -> 2 | T28: =IF(OR(P28="Partial",P28="No"),I28,"") | U28: =IF(Q28="",0,(1-Q28)*G28/SUMIFS($S$2:$S$97,$B$2:$B$97,B28)*INDEX(Scoring!$C$18:$C$27,MATCH(B28,Scoring!$B$18:$B$27,0))) -> 0 | V28: =IF(U28>0,U28+IF(AND(H28="Y",P28="No"),1000,0)+ROW()/100000,0) -> 0 | W28: Google: Core Web Vitals | X28: https://web.dev/articles/vitals
A29: UXD-11 | B29: Usability and design | C29: Compatibility | D29: Is there a defined browser, device and assistive technology support policy, and is the service tested against it before release? | E29: Yes / Partial / No / N/A | F29: Support policy; release test evidence. | G29: 1 | H29: N | I29: Define which browsers, devices and assistive technologies are supported based on user data, and test against that list before each release. | J29: GOV.UK Service Manual (designing for different browsers and devices) | L29: Good practice | M29: All | P29: Yes | Q29: =IF(P29="Yes",Scoring!$C$6,IF(P29="Partial",Scoring!$C$7,IF(P29="No",Scoring!$C$8,""))) -> 1 | R29: =IF(Q29="",0,G29*Q29) -> 1 | S29: =IF(Q29="",0,G29) -> 1 | T29: =IF(OR(P29="Partial",P29="No"),I29,"") | U29: =IF(Q29="",0,(1-Q29)*G29/SUMIFS($S$2:$S$97,$B$2:$B$97,B29)*INDEX(Scoring!$C$18:$C$27,MATCH(B29,Scoring!$B$18:$B$27,0))) -> 0 | V29: =IF(U29>0,U29+IF(AND(H29="Y",P29="No"),1000,0)+ROW()/100000,0) -> 0 | W29: GOV.UK: browser and device testing | X29: https://www.gov.uk/service-manual/technology/designing-for-different-browsers-and-devices
A30: UXD-12 | B30: Usability and design | C30: Data minimisation | D30: Does the service only ask for information it needs, and reuse information the agency already holds where lawful (so users don't repeat themselves)? | E30: Yes / Partial / No / N/A | F30: Field-by-field justification; data reuse arrangements. | G30: 1 | H30: N | I30: Remove questions that aren't needed, explain why information is asked for, and reuse information already held where the law allows. | J30: Privacy Act 2020 IPP 1; AU DSS 2.0 criterion 4 | K30: Privacy Act 2020 | L30: Recommended (NZ) | M30: Transactional | P30: Partial | Q30: =IF(P30="Yes",Scoring!$C$6,IF(P30="Partial",Scoring!$C$7,IF(P30="No",Scoring!$C$8,""))) -> 0.5 | R30: =IF(Q30="",0,G30*Q30) -> 0.5 | S30: =IF(Q30="",0,G30) -> 1 | T30: =IF(OR(P30="Partial",P30="No"),I30,"") -> Remove questions that aren't needed, explain why information is asked for, and reuse information already held where the law allows. | U30: =IF(Q30="",0,(1-Q30)*G30/SUMIFS($S$2:$S$97,$B$2:$B$97,B30)*INDEX(Scoring!$C$18:$C$27,MATCH(B30,Scoring!$B$18:$B$27,0))) -> 0.32608696 | V30: =IF(U30>0,U30+IF(AND(H30="Y",P30="No"),1000,0)+ROW()/100000,0) -> 0.32638696 | W30: Privacy Act 2020 | X30: https://www.legislation.govt.nz/act/public/2020/31/en/latest/
A31: CON-01 | B31: Content and tone of voice | C31: Plain language | D31: Is content written in plain language appropriate to the intended audience, and has it been checked (for example readability testing or user testing)? | E31: Yes / Partial / No / N/A | F31: Content review results; readability scores; plain language checks. | G31: 3 | H31: N | I31: Write and review all public content in plain language, test it with users, and follow the agency's Plain Language Act processes. | J31: Plain Language Act 2022 | K31: Plain Language Act 2022 | L31: Mandatory (NZ) | M31: Public-facing | N31: Applies to public service agencies and Crown agents. A Plain Language Act Repeal Bill was introduced in 2025 (first reading 1 Apr 2025) and had not been enacted at 24 Oct 2026. If the Act is repealed, change NZ status to Good practice and keep the criterion. | P31: Yes | Q31: =IF(P31="Yes",Scoring!$C$6,IF(P31="Partial",Scoring!$C$7,IF(P31="No",Scoring!$C$8,""))) -> 1 | R31: =IF(Q31="",0,G31*Q31) -> 3 | S31: =IF(Q31="",0,G31) -> 3 | T31: =IF(OR(P31="Partial",P31="No"),I31,"") | U31: =IF(Q31="",0,(1-Q31)*G31/SUMIFS($S$2:$S$97,$B$2:$B$97,B31)*INDEX(Scoring!$C$18:$C$27,MATCH(B31,Scoring!$B$18:$B$27,0))) -> 0 | V31: =IF(U31>0,U31+IF(AND(H31="Y",P31="No"),1000,0)+ROW()/100000,0) -> 0 | W31: Plain Language Act 2022 | X31: https://www.legislation.govt.nz/act/public/2022/0054/latest/whole.html
A32: CON-02 | B32: Content and tone of voice | C32: Tone of voice | D32: Does the organisation have tone of voice guidelines, and does the service's content follow them? | E32: Yes / Partial / No / N/A | F32: Tone of voice guidelines; content review against them. | G32: 2 | H32: N | I32: Apply the organisation's tone of voice guidelines to all service content, including error messages, emails and letters, and review content against them. | J32: Organisation brand and tone of voice guidelines | K32: Organisation-specific | L32: Good practice | M32: All | N32: Organisation supplies its own guideline reference. | P32: No | Q32: =IF(P32="Yes",Scoring!$C$6,IF(P32="Partial",Scoring!$C$7,IF(P32="No",Scoring!$C$8,""))) -> 0 | R32: =IF(Q32="",0,G32*Q32) -> 0 | S32: =IF(Q32="",0,G32) -> 2 | T32: =IF(OR(P32="Partial",P32="No"),I32,"") -> Apply the organisation's tone of voice guidelines to all service content, including error messages, emails and letters, and review content against them. | U32: =IF(Q32="",0,(1-Q32)*G32/SUMIFS($S$2:$S$97,$B$2:$B$97,B32)*INDEX(Scoring!$C$18:$C$27,MATCH(B32,Scoring!$B$18:$B$27,0))) -> 1.3333333 | V32: =IF(U32>0,U32+IF(AND(H32="Y",P32="No"),1000,0)+ROW()/100000,0) -> 1.3336533 | W32: Use your organisation's tone of voice
A33: CON-03 | B33: Content and tone of voice | C33: Style | D33: Is content consistent with a content style guide (NZ English, terminology, dates, numbers, capitalisation)? | E33: Yes / Partial / No / N/A | F33: Style guide reference; content audit results. | G33: 1 | H33: N | I33: Adopt a content style guide (organisation or NZ Government) and apply it consistently, including a glossary of service terms. | J33: Organisation style guide; NZ Government content guidance (Digital.govt.nz) | L33: Good practice | M33: All | P33: Yes | Q33: =IF(P33="Yes",Scoring!$C$6,IF(P33="Partial",Scoring!$C$7,IF(P33="No",Scoring!$C$8,""))) -> 1 | R33: =IF(Q33="",0,G33*Q33) -> 1 | S33: =IF(Q33="",0,G33) -> 1 | T33: =IF(OR(P33="Partial",P33="No"),I33,"") | U33: =IF(Q33="",0,(1-Q33)*G33/SUMIFS($S$2:$S$97,$B$2:$B$97,B33)*INDEX(Scoring!$C$18:$C$27,MATCH(B33,Scoring!$B$18:$B$27,0))) -> 0 | V33: =IF(U33>0,U33+IF(AND(H33="Y",P33="No"),1000,0)+ROW()/100000,0) -> 0 | W33: Use your organisation's style guide
A34: CON-04 | B34: Content and tone of voice | C34: Accuracy | D34: Is service content authoritative and current, with no duplicate or conflicting information across the agency's channels? | E34: Yes / Partial / No / N/A | F34: Content inventory; duplicate content review. | G34: 2 | H34: N | I34: Keep one authoritative source for each piece of service information, remove or redirect duplicates, and check consistency with call centre scripts and printed material. | J34: OMB M-23-22 (content pillar) | L34: Good practice | M34: All | P34: Partial | Q34: =IF(P34="Yes",Scoring!$C$6,IF(P34="Partial",Scoring!$C$7,IF(P34="No",Scoring!$C$8,""))) -> 0.5 | R34: =IF(Q34="",0,G34*Q34) -> 1 | S34: =IF(Q34="",0,G34) -> 2 | T34: =IF(OR(P34="Partial",P34="No"),I34,"") -> Keep one authoritative source for each piece of service information, remove or redirect duplicates, and check consistency with call centre scripts and printed material. | U34: =IF(Q34="",0,(1-Q34)*G34/SUMIFS($S$2:$S$97,$B$2:$B$97,B34)*INDEX(Scoring!$C$18:$C$27,MATCH(B34,Scoring!$B$18:$B$27,0))) -> 0.66666667 | V34: =IF(U34>0,U34+IF(AND(H34="Y",P34="No"),1000,0)+ROW()/100000,0) -> 0.66700667 | W34: US digital-first experience memo | X34: https://www.whitehouse.gov/wp-content/uploads/2023/09/M-23-22-Delivering-a-Digital-First-Public-Experience.pdf
A35: CON-05 | B35: Content and tone of voice | C35: Links and labels | D35: Are buttons, links and labels clear and specific (no 'click here'), and has microcopy been tested with users? | E35: Yes / Partial / No / N/A | F35: Audit findings for SC 2.4.4; microcopy test results. | G35: 1 | H35: N | I35: Write descriptive link text and button labels that make sense out of context, and test key microcopy with users. | J35: WCAG 2.2 SC 2.4.4, 2.4.6 | K35: WCAG 2.2 A/AA | L35: Mandatory (NZ) | M35: All | P35: Yes | Q35: =IF(P35="Yes",Scoring!$C$6,IF(P35="Partial",Scoring!$C$7,IF(P35="No",Scoring!$C$8,""))) -> 1 | R35: =IF(Q35="",0,G35*Q35) -> 1 | S35: =IF(Q35="",0,G35) -> 1 | T35: =IF(OR(P35="Partial",P35="No"),I35,"") | U35: =IF(Q35="",0,(1-Q35)*G35/SUMIFS($S$2:$S$97,$B$2:$B$97,B35)*INDEX(Scoring!$C$18:$C$27,MATCH(B35,Scoring!$B$18:$B$27,0))) -> 0 | V35: =IF(U35>0,U35+IF(AND(H35="Y",P35="No"),1000,0)+ROW()/100000,0) -> 0 | W35: WCAG 2.2 quick reference | X35: https://www.w3.org/WAI/WCAG22/quickref/
A36: CON-06 | B36: Content and tone of voice | C36: Te reo Māori | D36: Has the service considered te reo Māori - correct use and display of macrons, bilingual names and content where appropriate? | E36: Yes / Partial / No / N/A | F36: Te reo Māori approach; macron rendering test; reviewed translations. | G36: 1 | H36: N | I36: Agree a te reo Māori approach for the service, ensure macrons display and are searchable, and have te reo content reviewed by a qualified speaker. | J36: Te Ture mō Te Reo Māori 2016 (Māori Language Act); Digital Service Design Standard | L36: Recommended (NZ) | M36: All | P36: Yes | Q36: =IF(P36="Yes",Scoring!$C$6,IF(P36="Partial",Scoring!$C$7,IF(P36="No",Scoring!$C$8,""))) -> 1 | R36: =IF(Q36="",0,G36*Q36) -> 1 | S36: =IF(Q36="",0,G36) -> 1 | T36: =IF(OR(P36="Partial",P36="No"),I36,"") | U36: =IF(Q36="",0,(1-Q36)*G36/SUMIFS($S$2:$S$97,$B$2:$B$97,B36)*INDEX(Scoring!$C$18:$C$27,MATCH(B36,Scoring!$B$18:$B$27,0))) -> 0 | V36: =IF(U36>0,U36+IF(AND(H36="Y",P36="No"),1000,0)+ROW()/100000,0) -> 0 | W36: Māori Language Act 2016 | X36: https://www.legislation.govt.nz/act/public/2016/0017/latest/DLM6174566.html
A37: CON-07 | B37: Content and tone of voice | C37: Alternative formats | D37: Is key service information available in alternative formats where needed (for example Easy Read, NZ Sign Language, large print, audio, Braille)? | E37: Yes / Partial / No / N/A | F37: List of alternative formats; process for requesting them. | G37: 1 | H37: N | I37: Provide key information in alternative formats and offer a simple way to request others. | J37: Accessibility Charter (MSD); draft Digital Accessibility Standard | K37: DAS draft (Jul 2026) | L37: Recommended (NZ) | M37: Public-facing | P37: Partial | Q37: =IF(P37="Yes",Scoring!$C$6,IF(P37="Partial",Scoring!$C$7,IF(P37="No",Scoring!$C$8,""))) -> 0.5 | R37: =IF(Q37="",0,G37*Q37) -> 0.5 | S37: =IF(Q37="",0,G37) -> 1 | T37: =IF(OR(P37="Partial",P37="No"),I37,"") -> Provide key information in alternative formats and offer a simple way to request others. | U37: =IF(Q37="",0,(1-Q37)*G37/SUMIFS($S$2:$S$97,$B$2:$B$97,B37)*INDEX(Scoring!$C$18:$C$27,MATCH(B37,Scoring!$B$18:$B$27,0))) -> 0.33333333 | V37: =IF(U37>0,U37+IF(AND(H37="Y",P37="No"),1000,0)+ROW()/100000,0) -> 0.33370333 | W37: MSD Accessibility Charter | X37: https://www.msd.govt.nz/about-msd-and-our-work/work-programmes/accessibility/accessibility-charter/the-charter.html
A38: CON-08 | B38: Content and tone of voice | C38: Languages | D38: Have the language needs of the service's users been identified, with translated content provided where needed? | E38: Yes / Partial / No / N/A | F38: User language data; translated content inventory. | G38: 1 | H38: N | I38: Use research and demographic data to identify language needs and translate key content, using professional translators. | J38: Digital Service Design Standard | L38: Good practice | M38: Public-facing | P38: Yes | Q38: =IF(P38="Yes",Scoring!$C$6,IF(P38="Partial",Scoring!$C$7,IF(P38="No",Scoring!$C$8,""))) -> 1 | R38: =IF(Q38="",0,G38*Q38) -> 1 | S38: =IF(Q38="",0,G38) -> 1 | T38: =IF(OR(P38="Partial",P38="No"),I38,"") | U38: =IF(Q38="",0,(1-Q38)*G38/SUMIFS($S$2:$S$97,$B$2:$B$97,B38)*INDEX(Scoring!$C$18:$C$27,MATCH(B38,Scoring!$B$18:$B$27,0))) -> 0 | V38: =IF(U38>0,U38+IF(AND(H38="Y",P38="No"),1000,0)+ROW()/100000,0) -> 0 | W38: NZ Digital Service Design principles | X38: https://www.digital.govt.nz/standards-and-guidance/digital-service-design-standard/principles
A39: BRD-01 | B39: Brand and visual consistency | C39: Brand guidelines | D39: Does the service apply the organisation's brand guidelines - logos, font types, colour palette, iconography and styling? | E39: Yes / Partial / No / N/A | F39: Brand guideline reference; design review against guidelines. | G39: 3 | H39: N | I39: Apply the organisation's brand guidelines, including font types, colour palette and styling, to minimise experience inconsistency across applications. | J39: Organisation brand guidelines; OMB M-23-22 (branding pillar) | K39: Organisation-specific | L39: Good practice | M39: All | P39: No | Q39: =IF(P39="Yes",Scoring!$C$6,IF(P39="Partial",Scoring!$C$7,IF(P39="No",Scoring!$C$8,""))) -> 0 | R39: =IF(Q39="",0,G39*Q39) -> 0 | S39: =IF(Q39="",0,G39) -> 3 | T39: =IF(OR(P39="Partial",P39="No"),I39,"") -> Apply the organisation's brand guidelines, including font types, colour palette and styling, to minimise experience inconsistency across applications. | U39: =IF(Q39="",0,(1-Q39)*G39/SUMIFS($S$2:$S$97,$B$2:$B$97,B39)*INDEX(Scoring!$C$18:$C$27,MATCH(B39,Scoring!$B$18:$B$27,0))) -> 1.5 | V39: =IF(U39>0,U39+IF(AND(H39="Y",P39="No"),1000,0)+ROW()/100000,0) -> 1.50039 | W39: Use your organisation's brand guidelines
A40: BRD-02 | B40: Brand and visual consistency | C40: Government identity | D40: Does the website's home page clearly identify it as a NZ Government site and link to Govt.nz using the recommended NZ Government logo markup? | E40: Yes / Partial / No / N/A | F40: Screenshot of home page; markup check. | G40: 2 | H40: N | I40: Add the NZ Government identity link to Govt.nz on the home page using the recommended accessible logo markup. | J40: Web Usability Standard 1.4 s2.2 (Government identity); NZ government logo markup guidance | K40: WUS 1.4 (from 17 Mar 2025) | L40: Mandatory (NZ) | M40: Public-facing | N40: Web Usability Standard requirements are expected to become guidance within the updated Digital Service Design Standard. | P40: Yes | Q40: =IF(P40="Yes",Scoring!$C$6,IF(P40="Partial",Scoring!$C$7,IF(P40="No",Scoring!$C$8,""))) -> 1 | R40: =IF(Q40="",0,G40*Q40) -> 2 | S40: =IF(Q40="",0,G40) -> 2 | T40: =IF(OR(P40="Partial",P40="No"),I40,"") | U40: =IF(Q40="",0,(1-Q40)*G40/SUMIFS($S$2:$S$97,$B$2:$B$97,B40)*INDEX(Scoring!$C$18:$C$27,MATCH(B40,Scoring!$B$18:$B$27,0))) -> 0 | V40: =IF(U40>0,U40+IF(AND(H40="Y",P40="No"),1000,0)+ROW()/100000,0) -> 0 | W40: NZ government logo markup guidance | X40: https://www.digital.govt.nz/standards-and-guidance/design-and-ux/usability/nz-government-logo-markup
A41: BRD-03 | B41: Brand and visual consistency | C41: Accessible brand | D41: Has the brand colour palette and typography been checked for accessibility (contrast, legibility at small sizes)? | E41: Yes / Partial / No / N/A | F41: Contrast matrix for brand colours; typography test. | G41: 2 | H41: N | I41: Test the brand palette and type scale against WCAG and publish approved accessible colour combinations in the design system. | J41: WCAG 2.2 SC 1.4.3, 1.4.11 | K41: WCAG 2.2 AA | L41: Recommended (NZ) | M41: All | P41: Yes | Q41: =IF(P41="Yes",Scoring!$C$6,IF(P41="Partial",Scoring!$C$7,IF(P41="No",Scoring!$C$8,""))) -> 1 | R41: =IF(Q41="",0,G41*Q41) -> 2 | S41: =IF(Q41="",0,G41) -> 2 | T41: =IF(OR(P41="Partial",P41="No"),I41,"") | U41: =IF(Q41="",0,(1-Q41)*G41/SUMIFS($S$2:$S$97,$B$2:$B$97,B41)*INDEX(Scoring!$C$18:$C$27,MATCH(B41,Scoring!$B$18:$B$27,0))) -> 0 | V41: =IF(U41>0,U41+IF(AND(H41="Y",P41="No"),1000,0)+ROW()/100000,0) -> 0 | W41: WCAG 2.2 quick reference | X41: https://www.w3.org/WAI/WCAG22/quickref/
A42: BRD-04 | B42: Brand and visual consistency | C42: Consistency | D42: Is the look, feel and interaction behaviour consistent with the organisation's other digital services (shared components, design tokens, patterns)? | E42: Yes / Partial / No / N/A | F42: Comparison with other agency services; shared design token usage. | G42: 2 | H42: N | I42: Use shared design tokens and components across the organisation's applications so users get a consistent experience. | J42: Nielsen heuristic 4 (consistency and standards); OMB M-23-22 | L42: Good practice | M42: All | P42: Yes | Q42: =IF(P42="Yes",Scoring!$C$6,IF(P42="Partial",Scoring!$C$7,IF(P42="No",Scoring!$C$8,""))) -> 1 | R42: =IF(Q42="",0,G42*Q42) -> 2 | S42: =IF(Q42="",0,G42) -> 2 | T42: =IF(OR(P42="Partial",P42="No"),I42,"") | U42: =IF(Q42="",0,(1-Q42)*G42/SUMIFS($S$2:$S$97,$B$2:$B$97,B42)*INDEX(Scoring!$C$18:$C$27,MATCH(B42,Scoring!$B$18:$B$27,0))) -> 0 | V42: =IF(U42>0,U42+IF(AND(H42="Y",P42="No"),1000,0)+ROW()/100000,0) -> 0 | W42: NN/g: 10 usability heuristics | X42: https://www.nngroup.com/articles/ten-usability-heuristics/
A43: BRD-05 | B43: Brand and visual consistency | C43: Trust | D43: Is the service hosted on a .govt.nz domain (or another approved domain) that clearly identifies the agency, so users can trust it is genuine? | E43: Yes / Partial / No / N/A | F43: Domain name and approval. | G43: 2 | H43: N | I43: Host the service on a .govt.nz or other approved government domain and avoid third-party domains that could be mistaken for scams. | J43: Government domain names guidance (digital.govt.nz) | L43: Recommended (NZ) | M43: Public-facing | P43: Partial | Q43: =IF(P43="Yes",Scoring!$C$6,IF(P43="Partial",Scoring!$C$7,IF(P43="No",Scoring!$C$8,""))) -> 0.5 | R43: =IF(Q43="",0,G43*Q43) -> 1 | S43: =IF(Q43="",0,G43) -> 2 | T43: =IF(OR(P43="Partial",P43="No"),I43,"") -> Host the service on a .govt.nz or other approved government domain and avoid third-party domains that could be mistaken for scams. | U43: =IF(Q43="",0,(1-Q43)*G43/SUMIFS($S$2:$S$97,$B$2:$B$97,B43)*INDEX(Scoring!$C$18:$C$27,MATCH(B43,Scoring!$B$18:$B$27,0))) -> 0.5 | V43: =IF(U43>0,U43+IF(AND(H43="Y",P43="No"),1000,0)+ROW()/100000,0) -> 0.50043 | W43: NZ government domain names guidance | X43: https://www.digital.govt.nz/standards-and-guidance/technology-and-architecture/domain-names
A44: BRD-06 | B44: Brand and visual consistency | C44: Machinery of government | D44: Where the organisation has been renamed, merged or restructured, have legacy names, logos and URLs been updated or redirected? | E44: Yes / Partial / No / N/A | F44: Inventory of legacy brand references; redirect map. | G44: 1 | H44: N | I44: Update legacy names, logos and contact details, and redirect old URLs so users are not confused after machinery-of-government changes. | J44: Good practice | L44: Good practice | M44: All | P44: Yes | Q44: =IF(P44="Yes",Scoring!$C$6,IF(P44="Partial",Scoring!$C$7,IF(P44="No",Scoring!$C$8,""))) -> 1 | R44: =IF(Q44="",0,G44*Q44) -> 1 | S44: =IF(Q44="",0,G44) -> 1 | T44: =IF(OR(P44="Partial",P44="No"),I44,"") | U44: =IF(Q44="",0,(1-Q44)*G44/SUMIFS($S$2:$S$97,$B$2:$B$97,B44)*INDEX(Scoring!$C$18:$C$27,MATCH(B44,Scoring!$B$18:$B$27,0))) -> 0 | V44: =IF(U44>0,U44+IF(AND(H44="Y",P44="No"),1000,0)+ROW()/100000,0) -> 0 | W44: NZ government domain names guidance | X44: https://www.digital.govt.nz/standards-and-guidance/technology-and-architecture/domain-names
A45: SEC-01 | B45: Security and privacy | C45: Assurance | D45: Has the service completed a security risk assessment and certification and accreditation (C&A) in line with the NZISM, and is it reviewed after significant change? | E45: Yes / Partial / No / N/A | F45: C&A documentation; risk register; accreditation decision. | G45: 3 | H45: Y | I45: Complete a security risk assessment and certification and accreditation before go-live, and refresh it after significant change or on a set cycle. | J45: NZ Information Security Manual (NZISM); Protective Security Requirements | K45: NZISM (v3.9 released; check latest updates); PSR | L45: Mandatory (NZ) | M45: All | N45: Check current NZISM version and your organisation's PSR obligations. | P45: Partial | Q45: =IF(P45="Yes",Scoring!$C$6,IF(P45="Partial",Scoring!$C$7,IF(P45="No",Scoring!$C$8,""))) -> 0.5 | R45: =IF(Q45="",0,G45*Q45) -> 1.5 | S45: =IF(Q45="",0,G45) -> 3 | T45: =IF(OR(P45="Partial",P45="No"),I45,"") -> Complete a security risk assessment and certification and accreditation before go-live, and refresh it after significant change or on a set cycle. | U45: =IF(Q45="",0,(1-Q45)*G45/SUMIFS($S$2:$S$97,$B$2:$B$97,B45)*INDEX(Scoring!$C$18:$C$27,MATCH(B45,Scoring!$B$18:$B$27,0))) -> 0.875 | V45: =IF(U45>0,U45+IF(AND(H45="Y",P45="No"),1000,0)+ROW()/100000,0) -> 0.87545 | W45: NZ Information Security Manual | X45: https://www.ncsc.govt.nz/nzism/
A46: SEC-02 | B46: Security and privacy | C46: Application security | D46: Has the application been verified against the OWASP Application Security Verification Standard at a level appropriate to its risk (Level 1 minimum, Level 2 if it handles personal information)? | E46: Yes / Partial / No / N/A | F46: ASVS checklist results with level stated. | G46: 3 | H46: N | I46: Verify the application against OWASP ASVS 5.0 at the appropriate level and track gaps to remediation. | J46: OWASP ASVS 5.0.0 (chapters V1-V17, at the level chosen) | K46: ASVS 5.0.0 (May 2025) | L46: Good practice | M46: All | N46: OWASP ASVS is referenced by chapter ID only. No ASVS requirement text is reproduced (ASVS is CC BY-SA 4.0). In the app, cite requirement IDs in the form v5.0.0-<chapter>.<section>.<requirement>. | P46: Yes | Q46: =IF(P46="Yes",Scoring!$C$6,IF(P46="Partial",Scoring!$C$7,IF(P46="No",Scoring!$C$8,""))) -> 1 | R46: =IF(Q46="",0,G46*Q46) -> 3 | S46: =IF(Q46="",0,G46) -> 3 | T46: =IF(OR(P46="Partial",P46="No"),I46,"") | U46: =IF(Q46="",0,(1-Q46)*G46/SUMIFS($S$2:$S$97,$B$2:$B$97,B46)*INDEX(Scoring!$C$18:$C$27,MATCH(B46,Scoring!$B$18:$B$27,0))) -> 0 | V46: =IF(U46>0,U46+IF(AND(H46="Y",P46="No"),1000,0)+ROW()/100000,0) -> 0 | W46: OWASP ASVS project page | X46: https://owasp.org/projects/asvs
A47: SEC-03 | B47: Security and privacy | C47: Testing | D47: Has an independent penetration test been completed in the last 12 months or since the last major change, with findings remediated? | E47: Yes / Partial / No / N/A | F47: Pen test report; remediation tracker. | G47: 2 | H47: N | I47: Commission independent penetration testing annually and after major change, and remediate critical and high findings before release. | J47: NZISM | L47: Recommended (NZ) | M47: All | P47: Partial | Q47: =IF(P47="Yes",Scoring!$C$6,IF(P47="Partial",Scoring!$C$7,IF(P47="No",Scoring!$C$8,""))) -> 0.5 | R47: =IF(Q47="",0,G47*Q47) -> 1 | S47: =IF(Q47="",0,G47) -> 2 | T47: =IF(OR(P47="Partial",P47="No"),I47,"") -> Commission independent penetration testing annually and after major change, and remediate critical and high findings before release. | U47: =IF(Q47="",0,(1-Q47)*G47/SUMIFS($S$2:$S$97,$B$2:$B$97,B47)*INDEX(Scoring!$C$18:$C$27,MATCH(B47,Scoring!$B$18:$B$27,0))) -> 0.58333333 | V47: =IF(U47>0,U47+IF(AND(H47="Y",P47="No"),1000,0)+ROW()/100000,0) -> 0.58380333 | W47: NZ Information Security Manual | X47: https://www.ncsc.govt.nz/nzism/
A48: SEC-04 | B48: Security and privacy | C48: Transport security | D48: Is the service served only over HTTPS with modern TLS, HSTS and appropriate security headers (for example Content Security Policy)? | E48: Yes / Partial / No / N/A | F48: MDN HTTP Observatory and SSL Labs results. | G48: 2 | H48: N | I48: Enforce HTTPS with modern TLS, enable HSTS and configure security headers, checking regularly with free scanners such as MDN HTTP Observatory and SSL Labs. | J48: NZISM; OWASP ASVS 5.0.0 V12 (Secure Communication) and V3 (Web Frontend Security) | K48: ASVS 5.0.0 | L48: Recommended (NZ) | M48: All | N48: OWASP ASVS is referenced by chapter ID only. No ASVS requirement text is reproduced (ASVS is CC BY-SA 4.0). In the app, cite requirement IDs in the form v5.0.0-<chapter>.<section>.<requirement>. | P48: Yes | Q48: =IF(P48="Yes",Scoring!$C$6,IF(P48="Partial",Scoring!$C$7,IF(P48="No",Scoring!$C$8,""))) -> 1 | R48: =IF(Q48="",0,G48*Q48) -> 2 | S48: =IF(Q48="",0,G48) -> 2 | T48: =IF(OR(P48="Partial",P48="No"),I48,"") | U48: =IF(Q48="",0,(1-Q48)*G48/SUMIFS($S$2:$S$97,$B$2:$B$97,B48)*INDEX(Scoring!$C$18:$C$27,MATCH(B48,Scoring!$B$18:$B$27,0))) -> 0 | V48: =IF(U48>0,U48+IF(AND(H48="Y",P48="No"),1000,0)+ROW()/100000,0) -> 0 | W48: MDN HTTP Observatory scanner | X48: https://developer.mozilla.org/en-US/observatory
A49: SEC-05 | B49: Security and privacy | C49: Identity | D49: Is user authentication proportionate to risk (for example multi-factor authentication, RealMe or another trusted identity service) and is MFA required for administrators? | E49: Yes / Partial / No / N/A | F49: Authentication design; identity assurance assessment. | G49: 2 | H49: N | I49: Match authentication strength to the risk of the transaction, use trusted identity services where appropriate, and require MFA for all administrative access. | J49: NZ Government Identification Standards; RealMe; NZISM; OWASP ASVS 5.0.0 V6 (Authentication) and V7 (Session Management) | K49: ASVS 5.0.0 | L49: Recommended (NZ) | M49: Authenticated | N49: OWASP ASVS is referenced by chapter ID only. No ASVS requirement text is reproduced (ASVS is CC BY-SA 4.0). In the app, cite requirement IDs in the form v5.0.0-<chapter>.<section>.<requirement>. | P49: Yes | Q49: =IF(P49="Yes",Scoring!$C$6,IF(P49="Partial",Scoring!$C$7,IF(P49="No",Scoring!$C$8,""))) -> 1 | R49: =IF(Q49="",0,G49*Q49) -> 2 | S49: =IF(Q49="",0,G49) -> 2 | T49: =IF(OR(P49="Partial",P49="No"),I49,"") | U49: =IF(Q49="",0,(1-Q49)*G49/SUMIFS($S$2:$S$97,$B$2:$B$97,B49)*INDEX(Scoring!$C$18:$C$27,MATCH(B49,Scoring!$B$18:$B$27,0))) -> 0 | V49: =IF(U49>0,U49+IF(AND(H49="Y",P49="No"),1000,0)+ROW()/100000,0) -> 0 | W49: NZ Identification Standards | X49: https://www.digital.govt.nz/standards-and-guidance/identity/identification-management/identification-standards
A50: SEC-06 | B50: Security and privacy | C50: Privacy | D50: Has a privacy impact assessment (PIA) been completed and kept up to date for the service? | E50: Yes / Partial / No / N/A | F50: PIA document and approval. | G50: 2 | H50: N | I50: Complete a privacy impact assessment and update it whenever the collection, use or sharing of personal information changes. | J50: Privacy Act 2020; Office of the Privacy Commissioner PIA guidance | K50: Privacy Act 2020 | L50: Recommended (NZ) | M50: All | P50: Partial | Q50: =IF(P50="Yes",Scoring!$C$6,IF(P50="Partial",Scoring!$C$7,IF(P50="No",Scoring!$C$8,""))) -> 0.5 | R50: =IF(Q50="",0,G50*Q50) -> 1 | S50: =IF(Q50="",0,G50) -> 2 | T50: =IF(OR(P50="Partial",P50="No"),I50,"") -> Complete a privacy impact assessment and update it whenever the collection, use or sharing of personal information changes. | U50: =IF(Q50="",0,(1-Q50)*G50/SUMIFS($S$2:$S$97,$B$2:$B$97,B50)*INDEX(Scoring!$C$18:$C$27,MATCH(B50,Scoring!$B$18:$B$27,0))) -> 0.58333333 | V50: =IF(U50>0,U50+IF(AND(H50="Y",P50="No"),1000,0)+ROW()/100000,0) -> 0.58383333 | W50: OPC privacy impact assessment guidance | X50: https://www.privacy.org.nz/responsibilities/privacy-impact-assessments/
A51: SEC-07 | B51: Security and privacy | C51: Privacy | D51: Is a privacy statement available from every page, explaining what personal information is collected, why, who it's shared with, and how to access and correct it? | E51: Yes / Partial / No / N/A | F51: Privacy statement URL; check it is linked from all pages. | G51: 3 | H51: Y | I51: Publish a clear privacy statement linked from every page that meets Privacy Act 2020 information privacy principle 3 and the Web Usability Standard. | J51: Privacy Act 2020 IPP 3; Web Usability Standard 1.4 s2.5 (Privacy) | K51: Privacy Act 2020; WUS 1.4 | L51: Mandatory (NZ) | M51: All | N51: Weight raised to 3 in v1.10: the privacy statement is a legal obligation and a critical criterion. | P51: Yes | Q51: =IF(P51="Yes",Scoring!$C$6,IF(P51="Partial",Scoring!$C$7,IF(P51="No",Scoring!$C$8,""))) -> 1 | R51: =IF(Q51="",0,G51*Q51) -> 3 | S51: =IF(Q51="",0,G51) -> 3 | T51: =IF(OR(P51="Partial",P51="No"),I51,"") | U51: =IF(Q51="",0,(1-Q51)*G51/SUMIFS($S$2:$S$97,$B$2:$B$97,B51)*INDEX(Scoring!$C$18:$C$27,MATCH(B51,Scoring!$B$18:$B$27,0))) -> 0 | V51: =IF(U51>0,U51+IF(AND(H51="Y",P51="No"),1000,0)+ROW()/100000,0) -> 0 | W51: NZ Web Usability Standard 1.4 | X51: https://www.digital.govt.nz/standards-and-guidance/nz-government-web-standards/web-usability-standard-1-4
A52: SEC-08 | B52: Security and privacy | C52: Privacy | D52: Is there a tested process for responding to privacy breaches, including notifying the Privacy Commissioner and affected people where required? | E52: Yes / Partial / No / N/A | F52: Breach response procedure; exercise records. | G52: 2 | H52: N | I52: Document and exercise a privacy breach response process that meets the notifiable privacy breach requirements of the Privacy Act 2020. | J52: Privacy Act 2020 Part 6 | K52: Privacy Act 2020 | L52: Mandatory (NZ) | M52: All | P52: No | Q52: =IF(P52="Yes",Scoring!$C$6,IF(P52="Partial",Scoring!$C$7,IF(P52="No",Scoring!$C$8,""))) -> 0 | R52: =IF(Q52="",0,G52*Q52) -> 0 | S52: =IF(Q52="",0,G52) -> 2 | T52: =IF(OR(P52="Partial",P52="No"),I52,"") -> Document and exercise a privacy breach response process that meets the notifiable privacy breach requirements of the Privacy Act 2020. | U52: =IF(Q52="",0,(1-Q52)*G52/SUMIFS($S$2:$S$97,$B$2:$B$97,B52)*INDEX(Scoring!$C$18:$C$27,MATCH(B52,Scoring!$B$18:$B$27,0))) -> 1.1666667 | V52: =IF(U52>0,U52+IF(AND(H52="Y",P52="No"),1000,0)+ROW()/100000,0) -> 1.1671867 | W52: Privacy Act 2020 | X52: https://www.legislation.govt.nz/act/public/2020/31/en/latest/
A53: SEC-09 | B53: Security and privacy | C53: Vulnerabilities | D53: Are vulnerabilities and dependencies scanned regularly and patched within defined timeframes? | E53: Yes / Partial / No / N/A | F53: Scan reports; patching SLAs and performance. | G53: 2 | H53: N | I53: Scan code, dependencies and infrastructure continuously and patch within agreed timeframes based on severity. | J53: NZISM; OWASP ASVS 5.0.0 V15 (Secure Coding and Architecture) | K53: ASVS 5.0.0 | L53: Recommended (NZ) | M53: All | N53: OWASP ASVS is referenced by chapter ID only. No ASVS requirement text is reproduced (ASVS is CC BY-SA 4.0). In the app, cite requirement IDs in the form v5.0.0-<chapter>.<section>.<requirement>. | P53: Yes | Q53: =IF(P53="Yes",Scoring!$C$6,IF(P53="Partial",Scoring!$C$7,IF(P53="No",Scoring!$C$8,""))) -> 1 | R53: =IF(Q53="",0,G53*Q53) -> 2 | S53: =IF(Q53="",0,G53) -> 2 | T53: =IF(OR(P53="Partial",P53="No"),I53,"") | U53: =IF(Q53="",0,(1-Q53)*G53/SUMIFS($S$2:$S$97,$B$2:$B$97,B53)*INDEX(Scoring!$C$18:$C$27,MATCH(B53,Scoring!$B$18:$B$27,0))) -> 0 | V53: =IF(U53>0,U53+IF(AND(H53="Y",P53="No"),1000,0)+ROW()/100000,0) -> 0 | W53: OWASP ASVS project page | X53: https://owasp.org/projects/asvs
A54: SEC-10 | B54: Security and privacy | C54: Security monitoring | D54: Are security events logged and monitored, with alerts for suspicious activity, without logging sensitive personal information? | E54: Yes / Partial / No / N/A | F54: Logging standard; security monitoring and alerting configuration. | G54: 2 | H54: N | I54: Log security-relevant events centrally, alert on suspicious activity, and make sure logs don't contain passwords, tokens or unnecessary personal information. | J54: OWASP ASVS 5.0.0 V16 (Security Logging and Error Handling); NZISM | K54: ASVS 5.0.0 | L54: Good practice | M54: All | N54: OWASP ASVS is referenced by chapter ID only. No ASVS requirement text is reproduced (ASVS is CC BY-SA 4.0). In the app, cite requirement IDs in the form v5.0.0-<chapter>.<section>.<requirement>. | P54: Yes | Q54: =IF(P54="Yes",Scoring!$C$6,IF(P54="Partial",Scoring!$C$7,IF(P54="No",Scoring!$C$8,""))) -> 1 | R54: =IF(Q54="",0,G54*Q54) -> 2 | S54: =IF(Q54="",0,G54) -> 2 | T54: =IF(OR(P54="Partial",P54="No"),I54,"") | U54: =IF(Q54="",0,(1-Q54)*G54/SUMIFS($S$2:$S$97,$B$2:$B$97,B54)*INDEX(Scoring!$C$18:$C$27,MATCH(B54,Scoring!$B$18:$B$27,0))) -> 0 | V54: =IF(U54>0,U54+IF(AND(H54="Y",P54="No"),1000,0)+ROW()/100000,0) -> 0 | W54: OWASP ASVS project page | X54: https://owasp.org/projects/asvs
A55: SEC-11 | B55: Security and privacy | C55: Hosting | D55: Has a risk assessment been completed for the hosting and any cloud services used, including data location and jurisdiction? | E55: Yes / Partial / No / N/A | F55: Cloud risk assessment; data residency decision. | G55: 1 | H55: N | I55: Complete a cloud and hosting risk assessment covering data location, jurisdiction and supplier security, and record the decision. | J55: GCDO public cloud risk assessment guidance (digital.govt.nz); NZISM | L55: Recommended (NZ) | M55: All | P55: Yes | Q55: =IF(P55="Yes",Scoring!$C$6,IF(P55="Partial",Scoring!$C$7,IF(P55="No",Scoring!$C$8,""))) -> 1 | R55: =IF(Q55="",0,G55*Q55) -> 1 | S55: =IF(Q55="",0,G55) -> 1 | T55: =IF(OR(P55="Partial",P55="No"),I55,"") | U55: =IF(Q55="",0,(1-Q55)*G55/SUMIFS($S$2:$S$97,$B$2:$B$97,B55)*INDEX(Scoring!$C$18:$C$27,MATCH(B55,Scoring!$B$18:$B$27,0))) -> 0 | V55: =IF(U55>0,U55+IF(AND(H55="Y",P55="No"),1000,0)+ROW()/100000,0) -> 0 | W55: GCDO cloud risk assessment guidance | X55: https://www.digital.govt.nz/standards-and-guidance/technology-and-architecture/cloud-services/assess-the-risks
A56: OPS-01 | B56: Reliability, observability and service levels | C56: Service levels | D56: Are availability and performance targets (service levels or SLOs) defined for the service and agreed with the business owner? | E56: Yes / Partial / No / N/A | F56: Documented SLA/SLO with targets and measurement method. | G56: 3 | H56: N | I56: Define and agree availability, response time and support targets that reflect how critical the service is to users, and measure against them. | J56: AU Digital Performance Standard criterion 2; GOV.UK Service Standard point 14 | K56: AU DPS 1.0 (2024) | L56: Good practice | M56: All | P56: Partial | Q56: =IF(P56="Yes",Scoring!$C$6,IF(P56="Partial",Scoring!$C$7,IF(P56="No",Scoring!$C$8,""))) -> 0.5 | R56: =IF(Q56="",0,G56*Q56) -> 1.5 | S56: =IF(Q56="",0,G56) -> 3 | T56: =IF(OR(P56="Partial",P56="No"),I56,"") -> Define and agree availability, response time and support targets that reflect how critical the service is to users, and measure against them. | U56: =IF(Q56="",0,(1-Q56)*G56/SUMIFS($S$2:$S$97,$B$2:$B$97,B56)*INDEX(Scoring!$C$18:$C$27,MATCH(B56,Scoring!$B$18:$B$27,0))) -> 0.92857143 | V56: =IF(U56>0,U56+IF(AND(H56="Y",P56="No"),1000,0)+ROW()/100000,0) -> 0.92913143 | W56: AU guide: measuring service availability | X56: https://www.digital.gov.au/policy/digital-experience/digital-performance-standard/dps-criterion-2-measure-availability-your-digital-service
A57: OPS-02 | B57: Reliability, observability and service levels | C57: Monitoring | D57: Is there proactive monitoring and alerting (for example synthetic checks of key user journeys) so the team learns of problems before users report them? | E57: Yes / Partial / No / N/A | F57: Monitoring dashboard; alert rules and on-call routing. | G57: 3 | H57: N | I57: Deploy proactive monitoring and alerting to minimise issue triage and resolution time following service degradation or outage. | J57: AU Digital Performance Standard criteria 1 and 2 | K57: AU DPS 1.0 | L57: Good practice | M57: All | P57: Yes | Q57: =IF(P57="Yes",Scoring!$C$6,IF(P57="Partial",Scoring!$C$7,IF(P57="No",Scoring!$C$8,""))) -> 1 | R57: =IF(Q57="",0,G57*Q57) -> 3 | S57: =IF(Q57="",0,G57) -> 3 | T57: =IF(OR(P57="Partial",P57="No"),I57,"") | U57: =IF(Q57="",0,(1-Q57)*G57/SUMIFS($S$2:$S$97,$B$2:$B$97,B57)*INDEX(Scoring!$C$18:$C$27,MATCH(B57,Scoring!$B$18:$B$27,0))) -> 0 | V57: =IF(U57>0,U57+IF(AND(H57="Y",P57="No"),1000,0)+ROW()/100000,0) -> 0 | W57: AU guide: service monitoring framework | X57: https://www.digital.gov.au/policy/digital-experience/digital-performance-standard/dps-criterion-1-implement-monitoring-framework
A58: OPS-03 | B58: Reliability, observability and service levels | C58: Observability | D58: Are logs, metrics and traces centralised and correlated so the team can quickly diagnose the cause of an issue? | E58: Yes / Partial / No / N/A | F58: Observability tooling; example incident diagnosis time. | G58: 2 | H58: N | I58: Centralise logs, metrics and traces with correlation IDs so issues can be traced across components and suppliers. | J58: Site reliability engineering practice; OWASP ASVS 5.0.0 V16 (Security Logging and Error Handling) | K58: ASVS 5.0.0 | L58: Good practice | M58: All | N58: OWASP ASVS is referenced by chapter ID only. No ASVS requirement text is reproduced (ASVS is CC BY-SA 4.0). In the app, cite requirement IDs in the form v5.0.0-<chapter>.<section>.<requirement>. | P58: No | Q58: =IF(P58="Yes",Scoring!$C$6,IF(P58="Partial",Scoring!$C$7,IF(P58="No",Scoring!$C$8,""))) -> 0 | R58: =IF(Q58="",0,G58*Q58) -> 0 | S58: =IF(Q58="",0,G58) -> 2 | T58: =IF(OR(P58="Partial",P58="No"),I58,"") -> Centralise logs, metrics and traces with correlation IDs so issues can be traced across components and suppliers. | U58: =IF(Q58="",0,(1-Q58)*G58/SUMIFS($S$2:$S$97,$B$2:$B$97,B58)*INDEX(Scoring!$C$18:$C$27,MATCH(B58,Scoring!$B$18:$B$27,0))) -> 1.2380952 | V58: =IF(U58>0,U58+IF(AND(H58="Y",P58="No"),1000,0)+ROW()/100000,0) -> 1.2386752 | W58: Google site reliability engineering books | X58: https://sre.google/books/
A59: OPS-04 | B59: Reliability, observability and service levels | C59: Incident management | D59: Is there an incident management process with severity levels, response and resolution targets, escalation paths and named owners? | E59: Yes / Partial / No / N/A | F59: Incident process; recent incident records against targets. | G59: 3 | H59: Y | I59: Establish an incident management process with severity definitions, response and resolution targets, and clear escalation, and report performance against it. | J59: ITIL incident management; GOV.UK Service Standard point 14 | L59: Good practice | M59: All | P59: Yes | Q59: =IF(P59="Yes",Scoring!$C$6,IF(P59="Partial",Scoring!$C$7,IF(P59="No",Scoring!$C$8,""))) -> 1 | R59: =IF(Q59="",0,G59*Q59) -> 3 | S59: =IF(Q59="",0,G59) -> 3 | T59: =IF(OR(P59="Partial",P59="No"),I59,"") | U59: =IF(Q59="",0,(1-Q59)*G59/SUMIFS($S$2:$S$97,$B$2:$B$97,B59)*INDEX(Scoring!$C$18:$C$27,MATCH(B59,Scoring!$B$18:$B$27,0))) -> 0 | V59: =IF(U59>0,U59+IF(AND(H59="Y",P59="No"),1000,0)+ROW()/100000,0) -> 0 | W59: GOV.UK: operate a reliable service | X59: https://www.gov.uk/service-manual/service-standard/point-14-operate-a-reliable-service
A60: OPS-05 | B60: Reliability, observability and service levels | C60: Outage communication | D60: Are users told about outages and planned maintenance (for example a status page, service banner or alternative channel)? | E60: Yes / Partial / No / N/A | F60: Status page or banner; maintenance notification records. | G60: 2 | H60: N | I60: Tell users promptly about outages and planned maintenance, with expected recovery times and alternative ways to complete their task. | J60: GOV.UK Service Standard point 14 | L60: Good practice | M60: Public-facing | P60: Partial | Q60: =IF(P60="Yes",Scoring!$C$6,IF(P60="Partial",Scoring!$C$7,IF(P60="No",Scoring!$C$8,""))) -> 0.5 | R60: =IF(Q60="",0,G60*Q60) -> 1 | S60: =IF(Q60="",0,G60) -> 2 | T60: =IF(OR(P60="Partial",P60="No"),I60,"") -> Tell users promptly about outages and planned maintenance, with expected recovery times and alternative ways to complete their task. | U60: =IF(Q60="",0,(1-Q60)*G60/SUMIFS($S$2:$S$97,$B$2:$B$97,B60)*INDEX(Scoring!$C$18:$C$27,MATCH(B60,Scoring!$B$18:$B$27,0))) -> 0.61904762 | V60: =IF(U60>0,U60+IF(AND(H60="Y",P60="No"),1000,0)+ROW()/100000,0) -> 0.61964762 | W60: GOV.UK: operate a reliable service | X60: https://www.gov.uk/service-manual/service-standard/point-14-operate-a-reliable-service
A61: OPS-06 | B61: Reliability, observability and service levels | C61: Supplier contracts | D61: Do hosting, vendor and support contracts include service levels for availability, response, resolution and reporting that match the agreed service targets? | E61: Yes / Partial / No / N/A | F61: Contract schedules; supplier performance reports. | G61: 2 | H61: N | I61: Align supplier service levels and reporting with the service's agreed targets, with remedies for under-performance. | J61: Government Procurement Rules (context); good practice | L61: Good practice | M61: All | P61: Yes | Q61: =IF(P61="Yes",Scoring!$C$6,IF(P61="Partial",Scoring!$C$7,IF(P61="No",Scoring!$C$8,""))) -> 1 | R61: =IF(Q61="",0,G61*Q61) -> 2 | S61: =IF(Q61="",0,G61) -> 2 | T61: =IF(OR(P61="Partial",P61="No"),I61,"") | U61: =IF(Q61="",0,(1-Q61)*G61/SUMIFS($S$2:$S$97,$B$2:$B$97,B61)*INDEX(Scoring!$C$18:$C$27,MATCH(B61,Scoring!$B$18:$B$27,0))) -> 0 | V61: =IF(U61>0,U61+IF(AND(H61="Y",P61="No"),1000,0)+ROW()/100000,0) -> 0 | W61: NZ Government procurement framework | X61: https://www.procurement.govt.nz/government-procurement-framework/
A62: OPS-07 | B62: Reliability, observability and service levels | C62: Learning | D62: Are post-incident reviews held for significant incidents, with actions tracked to completion? | E62: Yes / Partial / No / N/A | F62: Post-incident review records and action tracker. | G62: 1 | H62: N | I62: Run blameless post-incident reviews for significant incidents and track improvement actions to completion. | J62: Site reliability engineering practice | L62: Good practice | M62: All | P62: Yes | Q62: =IF(P62="Yes",Scoring!$C$6,IF(P62="Partial",Scoring!$C$7,IF(P62="No",Scoring!$C$8,""))) -> 1 | R62: =IF(Q62="",0,G62*Q62) -> 1 | S62: =IF(Q62="",0,G62) -> 1 | T62: =IF(OR(P62="Partial",P62="No"),I62,"") | U62: =IF(Q62="",0,(1-Q62)*G62/SUMIFS($S$2:$S$97,$B$2:$B$97,B62)*INDEX(Scoring!$C$18:$C$27,MATCH(B62,Scoring!$B$18:$B$27,0))) -> 0 | V62: =IF(U62>0,U62+IF(AND(H62="Y",P62="No"),1000,0)+ROW()/100000,0) -> 0 | W62: Google site reliability engineering books | X62: https://sre.google/books/
A63: OPS-08 | B63: Reliability, observability and service levels | C63: Continuity | D63: Are recovery time and recovery point objectives defined, and have backup restore and disaster recovery been tested in the last 12 months? | E63: Yes / Partial / No / N/A | F63: BCP/DR plan; test results. | G63: 2 | H63: N | I63: Define RTO and RPO based on user impact and test restore and disaster recovery at least annually. | J63: NZISM; business continuity good practice | L63: Recommended (NZ) | M63: All | P63: Partial | Q63: =IF(P63="Yes",Scoring!$C$6,IF(P63="Partial",Scoring!$C$7,IF(P63="No",Scoring!$C$8,""))) -> 0.5 | R63: =IF(Q63="",0,G63*Q63) -> 1 | S63: =IF(Q63="",0,G63) -> 2 | T63: =IF(OR(P63="Partial",P63="No"),I63,"") -> Define RTO and RPO based on user impact and test restore and disaster recovery at least annually. | U63: =IF(Q63="",0,(1-Q63)*G63/SUMIFS($S$2:$S$97,$B$2:$B$97,B63)*INDEX(Scoring!$C$18:$C$27,MATCH(B63,Scoring!$B$18:$B$27,0))) -> 0.61904762 | V63: =IF(U63>0,U63+IF(AND(H63="Y",P63="No"),1000,0)+ROW()/100000,0) -> 0.61967762 | W63: NZ Information Security Manual | X63: https://www.ncsc.govt.nz/nzism/
A64: OPS-09 | B64: Reliability, observability and service levels | C64: Capacity | D64: Has the service been load tested for expected peak demand (for example deadlines, announcements, seasonal peaks)? | E64: Yes / Partial / No / N/A | F64: Load test results; capacity plan. | G64: 1 | H64: N | I64: Load test for expected peaks and plan capacity ahead of known high-demand events. | J64: Good practice | L64: Good practice | M64: All | P64: Yes | Q64: =IF(P64="Yes",Scoring!$C$6,IF(P64="Partial",Scoring!$C$7,IF(P64="No",Scoring!$C$8,""))) -> 1 | R64: =IF(Q64="",0,G64*Q64) -> 1 | S64: =IF(Q64="",0,G64) -> 1 | T64: =IF(OR(P64="Partial",P64="No"),I64,"") | U64: =IF(Q64="",0,(1-Q64)*G64/SUMIFS($S$2:$S$97,$B$2:$B$97,B64)*INDEX(Scoring!$C$18:$C$27,MATCH(B64,Scoring!$B$18:$B$27,0))) -> 0 | V64: =IF(U64>0,U64+IF(AND(H64="Y",P64="No"),1000,0)+ROW()/100000,0) -> 0 | W64: Google site reliability engineering books | X64: https://sre.google/books/
A65: OPS-10 | B65: Reliability, observability and service levels | C65: Change | D65: Can changes be released safely and frequently, with automated testing, rollback, and change windows communicated to support teams? | E65: Yes / Partial / No / N/A | F65: Release process; deployment frequency; rollback evidence. | G65: 1 | H65: N | I65: Automate testing and deployment, make releases small and reversible, and tell support teams about changes before they go live. | J65: GOV.UK Service Standard point 8; DORA software delivery metrics | K65: DORA five-metric model | L65: Good practice | M65: All | P65: No | Q65: =IF(P65="Yes",Scoring!$C$6,IF(P65="Partial",Scoring!$C$7,IF(P65="No",Scoring!$C$8,""))) -> 0 | R65: =IF(Q65="",0,G65*Q65) -> 0 | S65: =IF(Q65="",0,G65) -> 1 | T65: =IF(OR(P65="Partial",P65="No"),I65,"") -> Automate testing and deployment, make releases small and reversible, and tell support teams about changes before they go live. | U65: =IF(Q65="",0,(1-Q65)*G65/SUMIFS($S$2:$S$97,$B$2:$B$97,B65)*INDEX(Scoring!$C$18:$C$27,MATCH(B65,Scoring!$B$18:$B$27,0))) -> 0.61904762 | V65: =IF(U65>0,U65+IF(AND(H65="Y",P65="No"),1000,0)+ROW()/100000,0) -> 0.61969762 | W65: DORA software delivery metrics | X65: https://dora.dev/guides/dora-metrics/
A66: OPS-11 | B66: Reliability, observability and service levels | C66: Reporting | D66: Is service availability and performance reported regularly to the service owner and governance? | E66: Yes / Partial / No / N/A | F66: Performance reports to governance. | G66: 1 | H66: N | I66: Report availability, performance and incident trends to the service owner and governance on a regular cycle. | J66: AU Digital Performance Standard criterion 5; GOV.UK Service Standard point 10 | K66: AU DPS 1.0 | L66: Good practice | M66: All | P66: Yes | Q66: =IF(P66="Yes",Scoring!$C$6,IF(P66="Partial",Scoring!$C$7,IF(P66="No",Scoring!$C$8,""))) -> 1 | R66: =IF(Q66="",0,G66*Q66) -> 1 | S66: =IF(Q66="",0,G66) -> 1 | T66: =IF(OR(P66="Partial",P66="No"),I66,"") | U66: =IF(Q66="",0,(1-Q66)*G66/SUMIFS($S$2:$S$97,$B$2:$B$97,B66)*INDEX(Scoring!$C$18:$C$27,MATCH(B66,Scoring!$B$18:$B$27,0))) -> 0 | V66: =IF(U66>0,U66+IF(AND(H66="Y",P66="No"),1000,0)+ROW()/100000,0) -> 0 | W66: AU Digital Performance Standard | X66: https://www.digital.gov.au/policy/digital-experience/digital-performance-standard
A67: SUP-01 | B67: Support and contact channels | C67: Contact information | D67: Is a contact page linked from the home page that includes non-digital channels (such as phone and postal address) and information for NZ Relay users? | E67: Yes / Partial / No / N/A | F67: Contact page URL and content. | G67: 3 | H67: Y | I67: Provide a contact page linked from the home page with digital and non-digital contact options, including NZ Relay information. | J67: Web Usability Standard 1.4 s2.3 (Contact information; NZ Relay link at s2.3.3) | K67: WUS 1.4 | L67: Mandatory (NZ) | M67: Public-facing | N67: WUS 1.4 added requirements supporting non-digital access channels. | P67: Yes | Q67: =IF(P67="Yes",Scoring!$C$6,IF(P67="Partial",Scoring!$C$7,IF(P67="No",Scoring!$C$8,""))) -> 1 | R67: =IF(Q67="",0,G67*Q67) -> 3 | S67: =IF(Q67="",0,G67) -> 3 | T67: =IF(OR(P67="Partial",P67="No"),I67,"") | U67: =IF(Q67="",0,(1-Q67)*G67/SUMIFS($S$2:$S$97,$B$2:$B$97,B67)*INDEX(Scoring!$C$18:$C$27,MATCH(B67,Scoring!$B$18:$B$27,0))) -> 0 | V67: =IF(U67>0,U67+IF(AND(H67="Y",P67="No"),1000,0)+ROW()/100000,0) -> 0 | W67: NZ Web Usability Standard 1.4 | X67: https://www.digital.govt.nz/standards-and-guidance/nz-government-web-standards/web-usability-standard-1-4
A68: SUP-02 | B68: Support and contact channels | C68: In-service help | D68: Is help available at the point of need within the service (help text, FAQs, guidance), in a consistent location on each page? | E68: Yes / Partial / No / N/A | F68: Help content; audit findings for WCAG SC 3.2.6. | G68: 2 | H68: N | I68: Provide contextual help where users need it and keep help mechanisms in the same place on every page. | J68: WCAG 2.2 SC 3.2.6 (consistent help); Nielsen heuristic 10 | K68: WCAG 2.2 A | L68: Mandatory (NZ) | M68: All | P68: Yes | Q68: =IF(P68="Yes",Scoring!$C$6,IF(P68="Partial",Scoring!$C$7,IF(P68="No",Scoring!$C$8,""))) -> 1 | R68: =IF(Q68="",0,G68*Q68) -> 2 | S68: =IF(Q68="",0,G68) -> 2 | T68: =IF(OR(P68="Partial",P68="No"),I68,"") | U68: =IF(Q68="",0,(1-Q68)*G68/SUMIFS($S$2:$S$97,$B$2:$B$97,B68)*INDEX(Scoring!$C$18:$C$27,MATCH(B68,Scoring!$B$18:$B$27,0))) -> 0 | V68: =IF(U68>0,U68+IF(AND(H68="Y",P68="No"),1000,0)+ROW()/100000,0) -> 0 | W68: NN/g: help and documentation | X68: https://www.nngroup.com/articles/help-and-documentation/
A69: SUP-03 | B69: Support and contact channels | C69: Accessibility support | D69: Can people ask for accessibility help in more than one way, and does the agency reply to accessibility questions within 3 days? | E69: Yes / Partial / No / N/A | F69: Accessibility contact options; response time records. | G69: 2 | H69: N | I69: Offer several ways to ask for accessibility help and respond within 3 days, saying when a full answer will be provided. | J69: Draft Digital Accessibility Standard (consultation draft) | K69: DAS draft (Jul 2026) | L69: Recommended (NZ) | M69: Public-facing | N69: Draft requirement - confirm when DAS is finalised (expected early 2027). | P69: Partial | Q69: =IF(P69="Yes",Scoring!$C$6,IF(P69="Partial",Scoring!$C$7,IF(P69="No",Scoring!$C$8,""))) -> 0.5 | R69: =IF(Q69="",0,G69*Q69) -> 1 | S69: =IF(Q69="",0,G69) -> 2 | T69: =IF(OR(P69="Partial",P69="No"),I69,"") -> Offer several ways to ask for accessibility help and respond within 3 days, saying when a full answer will be provided. | U69: =IF(Q69="",0,(1-Q69)*G69/SUMIFS($S$2:$S$97,$B$2:$B$97,B69)*INDEX(Scoring!$C$18:$C$27,MATCH(B69,Scoring!$B$18:$B$27,0))) -> 0.57142857 | V69: =IF(U69>0,U69+IF(AND(H69="Y",P69="No"),1000,0)+ROW()/100000,0) -> 0.57211857 | W69: NZ Digital Accessibility Standard (draft) | X69: https://www.digital.govt.nz/standards-and-guidance/nz-government-web-standards/digital-accessibility-standard
A70: SUP-04 | B70: Support and contact channels | C70: Support model | D70: Is there a defined support model - support tiers, hours, response targets and escalation - and are front-line staff trained on the service? | E70: Yes / Partial / No / N/A | F70: Support model document; training records; knowledge base. | G70: 2 | H70: N | I70: Define support tiers, hours and response targets, train front-line staff on the service and keep a shared knowledge base up to date. | J70: Good practice (ITIL service desk) | L70: Good practice | M70: All | P70: Yes | Q70: =IF(P70="Yes",Scoring!$C$6,IF(P70="Partial",Scoring!$C$7,IF(P70="No",Scoring!$C$8,""))) -> 1 | R70: =IF(Q70="",0,G70*Q70) -> 2 | S70: =IF(Q70="",0,G70) -> 2 | T70: =IF(OR(P70="Partial",P70="No"),I70,"") | U70: =IF(Q70="",0,(1-Q70)*G70/SUMIFS($S$2:$S$97,$B$2:$B$97,B70)*INDEX(Scoring!$C$18:$C$27,MATCH(B70,Scoring!$B$18:$B$27,0))) -> 0 | V70: =IF(U70>0,U70+IF(AND(H70="Y",P70="No"),1000,0)+ROW()/100000,0) -> 0 | W70: Use your organisation's internal guidance
A71: SUP-05 | B71: Support and contact channels | C71: Feedback | D71: Can users give feedback on each page and at the end of a transaction, and is it reviewed and acted on? | E71: Yes / Partial / No / N/A | F71: Feedback mechanism; feedback log and actions. | G71: 2 | H71: N | I71: Add feedback options on each page and at the end of transactions, review feedback regularly and close the loop on changes made. | J71: AU Digital Performance Standard criterion 4 | K71: AU DPS 1.0 | L71: Good practice | M71: All | P71: No | Q71: =IF(P71="Yes",Scoring!$C$6,IF(P71="Partial",Scoring!$C$7,IF(P71="No",Scoring!$C$8,""))) -> 0 | R71: =IF(Q71="",0,G71*Q71) -> 0 | S71: =IF(Q71="",0,G71) -> 2 | T71: =IF(OR(P71="Partial",P71="No"),I71,"") -> Add feedback options on each page and at the end of transactions, review feedback regularly and close the loop on changes made. | U71: =IF(Q71="",0,(1-Q71)*G71/SUMIFS($S$2:$S$97,$B$2:$B$97,B71)*INDEX(Scoring!$C$18:$C$27,MATCH(B71,Scoring!$B$18:$B$27,0))) -> 1.1428571 | V71: =IF(U71>0,U71+IF(AND(H71="Y",P71="No"),1000,0)+ROW()/100000,0) -> 1.1435671 | W71: AU Digital Performance Standard | X71: https://www.digital.gov.au/policy/digital-experience/digital-performance-standard
A72: SUP-06 | B72: Support and contact channels | C72: Assisted channels | D72: Can people who cannot use the digital service complete the same task through an assisted or offline channel with an equivalent outcome? | E72: Yes / Partial / No / N/A | F72: Assisted digital / offline process description. | G72: 2 | H72: N | I72: Provide an assisted or offline route that achieves the same outcome, and make sure it is promoted and resourced. | J72: Digital Service Design Standard; GOV.UK Service Standard point 3; AU DSS 2.0 criterion 3 | L72: Recommended (NZ) | M72: Public-facing | P72: Yes | Q72: =IF(P72="Yes",Scoring!$C$6,IF(P72="Partial",Scoring!$C$7,IF(P72="No",Scoring!$C$8,""))) -> 1 | R72: =IF(Q72="",0,G72*Q72) -> 2 | S72: =IF(Q72="",0,G72) -> 2 | T72: =IF(OR(P72="Partial",P72="No"),I72,"") | U72: =IF(Q72="",0,(1-Q72)*G72/SUMIFS($S$2:$S$97,$B$2:$B$97,B72)*INDEX(Scoring!$C$18:$C$27,MATCH(B72,Scoring!$B$18:$B$27,0))) -> 0 | V72: =IF(U72>0,U72+IF(AND(H72="Y",P72="No"),1000,0)+ROW()/100000,0) -> 0 | W72: GOV.UK: join up across channels | X72: https://www.gov.uk/service-manual/service-standard/point-3-join-up-across-channels
A73: SUP-07 | B73: Support and contact channels | C73: Complaints | D73: Is there a published complaints process with timeframes and information about escalation (for example to the Ombudsman or Privacy Commissioner)? | E73: Yes / Partial / No / N/A | F73: Complaints process URL. | G73: 1 | H73: N | I73: Publish a complaints process with timeframes and information on how to escalate to the Ombudsman or Privacy Commissioner. | J73: Ombudsman guidance: Effective complaint handling | L73: Good practice | M73: Public-facing | P73: Partial | Q73: =IF(P73="Yes",Scoring!$C$6,IF(P73="Partial",Scoring!$C$7,IF(P73="No",Scoring!$C$8,""))) -> 0.5 | R73: =IF(Q73="",0,G73*Q73) -> 0.5 | S73: =IF(Q73="",0,G73) -> 1 | T73: =IF(OR(P73="Partial",P73="No"),I73,"") -> Publish a complaints process with timeframes and information on how to escalate to the Ombudsman or Privacy Commissioner. | U73: =IF(Q73="",0,(1-Q73)*G73/SUMIFS($S$2:$S$97,$B$2:$B$97,B73)*INDEX(Scoring!$C$18:$C$27,MATCH(B73,Scoring!$B$18:$B$27,0))) -> 0.28571429 | V73: =IF(U73>0,U73+IF(AND(H73="Y",P73="No"),1000,0)+ROW()/100000,0) -> 0.28644429 | W73: Ombudsman: effective complaint handling | X73: https://www.ombudsman.parliament.nz/resources/effective-complaint-handling
A74: LEG-01 | B74: Legal and regulatory | C74: Copyright | D74: Is a copyright and licensing statement linked from the home page, applying NZGOAL open licensing where appropriate? | E74: Yes / Partial / No / N/A | F74: Copyright statement URL. | G74: 1 | H74: N | I74: Publish a copyright statement linked from the home page and apply NZGOAL licensing to reusable content where appropriate. | J74: Web Usability Standard 1.4 s2.4 (Copyright); NZGOAL | K74: WUS 1.4 | L74: Mandatory (NZ) | M74: Public-facing | P74: Yes | Q74: =IF(P74="Yes",Scoring!$C$6,IF(P74="Partial",Scoring!$C$7,IF(P74="No",Scoring!$C$8,""))) -> 1 | R74: =IF(Q74="",0,G74*Q74) -> 1 | S74: =IF(Q74="",0,G74) -> 1 | T74: =IF(OR(P74="Partial",P74="No"),I74,"") | U74: =IF(Q74="",0,(1-Q74)*G74/SUMIFS($S$2:$S$97,$B$2:$B$97,B74)*INDEX(Scoring!$C$18:$C$27,MATCH(B74,Scoring!$B$18:$B$27,0))) -> 0 | V74: =IF(U74>0,U74+IF(AND(H74="Y",P74="No"),1000,0)+ROW()/100000,0) -> 0 | W74: NZGOAL open licensing framework | X74: https://www.data.govt.nz/manage-data/policies/nzgoal
A75: LEG-02 | B75: Legal and regulatory | C75: Records | D75: Are records created by the service captured, kept and disposed of in line with the Public Records Act and the agency's disposal authority? | E75: Yes / Partial / No / N/A | F75: Records management assessment; disposal authority reference. | G75: 2 | H75: N | I75: Assess the service against Archives NZ requirements, ensure records are captured and retained correctly, and apply the relevant disposal authority. | J75: Public Records Act 2005; Archives NZ Information and Records Management Standard (16/S1) | L75: Mandatory (NZ) | M75: All | P75: Yes | Q75: =IF(P75="Yes",Scoring!$C$6,IF(P75="Partial",Scoring!$C$7,IF(P75="No",Scoring!$C$8,""))) -> 1 | R75: =IF(Q75="",0,G75*Q75) -> 2 | S75: =IF(Q75="",0,G75) -> 2 | T75: =IF(OR(P75="Partial",P75="No"),I75,"") | U75: =IF(Q75="",0,(1-Q75)*G75/SUMIFS($S$2:$S$97,$B$2:$B$97,B75)*INDEX(Scoring!$C$18:$C$27,MATCH(B75,Scoring!$B$18:$B$27,0))) -> 0 | V75: =IF(U75>0,U75+IF(AND(H75="Y",P75="No"),1000,0)+ROW()/100000,0) -> 0 | W75: Archives NZ records management standard | X75: https://archives.govt.nz/manage-information/how-to-manage-your-information/key-obligations-and-the-standard/information-and-records-management-standard
A76: LEG-03 | B76: Legal and regulatory | C76: Information access | D76: Can information held by the service be found and retrieved to respond to Official Information Act and Privacy Act access requests within statutory timeframes? | E76: Yes / Partial / No / N/A | F76: Retrieval process; test retrieval. | G76: 1 | H76: N | I76: Make sure information can be searched and extracted to answer OIA and Privacy Act requests within statutory timeframes. | J76: Official Information Act 1982; Privacy Act 2020 IPP 6 | L76: Mandatory (NZ) | M76: All | P76: Partial | Q76: =IF(P76="Yes",Scoring!$C$6,IF(P76="Partial",Scoring!$C$7,IF(P76="No",Scoring!$C$8,""))) -> 0.5 | R76: =IF(Q76="",0,G76*Q76) -> 0.5 | S76: =IF(Q76="",0,G76) -> 1 | T76: =IF(OR(P76="Partial",P76="No"),I76,"") -> Make sure information can be searched and extracted to answer OIA and Privacy Act requests within statutory timeframes. | U76: =IF(Q76="",0,(1-Q76)*G76/SUMIFS($S$2:$S$97,$B$2:$B$97,B76)*INDEX(Scoring!$C$18:$C$27,MATCH(B76,Scoring!$B$18:$B$27,0))) -> 0.23076923 | V76: =IF(U76>0,U76+IF(AND(H76="Y",P76="No"),1000,0)+ROW()/100000,0) -> 0.23152923 | W76: Official Information Act 1982 | X76: https://www.legislation.govt.nz/act/public/1982/156/en/latest/
A77: LEG-04 | B77: Legal and regulatory | C77: Equal access | D77: Has the service been checked to ensure it does not discriminate, and that disabled people and other groups have equivalent access to the service and information? | E77: Yes / Partial / No / N/A | F77: Equity or inclusion assessment; accessibility evidence. | G77: 2 | H77: N | I77: Assess the service for discriminatory effects and barriers to access, and provide equivalent access routes where barriers can't be removed. | J77: Human Rights Act 1993; NZ Bill of Rights Act 1990; UNCRPD | L77: Mandatory (NZ) | M77: All | P77: Yes | Q77: =IF(P77="Yes",Scoring!$C$6,IF(P77="Partial",Scoring!$C$7,IF(P77="No",Scoring!$C$8,""))) -> 1 | R77: =IF(Q77="",0,G77*Q77) -> 2 | S77: =IF(Q77="",0,G77) -> 2 | T77: =IF(OR(P77="Partial",P77="No"),I77,"") | U77: =IF(Q77="",0,(1-Q77)*G77/SUMIFS($S$2:$S$97,$B$2:$B$97,B77)*INDEX(Scoring!$C$18:$C$27,MATCH(B77,Scoring!$B$18:$B$27,0))) -> 0 | V77: =IF(U77>0,U77+IF(AND(H77="Y",P77="No"),1000,0)+ROW()/100000,0) -> 0 | W77: Human Rights Act 1993 | X77: https://www.legislation.govt.nz/act/public/1993/82/en/latest/
A78: LEG-05 | B78: Legal and regulatory | C78: Legal basis | D78: Does the service accurately reflect its legal basis - eligibility rules, statutory timeframes, fees and rights of review or appeal? | E78: Yes / Partial / No / N/A | F78: Legal review sign-off of rules and content. | G78: 2 | H78: N | I78: Have the service's rules and content reviewed against the empowering legislation, and tell users about their rights of review or appeal. | J78: Empowering legislation for the service | K78: Service-specific | L78: Mandatory (NZ) | M78: Transactional | P78: No | Q78: =IF(P78="Yes",Scoring!$C$6,IF(P78="Partial",Scoring!$C$7,IF(P78="No",Scoring!$C$8,""))) -> 0 | R78: =IF(Q78="",0,G78*Q78) -> 0 | S78: =IF(Q78="",0,G78) -> 2 | T78: =IF(OR(P78="Partial",P78="No"),I78,"") -> Have the service's rules and content reviewed against the empowering legislation, and tell users about their rights of review or appeal. | U78: =IF(Q78="",0,(1-Q78)*G78/SUMIFS($S$2:$S$97,$B$2:$B$97,B78)*INDEX(Scoring!$C$18:$C$27,MATCH(B78,Scoring!$B$18:$B$27,0))) -> 0.92307692 | V78: =IF(U78>0,U78+IF(AND(H78="Y",P78="No"),1000,0)+ROW()/100000,0) -> 0.92385692 | W78: Refer to your service's own legislation
A79: LEG-06 | B79: Legal and regulatory | C79: Terms of use | D79: Are terms of use published for transactional or authenticated services, in plain language? | E79: Yes / Partial / No / N/A | F79: Terms of use URL. | G79: 1 | H79: N | I79: Publish plain language terms of use covering acceptable use, liability and how accounts and data are managed. | J79: Good practice | L79: Good practice | M79: Authenticated | P79: Yes | Q79: =IF(P79="Yes",Scoring!$C$6,IF(P79="Partial",Scoring!$C$7,IF(P79="No",Scoring!$C$8,""))) -> 1 | R79: =IF(Q79="",0,G79*Q79) -> 1 | S79: =IF(Q79="",0,G79) -> 1 | T79: =IF(OR(P79="Partial",P79="No"),I79,"") | U79: =IF(Q79="",0,(1-Q79)*G79/SUMIFS($S$2:$S$97,$B$2:$B$97,B79)*INDEX(Scoring!$C$18:$C$27,MATCH(B79,Scoring!$B$18:$B$27,0))) -> 0 | V79: =IF(U79>0,U79+IF(AND(H79="Y",P79="No"),1000,0)+ROW()/100000,0) -> 0 | W79: Use your organisation's internal guidance
A80: LEG-07 | B80: Legal and regulatory | C80: Algorithms and AI | D80: If the service uses algorithms or AI that affect people, has this been assessed against NZ Government AI and algorithm guidance, with transparency for users? | E80: Yes / Partial / No / N/A | F80: Algorithm/AI assessment; public explanation. | G80: 1 | H80: N | I80: Assess algorithmic and AI use against NZ Government guidance and the Algorithm Charter (if a signatory), and explain to users how decisions are made. | J80: Algorithm Charter for Aotearoa New Zealand; Public Service AI Framework (2025) | L80: Recommended (NZ) | M80: Uses AI | P80: N/A | Q80: =IF(P80="Yes",Scoring!$C$6,IF(P80="Partial",Scoring!$C$7,IF(P80="No",Scoring!$C$8,""))) | R80: =IF(Q80="",0,G80*Q80) -> 0 | S80: =IF(Q80="",0,G80) -> 0 | T80: =IF(OR(P80="Partial",P80="No"),I80,"") | U80: =IF(Q80="",0,(1-Q80)*G80/SUMIFS($S$2:$S$97,$B$2:$B$97,B80)*INDEX(Scoring!$C$18:$C$27,MATCH(B80,Scoring!$B$18:$B$27,0))) -> 0 | V80: =IF(U80>0,U80+IF(AND(H80="Y",P80="No"),1000,0)+ROW()/100000,0) -> 0 | W80: Algorithm Charter for Aotearoa NZ | X80: https://data.govt.nz/algorithm-charter/
A81: LEG-08 | B81: Legal and regulatory | C81: Te Tiriti | D81: Have the Crown's obligations under Te Tiriti o Waitangi been considered in the design of the service, including Māori users' needs? | E81: Yes / Partial / No / N/A | F81: Engagement records; design decisions. | G81: 1 | H81: N | I81: Engage with Māori users and partners in design and consider how the service supports the Crown's relationship with Māori. | J81: Public Service Act 2020 s14; Digital Service Design Standard | L81: Recommended (NZ) | M81: All | P81: Yes | Q81: =IF(P81="Yes",Scoring!$C$6,IF(P81="Partial",Scoring!$C$7,IF(P81="No",Scoring!$C$8,""))) -> 1 | R81: =IF(Q81="",0,G81*Q81) -> 1 | S81: =IF(Q81="",0,G81) -> 1 | T81: =IF(OR(P81="Partial",P81="No"),I81,"") | U81: =IF(Q81="",0,(1-Q81)*G81/SUMIFS($S$2:$S$97,$B$2:$B$97,B81)*INDEX(Scoring!$C$18:$C$27,MATCH(B81,Scoring!$B$18:$B$27,0))) -> 0 | V81: =IF(U81>0,U81+IF(AND(H81="Y",P81="No"),1000,0)+ROW()/100000,0) -> 0 | W81: Public Service Act 2020, section 14 | X81: https://www.legislation.govt.nz/act/public/2020/0040/latest/LMS356875.html
A82: LEG-09 | B82: Legal and regulatory | C82: Legislative compliance | D82: Has the service identified the legislation it is subject to - including service-specific legislation such as the Planning Act and Natural Environment Act where relevant - and confirmed it meets the relevant provisions, including equal access, legal basis, public records and information access? | E82: Yes / Partial / No / N/A | F82: Register of legislation that applies to the service, with each obligation and how it is met; legal review sign-off; links to evidence for LEG-02 to LEG-05. | G82: 3 | H82: N | I82: Create and maintain a register of the legislation the service is subject to - including service-specific Acts such as the Planning Act and Natural Environment Act, and cross-cutting obligations on equal access, legal basis, public records and information access - have it reviewed by legal advisors, and re-check it when legislation or the service changes. | J82: Planning Act; Natural Environment Act; Human Rights Act 1993; NZ Bill of Rights Act 1990; Public Records Act 2005; Official Information Act 1982; Privacy Act 2020 | K82: Planning Act and Natural Environment Act in force 30 Sep 2026 (transitional provisions apply) | L82: Mandatory (NZ) | M82: All | N82: Catch-all legal criterion at weight 3 (v1.10) so legislative obligations are covered in the simple set. Detailed checks remain at LEG-02 to LEG-05. The Planning Act and Natural Environment Act replace the Resource Management Act system with transitional arrangements - confirm which provisions apply to the service. | P82: Partial | Q82: =IF(P82="Yes",Scoring!$C$6,IF(P82="Partial",Scoring!$C$7,IF(P82="No",Scoring!$C$8,""))) -> 0.5 | R82: =IF(Q82="",0,G82*Q82) -> 1.5 | S82: =IF(Q82="",0,G82) -> 3 | T82: =IF(OR(P82="Partial",P82="No"),I82,"") -> Create and maintain a register of the legislation the service is subject to - including service-specific Acts such as the Planning Act and Natural Environment Act, and cross-cutting obligations on equal access, legal basis, public records and information access - have it reviewed by legal advisors, and re-check it when legislation or the service changes. | U82: =IF(Q82="",0,(1-Q82)*G82/SUMIFS($S$2:$S$97,$B$2:$B$97,B82)*INDEX(Scoring!$C$18:$C$27,MATCH(B82,Scoring!$B$18:$B$27,0))) -> 0.69230769 | V82: =IF(U82>0,U82+IF(AND(H82="Y",P82="No"),1000,0)+ROW()/100000,0) -> 0.69312769 | W82: Planning and Natural Environment Acts overview | X82: https://www.buddlefindlay.com/insights/resource-management-reform-an-overview-of-the-planning-act-and-natural-environment-act/
A83: CMG-01 | B83: Content management and governance | C83: Ownership | D83: Is there a named service owner accountable for the service's user experience, roadmap and budget? | E83: Yes / Partial / No / N/A | F83: Named owner and terms of reference. | G83: 2 | H83: N | I83: Appoint a service owner with the authority and budget to improve the service over its lifetime. | J83: GOV.UK Service Standard point 6 | L83: Good practice | M83: All | P83: Yes | Q83: =IF(P83="Yes",Scoring!$C$6,IF(P83="Partial",Scoring!$C$7,IF(P83="No",Scoring!$C$8,""))) -> 1 | R83: =IF(Q83="",0,G83*Q83) -> 2 | S83: =IF(Q83="",0,G83) -> 2 | T83: =IF(OR(P83="Partial",P83="No"),I83,"") | U83: =IF(Q83="",0,(1-Q83)*G83/SUMIFS($S$2:$S$97,$B$2:$B$97,B83)*INDEX(Scoring!$C$18:$C$27,MATCH(B83,Scoring!$B$18:$B$27,0))) -> 0 | V83: =IF(U83>0,U83+IF(AND(H83="Y",P83="No"),1000,0)+ROW()/100000,0) -> 0 | W83: GOV.UK: have a multidisciplinary team | X83: https://www.gov.uk/service-manual/service-standard/point-6-have-a-multidisciplinary-team
A84: CMG-02 | B84: Content management and governance | C84: Content lifecycle | D84: Does each piece of content have an owner and review date, with outdated content updated, archived or removed? | E84: Yes / Partial / No / N/A | F84: Content inventory with owners and review dates. | G84: 2 | H84: N | I84: Assign owners and review dates to all content, review at least annually and remove or archive content that is out of date. | J84: Good practice; WAS 1.2 (inactive web pages) | L84: Good practice | M84: All | P84: No | Q84: =IF(P84="Yes",Scoring!$C$6,IF(P84="Partial",Scoring!$C$7,IF(P84="No",Scoring!$C$8,""))) -> 0 | R84: =IF(Q84="",0,G84*Q84) -> 0 | S84: =IF(Q84="",0,G84) -> 2 | T84: =IF(OR(P84="Partial",P84="No"),I84,"") -> Assign owners and review dates to all content, review at least annually and remove or archive content that is out of date. | U84: =IF(Q84="",0,(1-Q84)*G84/SUMIFS($S$2:$S$97,$B$2:$B$97,B84)*INDEX(Scoring!$C$18:$C$27,MATCH(B84,Scoring!$B$18:$B$27,0))) -> 0.625 | V84: =IF(U84>0,U84+IF(AND(H84="Y",P84="No"),1000,0)+ROW()/100000,0) -> 0.62584 | W84: US digital-first experience memo | X84: https://www.whitehouse.gov/wp-content/uploads/2023/09/M-23-22-Delivering-a-Digital-First-Public-Experience.pdf
A85: CMG-03 | B85: Content management and governance | C85: Accessible authoring | D85: Does the content management system support accessible authoring - enforcing headings, alt text, link text and accessibility checks before publishing? | E85: Yes / Partial / No / N/A | F85: CMS configuration; authoring guidance. | G85: 2 | H85: N | I85: Configure the CMS to prompt for and check accessibility (alt text, headings, link text) and block publishing of known errors. | J85: W3C ATAG 2.0 | K85: ATAG 2.0 | L85: Good practice | M85: Uses CMS | P85: Yes | Q85: =IF(P85="Yes",Scoring!$C$6,IF(P85="Partial",Scoring!$C$7,IF(P85="No",Scoring!$C$8,""))) -> 1 | R85: =IF(Q85="",0,G85*Q85) -> 2 | S85: =IF(Q85="",0,G85) -> 2 | T85: =IF(OR(P85="Partial",P85="No"),I85,"") | U85: =IF(Q85="",0,(1-Q85)*G85/SUMIFS($S$2:$S$97,$B$2:$B$97,B85)*INDEX(Scoring!$C$18:$C$27,MATCH(B85,Scoring!$B$18:$B$27,0))) -> 0 | V85: =IF(U85>0,U85+IF(AND(H85="Y",P85="No"),1000,0)+ROW()/100000,0) -> 0 | W85: W3C authoring tool guidelines (ATAG) | X85: https://www.w3.org/WAI/standards-guidelines/atag/
A86: CMG-04 | B86: Content management and governance | C86: Publishing workflow | D86: Is there a publishing workflow with review and approval, and are content authors trained in plain language and accessibility? | E86: Yes / Partial / No / N/A | F86: Workflow configuration; training records. | G86: 1 | H86: N | I86: Set up a review and approval workflow and train authors in plain language, accessibility and the style guide. | J86: Good practice | L86: Good practice | M86: Uses CMS | P86: Partial | Q86: =IF(P86="Yes",Scoring!$C$6,IF(P86="Partial",Scoring!$C$7,IF(P86="No",Scoring!$C$8,""))) -> 0.5 | R86: =IF(Q86="",0,G86*Q86) -> 0.5 | S86: =IF(Q86="",0,G86) -> 1 | T86: =IF(OR(P86="Partial",P86="No"),I86,"") -> Set up a review and approval workflow and train authors in plain language, accessibility and the style guide. | U86: =IF(Q86="",0,(1-Q86)*G86/SUMIFS($S$2:$S$97,$B$2:$B$97,B86)*INDEX(Scoring!$C$18:$C$27,MATCH(B86,Scoring!$B$18:$B$27,0))) -> 0.15625 | V86: =IF(U86>0,U86+IF(AND(H86="Y",P86="No"),1000,0)+ROW()/100000,0) -> 0.15711 | W86: W3C authoring tool guidelines (ATAG) | X86: https://www.w3.org/WAI/standards-guidelines/atag/
A87: CMG-05 | B87: Content management and governance | C87: Link health | D87: Are broken links, redirects and URL changes monitored and managed? | E87: Yes / Partial / No / N/A | F87: Link checker results; redirect register. | G87: 1 | H87: N | I87: Run regular broken-link checks and maintain redirects when URLs change. | J87: Good practice | L87: Good practice | M87: All | P87: Yes | Q87: =IF(P87="Yes",Scoring!$C$6,IF(P87="Partial",Scoring!$C$7,IF(P87="No",Scoring!$C$8,""))) -> 1 | R87: =IF(Q87="",0,G87*Q87) -> 1 | S87: =IF(Q87="",0,G87) -> 1 | T87: =IF(OR(P87="Partial",P87="No"),I87,"") | U87: =IF(Q87="",0,(1-Q87)*G87/SUMIFS($S$2:$S$97,$B$2:$B$97,B87)*INDEX(Scoring!$C$18:$C$27,MATCH(B87,Scoring!$B$18:$B$27,0))) -> 0 | V87: =IF(U87>0,U87+IF(AND(H87="Y",P87="No"),1000,0)+ROW()/100000,0) -> 0 | W87: Use your organisation's internal guidance
A88: CMG-06 | B88: Content management and governance | C88: Sustained funding | D88: Is ongoing funding and capacity in place to keep improving the service after launch, not only for the initial project? | E88: Yes / Partial / No / N/A | F88: Budget line; team capacity plan. | G88: 2 | H88: N | I88: Secure ongoing funding and a team to maintain and improve the service across its lifetime. | J88: Digital Service Design Standard; AU DSS 2.0 criterion 10 (keep it relevant) | L88: Recommended (NZ) | M88: All | P88: Yes | Q88: =IF(P88="Yes",Scoring!$C$6,IF(P88="Partial",Scoring!$C$7,IF(P88="No",Scoring!$C$8,""))) -> 1 | R88: =IF(Q88="",0,G88*Q88) -> 2 | S88: =IF(Q88="",0,G88) -> 2 | T88: =IF(OR(P88="Partial",P88="No"),I88,"") | U88: =IF(Q88="",0,(1-Q88)*G88/SUMIFS($S$2:$S$97,$B$2:$B$97,B88)*INDEX(Scoring!$C$18:$C$27,MATCH(B88,Scoring!$B$18:$B$27,0))) -> 0 | V88: =IF(U88>0,U88+IF(AND(H88="Y",P88="No"),1000,0)+ROW()/100000,0) -> 0 | W88: NZ Digital Service Design principles | X88: https://www.digital.govt.nz/standards-and-guidance/digital-service-design-standard/principles
A89: CMG-07 | B89: Content management and governance | C89: Content management | D89: Is there an agreed content management approach for the service - named content owners, a review schedule, a publishing workflow with approval, and accessible authoring - and is it being followed? | E89: Yes / Partial / No / N/A | F89: Content management plan; content inventory with owners and review dates; publishing workflow records from the last 3 months. | G89: 3 | H89: N | I89: Put in place and follow a content management approach with named owners, scheduled reviews, an approval workflow and accessible authoring, so content stays accurate, current and consistent. | J89: OMB M-23-22 (content pillar); W3C ATAG 2.0; good practice | L89: Good practice | M89: All | N89: Weight 3: content management, governance, measurement and continuous improvement are critical to app health and hygiene, and therefore have a consequential impact on user experience if not considered as part of the assessment. Added in v1.10. | P89: Partial | Q89: =IF(P89="Yes",Scoring!$C$6,IF(P89="Partial",Scoring!$C$7,IF(P89="No",Scoring!$C$8,""))) -> 0.5 | R89: =IF(Q89="",0,G89*Q89) -> 1.5 | S89: =IF(Q89="",0,G89) -> 3 | T89: =IF(OR(P89="Partial",P89="No"),I89,"") -> Put in place and follow a content management approach with named owners, scheduled reviews, an approval workflow and accessible authoring, so content stays accurate, current and consistent. | U89: =IF(Q89="",0,(1-Q89)*G89/SUMIFS($S$2:$S$97,$B$2:$B$97,B89)*INDEX(Scoring!$C$18:$C$27,MATCH(B89,Scoring!$B$18:$B$27,0))) -> 0.46875 | V89: =IF(U89>0,U89+IF(AND(H89="Y",P89="No"),1000,0)+ROW()/100000,0) -> 0.46964 | W89: US digital-first experience memo | X89: https://www.whitehouse.gov/wp-content/uploads/2023/09/M-23-22-Delivering-a-Digital-First-Public-Experience.pdf
A90: CMG-08 | B90: Content management and governance | C90: Governance | D90: Does the service have clear governance - a named service owner, defined decision rights, a regular forum that reviews performance, risks and the improvement roadmap, and funding for ongoing maintenance? | E90: Yes / Partial / No / N/A | F90: Terms of reference; recent governance minutes; risk register; funded roadmap. | G90: 3 | H90: N | I90: Establish governance for the service with a named owner, clear decision rights, a regular review of performance, risks and roadmap, and ongoing funding for maintenance and improvement. | J90: GOV.UK Service Standard point 6; Digital Service Design Standard; AU Digital Service Standard 2.0 criterion 10 (keep it relevant) | L90: Recommended (NZ) | M90: All | N90: Weight 3: content management, governance, measurement and continuous improvement are critical to app health and hygiene, and therefore have a consequential impact on user experience if not considered as part of the assessment. Added in v1.10. | P90: Yes | Q90: =IF(P90="Yes",Scoring!$C$6,IF(P90="Partial",Scoring!$C$7,IF(P90="No",Scoring!$C$8,""))) -> 1 | R90: =IF(Q90="",0,G90*Q90) -> 3 | S90: =IF(Q90="",0,G90) -> 3 | T90: =IF(OR(P90="Partial",P90="No"),I90,"") | U90: =IF(Q90="",0,(1-Q90)*G90/SUMIFS($S$2:$S$97,$B$2:$B$97,B90)*INDEX(Scoring!$C$18:$C$27,MATCH(B90,Scoring!$B$18:$B$27,0))) -> 0 | V90: =IF(U90>0,U90+IF(AND(H90="Y",P90="No"),1000,0)+ROW()/100000,0) -> 0 | W90: GOV.UK: have a multidisciplinary team | X90: https://www.gov.uk/service-manual/service-standard/point-6-have-a-multidisciplinary-team
A91: MSR-01 | B91: Measurement and continuous improvement | C91: Success measures | D91: Are success measures defined for the service (for example completion rate, user satisfaction, cost per transaction, digital take-up) and tracked? | E91: Yes / Partial / No / N/A | F91: Measurement framework; dashboard. | G91: 2 | H91: N | I91: Define success measures linked to the service's purpose and track them in a dashboard the team reviews regularly. | J91: GOV.UK Service Standard point 10; AU Digital Performance Standard criterion 3 | L91: Good practice | M91: All | P91: No | Q91: =IF(P91="Yes",Scoring!$C$6,IF(P91="Partial",Scoring!$C$7,IF(P91="No",Scoring!$C$8,""))) -> 0 | R91: =IF(Q91="",0,G91*Q91) -> 0 | S91: =IF(Q91="",0,G91) -> 2 | T91: =IF(OR(P91="Partial",P91="No"),I91,"") -> Define success measures linked to the service's purpose and track them in a dashboard the team reviews regularly. | U91: =IF(Q91="",0,(1-Q91)*G91/SUMIFS($S$2:$S$97,$B$2:$B$97,B91)*INDEX(Scoring!$C$18:$C$27,MATCH(B91,Scoring!$B$18:$B$27,0))) -> 0.71428571 | V91: =IF(U91>0,U91+IF(AND(H91="Y",P91="No"),1000,0)+ROW()/100000,0) -> 0.71519571 | W91: GOV.UK: define and measure success | X91: https://www.gov.uk/service-manual/service-standard/point-10-define-success-publish-performance-data
A92: MSR-02 | B92: Measurement and continuous improvement | C92: Analytics | D92: Is web analytics implemented in a privacy-respecting way (no personal information in URLs or events, clear notice in the privacy statement)? | E92: Yes / Partial / No / N/A | F92: Analytics configuration review. | G92: 1 | H92: N | I92: Configure analytics to exclude personal information and describe analytics use in the privacy statement. | J92: Privacy Act 2020; OMB M-23-22 (analytics pillar); OWASP ASVS 5.0.0 V14 (Data Protection) | K92: ASVS 5.0.0 | L92: Recommended (NZ) | M92: All | N92: OWASP ASVS is referenced by chapter ID only. No ASVS requirement text is reproduced (ASVS is CC BY-SA 4.0). In the app, cite requirement IDs in the form v5.0.0-<chapter>.<section>.<requirement>. | P92: Yes | Q92: =IF(P92="Yes",Scoring!$C$6,IF(P92="Partial",Scoring!$C$7,IF(P92="No",Scoring!$C$8,""))) -> 1 | R92: =IF(Q92="",0,G92*Q92) -> 1 | S92: =IF(Q92="",0,G92) -> 1 | T92: =IF(OR(P92="Partial",P92="No"),I92,"") | U92: =IF(Q92="",0,(1-Q92)*G92/SUMIFS($S$2:$S$97,$B$2:$B$97,B92)*INDEX(Scoring!$C$18:$C$27,MATCH(B92,Scoring!$B$18:$B$27,0))) -> 0 | V92: =IF(U92>0,U92+IF(AND(H92="Y",P92="No"),1000,0)+ROW()/100000,0) -> 0 | W92: Privacy Act 2020 | X92: https://www.legislation.govt.nz/act/public/2020/31/en/latest/
A93: MSR-03 | B93: Measurement and continuous improvement | C93: Satisfaction | D93: Is user satisfaction measured (for example CSAT or the System Usability Scale) and are results used to prioritise improvements? | E93: Yes / Partial / No / N/A | F93: Satisfaction results over time; linked backlog items. | G93: 2 | H93: N | I93: Measure user satisfaction consistently over time and use results to prioritise improvements. | J93: AU Digital Performance Standard criterion 4; System Usability Scale | L93: Good practice | M93: All | P93: Yes | Q93: =IF(P93="Yes",Scoring!$C$6,IF(P93="Partial",Scoring!$C$7,IF(P93="No",Scoring!$C$8,""))) -> 1 | R93: =IF(Q93="",0,G93*Q93) -> 2 | S93: =IF(Q93="",0,G93) -> 2 | T93: =IF(OR(P93="Partial",P93="No"),I93,"") | U93: =IF(Q93="",0,(1-Q93)*G93/SUMIFS($S$2:$S$97,$B$2:$B$97,B93)*INDEX(Scoring!$C$18:$C$27,MATCH(B93,Scoring!$B$18:$B$27,0))) -> 0 | V93: =IF(U93>0,U93+IF(AND(H93="Y",P93="No"),1000,0)+ROW()/100000,0) -> 0 | W93: System Usability Scale (Brooke, 1996) | X93: https://verdi.cs.ucl.ac.uk/constructDB/publications/brooke-susa-1996.html
A94: MSR-04 | B94: Measurement and continuous improvement | C94: Improvement | D94: Is there a prioritised improvement backlog fed by research, analytics, feedback and support data, with improvements released regularly? | E94: Yes / Partial / No / N/A | F94: Backlog; release notes. | G94: 2 | H94: N | I94: Maintain a single prioritised backlog drawing on research, analytics, feedback and support trends, and release improvements regularly. | J94: GOV.UK Service Standard point 8 | L94: Good practice | M94: All | P94: Yes | Q94: =IF(P94="Yes",Scoring!$C$6,IF(P94="Partial",Scoring!$C$7,IF(P94="No",Scoring!$C$8,""))) -> 1 | R94: =IF(Q94="",0,G94*Q94) -> 2 | S94: =IF(Q94="",0,G94) -> 2 | T94: =IF(OR(P94="Partial",P94="No"),I94,"") | U94: =IF(Q94="",0,(1-Q94)*G94/SUMIFS($S$2:$S$97,$B$2:$B$97,B94)*INDEX(Scoring!$C$18:$C$27,MATCH(B94,Scoring!$B$18:$B$27,0))) -> 0 | V94: =IF(U94>0,U94+IF(AND(H94="Y",P94="No"),1000,0)+ROW()/100000,0) -> 0 | W94: GOV.UK Service Standard (14 points) | X94: https://www.gov.uk/service-manual/service-standard
A95: MSR-05 | B95: Measurement and continuous improvement | C95: Health check cycle | D95: Is this UX health check repeated at least annually and after major change, with progress against previous recommendations tracked? | E95: Yes / Partial / No / N/A | F95: Previous health check reports and action tracking. | G95: 1 | H95: N | I95: Repeat the UX health check at least annually and after major change, and track progress on previous recommendations. | J95: Good practice | L95: Good practice | M95: All | P95: Partial | Q95: =IF(P95="Yes",Scoring!$C$6,IF(P95="Partial",Scoring!$C$7,IF(P95="No",Scoring!$C$8,""))) -> 0.5 | R95: =IF(Q95="",0,G95*Q95) -> 0.5 | S95: =IF(Q95="",0,G95) -> 1 | T95: =IF(OR(P95="Partial",P95="No"),I95,"") -> Repeat the UX health check at least annually and after major change, and track progress on previous recommendations. | U95: =IF(Q95="",0,(1-Q95)*G95/SUMIFS($S$2:$S$97,$B$2:$B$97,B95)*INDEX(Scoring!$C$18:$C$27,MATCH(B95,Scoring!$B$18:$B$27,0))) -> 0.17857143 | V95: =IF(U95>0,U95+IF(AND(H95="Y",P95="No"),1000,0)+ROW()/100000,0) -> 0.17952143 | W95: Use your organisation's internal guidance
A96: MSR-06 | B96: Measurement and continuous improvement | C96: Measurement | D96: Is the service's performance measured against agreed indicators - for example availability, task completion, user satisfaction, and open accessibility and usability issues - with results reported to the service owner at least quarterly? | E96: Yes / Partial / No / N/A | F96: Agreed indicator set; performance dashboard; the last four quarterly reports. | G96: 3 | H96: N | I96: Agree a small set of performance indicators covering availability, task completion, satisfaction and open accessibility and usability issues, and report them to the service owner at least quarterly. | J96: AU Digital Performance Standard criteria 1-5; GOV.UK Service Standard point 10 | K96: AU DPS 1.0 | L96: Good practice | M96: All | N96: Weight 3: content management, governance, measurement and continuous improvement are critical to app health and hygiene, and therefore have a consequential impact on user experience if not considered as part of the assessment. Added in v1.10. | P96: Yes | Q96: =IF(P96="Yes",Scoring!$C$6,IF(P96="Partial",Scoring!$C$7,IF(P96="No",Scoring!$C$8,""))) -> 1 | R96: =IF(Q96="",0,G96*Q96) -> 3 | S96: =IF(Q96="",0,G96) -> 3 | T96: =IF(OR(P96="Partial",P96="No"),I96,"") | U96: =IF(Q96="",0,(1-Q96)*G96/SUMIFS($S$2:$S$97,$B$2:$B$97,B96)*INDEX(Scoring!$C$18:$C$27,MATCH(B96,Scoring!$B$18:$B$27,0))) -> 0 | V96: =IF(U96>0,U96+IF(AND(H96="Y",P96="No"),1000,0)+ROW()/100000,0) -> 0 | W96: AU Digital Performance Standard | X96: https://www.digital.gov.au/policy/digital-experience/digital-performance-standard
A97: MSR-07 | B97: Measurement and continuous improvement | C97: Continuous improvement | D97: Is there a regular, resourced improvement cycle where insights from research, analytics, feedback, incidents and health checks are turned into prioritised changes that are released and their impact measured? | E97: Yes / Partial / No / N/A | F97: Improvement backlog; release history; before-and-after measures for recent changes. | G97: 3 | H97: N | I97: Run a regular improvement cycle that turns insights from research, analytics, feedback, incidents and health checks into prioritised changes, releases them, and measures their impact. | J97: GOV.UK Service Standard point 8; AU Digital Service Standard 2.0 criterion 10 (keep it relevant) | L97: Good practice | M97: All | N97: Weight 3: content management, governance, measurement and continuous improvement are critical to app health and hygiene, and therefore have a consequential impact on user experience if not considered as part of the assessment. Added in v1.10. | P97: No | Q97: =IF(P97="Yes",Scoring!$C$6,IF(P97="Partial",Scoring!$C$7,IF(P97="No",Scoring!$C$8,""))) -> 0 | R97: =IF(Q97="",0,G97*Q97) -> 0 | S97: =IF(Q97="",0,G97) -> 3 | T97: =IF(OR(P97="Partial",P97="No"),I97,"") -> Run a regular improvement cycle that turns insights from research, analytics, feedback, incidents and health checks into prioritised changes, releases them, and measures their impact. | U97: =IF(Q97="",0,(1-Q97)*G97/SUMIFS($S$2:$S$97,$B$2:$B$97,B97)*INDEX(Scoring!$C$18:$C$27,MATCH(B97,Scoring!$B$18:$B$27,0))) -> 1.0714286 | V97: =IF(U97>0,U97+IF(AND(H97="Y",P97="No"),1000,0)+ROW()/100000,0) -> 1.0723986 | W97: GOV.UK Service Standard (14 points) | X97: https://www.gov.uk/service-manual/service-standard

Sheet Scoring
B1: Scoring - detailed criteria
B2: Yellow cells are editable. Results use the Test answer column on the Criteria tab. Earned/Available are weighted (weight x answer points).
B4: Parameters
B5: Answer | C5: Points
B6: Yes | C6: 1
B7: Partial | C7: 0.5
B8: No | C8: 0
B10: Overall score cap when any critical criterion is 'No' | C10: 60 | E10: Proposed defaults - validate with test assessments before use.
B11: Rating threshold - Healthy (score at or above) | C11: 85
B12: Rating threshold - Good, with gaps (at or above) | C12: 70
B13: Rating threshold - Needs attention (at or above); below = At risk | C13: 50
B16: Category results
B17: Category | C17: Points (of 100) | D17: Criteria | E17: Earned | F17: Available | G17: Category % | H17: Score | I17: What good looks like
B18: Accessibility | C18: 20 | D18: =COUNTIF(Criteria!$B$2:$B$97,B18) -> 17 | E18: =SUMIFS(Criteria!$R$2:$R$97,Criteria!$B$2:$B$97,B18) -> 27 | F18: =SUMIFS(Criteria!$S$2:$S$97,Criteria!$B$2:$B$97,B18) -> 33 | G18: =IF(F18=0,"",E18/F18) -> 0.81818182 | H18: =IF(F18=0,"",G18*C18) -> 16.363636 | I18: Disabled people, including blind and low vision users, can perceive, operate and complete the service.
B19: Usability and design | C19: 15 | D19: =COUNTIF(Criteria!$B$2:$B$97,B19) -> 12 | E19: =SUMIFS(Criteria!$R$2:$R$97,Criteria!$B$2:$B$97,B19) -> 17 | F19: =SUMIFS(Criteria!$S$2:$S$97,Criteria!$B$2:$B$97,B19) -> 23 | G19: =IF(F19=0,"",E19/F19) -> 0.73913043 | H19: =IF(F19=0,"",G19*C19) -> 11.086957 | I19: The service is easy to use, works across devices and is designed around user needs.
B20: Content and tone of voice | C20: 8 | D20: =COUNTIF(Criteria!$B$2:$B$97,B20) -> 8 | E20: =SUMIFS(Criteria!$R$2:$R$97,Criteria!$B$2:$B$97,B20) -> 8.5 | F20: =SUMIFS(Criteria!$S$2:$S$97,Criteria!$B$2:$B$97,B20) -> 12 | G20: =IF(F20=0,"",E20/F20) -> 0.70833333 | H20: =IF(F20=0,"",G20*C20) -> 5.6666667 | I20: Content is plain, accurate, consistent and written in the organisation's voice.
B21: Brand and visual consistency | C21: 6 | D21: =COUNTIF(Criteria!$B$2:$B$97,B21) -> 6 | E21: =SUMIFS(Criteria!$R$2:$R$97,Criteria!$B$2:$B$97,B21) -> 8 | F21: =SUMIFS(Criteria!$S$2:$S$97,Criteria!$B$2:$B$97,B21) -> 12 | G21: =IF(F21=0,"",E21/F21) -> 0.66666667 | H21: =IF(F21=0,"",G21*C21) -> 4 | I21: The service looks and feels consistent with the organisation and NZ Government identity.
B22: Security and privacy | C22: 14 | D22: =COUNTIF(Criteria!$B$2:$B$97,B22) -> 11 | E22: =SUMIFS(Criteria!$R$2:$R$97,Criteria!$B$2:$B$97,B22) -> 18.5 | F22: =SUMIFS(Criteria!$S$2:$S$97,Criteria!$B$2:$B$97,B22) -> 24 | G22: =IF(F22=0,"",E22/F22) -> 0.77083333 | H22: =IF(F22=0,"",G22*C22) -> 10.791667 | I22: The service protects users and their information and meets NZ security and privacy obligations.
B23: Reliability, observability and service levels | C23: 13 | D23: =COUNTIF(Criteria!$B$2:$B$97,B23) -> 11 | E23: =SUMIFS(Criteria!$R$2:$R$97,Criteria!$B$2:$B$97,B23) -> 14.5 | F23: =SUMIFS(Criteria!$S$2:$S$97,Criteria!$B$2:$B$97,B23) -> 21 | G23: =IF(F23=0,"",E23/F23) -> 0.69047619 | H23: =IF(F23=0,"",G23*C23) -> 8.9761905 | I23: The service is available, monitored, and issues are found and fixed quickly.
B24: Support and contact channels | C24: 8 | D24: =COUNTIF(Criteria!$B$2:$B$97,B24) -> 7 | E24: =SUMIFS(Criteria!$R$2:$R$97,Criteria!$B$2:$B$97,B24) -> 10.5 | F24: =SUMIFS(Criteria!$S$2:$S$97,Criteria!$B$2:$B$97,B24) -> 14 | G24: =IF(F24=0,"",E24/F24) -> 0.75 | H24: =IF(F24=0,"",G24*C24) -> 6 | I24: People can get help, in the channel that works for them, when they need it.
B25: Legal and regulatory | C25: 6 | D25: =COUNTIF(Criteria!$B$2:$B$97,B25) -> 9 | E25: =SUMIFS(Criteria!$R$2:$R$97,Criteria!$B$2:$B$97,B25) -> 9 | F25: =SUMIFS(Criteria!$S$2:$S$97,Criteria!$B$2:$B$97,B25) -> 13 | G25: =IF(F25=0,"",E25/F25) -> 0.69230769 | H25: =IF(F25=0,"",G25*C25) -> 4.1538462 | I25: The service meets NZ legal and public sector obligations about access to services and information.
B26: Content management and governance | C26: 5 | D26: =COUNTIF(Criteria!$B$2:$B$97,B26) -> 8 | E26: =SUMIFS(Criteria!$R$2:$R$97,Criteria!$B$2:$B$97,B26) -> 12 | F26: =SUMIFS(Criteria!$S$2:$S$97,Criteria!$B$2:$B$97,B26) -> 16 | G26: =IF(F26=0,"",E26/F26) -> 0.75 | H26: =IF(F26=0,"",G26*C26) -> 3.75 | I26: The service and its content have clear ownership, workflows and ongoing funding.
B27: Measurement and continuous improvement | C27: 5 | D27: =COUNTIF(Criteria!$B$2:$B$97,B27) -> 7 | E27: =SUMIFS(Criteria!$R$2:$R$97,Criteria!$B$2:$B$97,B27) -> 8.5 | F27: =SUMIFS(Criteria!$S$2:$S$97,Criteria!$B$2:$B$97,B27) -> 14 | G27: =IF(F27=0,"",E27/F27) -> 0.60714286 | H27: =IF(F27=0,"",G27*C27) -> 3.0357143 | I27: Performance and satisfaction are measured and used to improve the service.
B28: Total | C28: =SUM(C18:C27) -> 100 | D28: =SUM(D18:D27) -> 96 | I28: =IF(C28=100,"Category points total 100 - OK","CHECK: category points must total 100") -> Category points total 100 - OK
B30: Overall result
B31: Raw score (out of 100, rescaled for N/A categories) | C31: =IF(SUMIFS(C18:C27,F18:F27,">0")=0,"",SUM(H18:H27)/SUMIFS(C18:C27,F18:F27,">0")*100) -> 73.824677
B32: Critical criteria answered 'No' | C32: =COUNTIFS(Criteria!$H$2:$H$97,"Y",Criteria!$P$2:$P$97,"No") -> 0
B33: Final score (after critical cap) | C33: =IF(C31="","",IF(C32>0,MIN(C31,C10),C31)) -> 73.824677
B34: Rating | C34: =IF(C33="","",IF(C33>=C11,"Healthy",IF(C33>=C12,"Good, with gaps",IF(C33>=C13,"Needs attention","At risk")))) -> Good, with gaps
B35: Criteria answered | C35: =COUNTIF(Criteria!$P$2:$P$97,"Yes")+COUNTIF(Criteria!$P$2:$P$97,"Partial")+COUNTIF(Criteria!$P$2:$P$97,"No") -> 95
B36: Criteria N/A | C36: =COUNTIF(Criteria!$P$2:$P$97,"N/A") -> 1
B37: Criteria not yet answered | C37: =COUNTBLANK(Criteria!$P$2:$P$97) -> 0
B40: Key recommendations (top 5 by points lost; critical failures first)
B41: Rank | C41: ID | D41: Points lost | E41: Recommendation
B42: 1 | C42: =IF(LARGE(Criteria!$V$2:$V$97,1)=0,"",INDEX(Criteria!$A$2:$A$97,MATCH(LARGE(Criteria!$V$2:$V$97,1),Criteria!$V$2:$V$97,0))) -> BRD-01 | D42: =IF(C42="","",INDEX(Criteria!$U$2:$U$97,MATCH(C42,Criteria!$A$2:$A$97,0))) -> 1.5 | E42: =IF(C42="","",INDEX(Criteria!$I$2:$I$97,MATCH(C42,Criteria!$A$2:$A$97,0))) -> Apply the organisation's brand guidelines, including font types, colour palette and styling, to minimise experience inconsistency across applications.
B43: 2 | C43: =IF(LARGE(Criteria!$V$2:$V$97,2)=0,"",INDEX(Criteria!$A$2:$A$97,MATCH(LARGE(Criteria!$V$2:$V$97,2),Criteria!$V$2:$V$97,0))) -> CON-02 | D43: =IF(C43="","",INDEX(Criteria!$U$2:$U$97,MATCH(C43,Criteria!$A$2:$A$97,0))) -> 1.3333333 | E43: =IF(C43="","",INDEX(Criteria!$I$2:$I$97,MATCH(C43,Criteria!$A$2:$A$97,0))) -> Apply the organisation's tone of voice guidelines to all service content, including error messages, emails and letters, and review content against them.
B44: 3 | C44: =IF(LARGE(Criteria!$V$2:$V$97,3)=0,"",INDEX(Criteria!$A$2:$A$97,MATCH(LARGE(Criteria!$V$2:$V$97,3),Criteria!$V$2:$V$97,0))) -> UXD-08 | D44: =IF(C44="","",INDEX(Criteria!$U$2:$U$97,MATCH(C44,Criteria!$A$2:$A$97,0))) -> 1.3043478 | E44: =IF(C44="","",INDEX(Criteria!$I$2:$I$97,MATCH(C44,Criteria!$A$2:$A$97,0))) -> Use and contribute to a shared design system so components are tested, accessible and consistent across the organisation's services.
B45: 4 | C45: =IF(LARGE(Criteria!$V$2:$V$97,4)=0,"",INDEX(Criteria!$A$2:$A$97,MATCH(LARGE(Criteria!$V$2:$V$97,4),Criteria!$V$2:$V$97,0))) -> OPS-03 | D45: =IF(C45="","",INDEX(Criteria!$U$2:$U$97,MATCH(C45,Criteria!$A$2:$A$97,0))) -> 1.2380952 | E45: =IF(C45="","",INDEX(Criteria!$I$2:$I$97,MATCH(C45,Criteria!$A$2:$A$97,0))) -> Centralise logs, metrics and traces with correlation IDs so issues can be traced across components and suppliers.
B46: 5 | C46: =IF(LARGE(Criteria!$V$2:$V$97,5)=0,"",INDEX(Criteria!$A$2:$A$97,MATCH(LARGE(Criteria!$V$2:$V$97,5),Criteria!$V$2:$V$97,0))) -> SEC-08 | D46: =IF(C46="","",INDEX(Criteria!$U$2:$U$97,MATCH(C46,Criteria!$A$2:$A$97,0))) -> 1.1666667 | E46: =IF(C46="","",INDEX(Criteria!$I$2:$I$97,MATCH(C46,Criteria!$A$2:$A$97,0))) -> Document and exercise a privacy breach response process that meets the notifiable privacy breach requirements of the Privacy Act 2020.

Sheet Criteria (simple)
A1: ID | B1: Category | C1: Question | D1: Critical (Y/N) | E1: Recommendation (shown if Partial/No) | F1: Source | G1: NZ status | H1: Applies to | J1: Answer | K1: Answer points | L1: Earned | M1: Available | N1: Max points (all answered) | O1: Report recommendation | P1: Points lost | Q1: Rank key | R1: Supporting link
A2: ACC-01 | B2: =INDEX(Criteria!$B$2:$B$97,MATCH($A2,Criteria!$A$2:$A$97,0)) -> Accessibility | C2: =INDEX(Criteria!$D$2:$D$97,MATCH($A2,Criteria!$A$2:$A$97,0)) -> Has the service been assessed against WCAG 2.2 Level AA in the last 12 months, including manual testing (not automated tools alone)? | D2: =INDEX(Criteria!$H$2:$H$97,MATCH($A2,Criteria!$A$2:$A$97,0)) -> Y | E2: =INDEX(Criteria!$I$2:$I$97,MATCH($A2,Criteria!$A$2:$A$97,0)) -> Commission or complete a WCAG 2.2 AA assessment that includes manual and assistive technology testing, covering every page in each complete process, and repeat it at least annually or after major change. | F2: =INDEX(Criteria!$J$2:$J$97,MATCH($A2,Criteria!$A$2:$A$97,0)) -> NZ Government Web Accessibility Standard; WCAG 2.2 | G2: =INDEX(Criteria!$L$2:$L$97,MATCH($A2,Criteria!$A$2:$A$97,0)) -> Mandatory (NZ) | H2: =INDEX(Criteria!$M$2:$M$97,MATCH($A2,Criteria!$A$2:$A$97,0)) -> All | J2: Yes | K2: =IF(J2="Yes",'Scoring (simple)'!$C$6,IF(J2="Partial",'Scoring (simple)'!$C$7,IF(J2="No",'Scoring (simple)'!$C$8,""))) -> 1 | L2: =IF(K2="",0,K2) -> 1 | M2: =IF(K2="",0,1) -> 1 | N2: =INDEX('Scoring (simple)'!$C$18:$C$27,MATCH(B2,'Scoring (simple)'!$B$18:$B$27,0))/COUNTIF($B$2:$B$20,B2) -> 6.6666667 | O2: =IF(OR(J2="Partial",J2="No"),E2,"") | P2: =IF(K2="",0,(1-K2)/SUMIFS($M$2:$M$20,$B$2:$B$20,B2)*INDEX('Scoring (simple)'!$C$18:$C$27,MATCH(B2,'Scoring (simple)'!$B$18:$B$27,0))) -> 0 | Q2: =IF(P2>0,P2+IF(AND(D2="Y",J2="No"),1000,0)+ROW()/100000,0) -> 0 | R2: =IF(INDEX(Criteria!$X$2:$X$97,MATCH($A2,Criteria!$A$2:$A$97,0))="",INDEX(Criteria!$W$2:$W$97,MATCH($A2,Criteria!$A$2:$A$97,0)),HYPERLINK(INDEX(Criteria!$X$2:$X$97,MATCH($A2,Criteria!$A$2:$A$97,0)),INDEX(Criteria!$W$2:$W$97,MATCH($A2,Criteria!$A$2:$A$97,0)))) -> NZ Web Accessibility Standard 1.2
A3: ACC-02 | B3: =INDEX(Criteria!$B$2:$B$97,MATCH($A3,Criteria!$A$2:$A$97,0)) -> Accessibility | C3: =INDEX(Criteria!$D$2:$D$97,MATCH($A3,Criteria!$A$2:$A$97,0)) -> Have the service's key tasks been tested end to end with screen readers on both desktop and mobile (for example NVDA or JAWS, VoiceOver, TalkBack)? | D3: =INDEX(Criteria!$H$2:$H$97,MATCH($A3,Criteria!$A$2:$A$97,0)) -> N | E3: =INDEX(Criteria!$I$2:$I$97,MATCH($A3,Criteria!$A$2:$A$97,0)) -> Test every key task with at least one desktop and one mobile screen reader, ideally including blind and low vision users, and fix issues that stop tasks being completed. | F3: =INDEX(Criteria!$J$2:$J$97,MATCH($A3,Criteria!$A$2:$A$97,0)) -> WCAG 2.2 SC 4.1.2, 1.3.1; W3C WCAG-EM | G3: =INDEX(Criteria!$L$2:$L$97,MATCH($A3,Criteria!$A$2:$A$97,0)) -> Recommended (NZ) | H3: =INDEX(Criteria!$M$2:$M$97,MATCH($A3,Criteria!$A$2:$A$97,0)) -> All | J3: Partial | K3: =IF(J3="Yes",'Scoring (simple)'!$C$6,IF(J3="Partial",'Scoring (simple)'!$C$7,IF(J3="No",'Scoring (simple)'!$C$8,""))) -> 0.5 | L3: =IF(K3="",0,K3) -> 0.5 | M3: =IF(K3="",0,1) -> 1 | N3: =INDEX('Scoring (simple)'!$C$18:$C$27,MATCH(B3,'Scoring (simple)'!$B$18:$B$27,0))/COUNTIF($B$2:$B$20,B3) -> 6.6666667 | O3: =IF(OR(J3="Partial",J3="No"),E3,"") -> Test every key task with at least one desktop and one mobile screen reader, ideally including blind and low vision users, and fix issues that stop tasks being completed. | P3: =IF(K3="",0,(1-K3)/SUMIFS($M$2:$M$20,$B$2:$B$20,B3)*INDEX('Scoring (simple)'!$C$18:$C$27,MATCH(B3,'Scoring (simple)'!$B$18:$B$27,0))) -> 3.3333333 | Q3: =IF(P3>0,P3+IF(AND(D3="Y",J3="No"),1000,0)+ROW()/100000,0) -> 3.3333633 | R3: =IF(INDEX(Criteria!$X$2:$X$97,MATCH($A3,Criteria!$A$2:$A$97,0))="",INDEX(Criteria!$W$2:$W$97,MATCH($A3,Criteria!$A$2:$A$97,0)),HYPERLINK(INDEX(Criteria!$X$2:$X$97,MATCH($A3,Criteria!$A$2:$A$97,0)),INDEX(Criteria!$W$2:$W$97,MATCH($A3,Criteria!$A$2:$A$97,0)))) -> W3C accessibility evaluation methodology
A4: ACC-05 | B4: =INDEX(Criteria!$B$2:$B$97,MATCH($A4,Criteria!$A$2:$A$97,0)) -> Accessibility | C4: =INDEX(Criteria!$D$2:$D$97,MATCH($A4,Criteria!$A$2:$A$97,0)) -> Can every function be used with a keyboard alone, with no keyboard traps, a logical focus order, and a visible focus indicator that is not hidden by other content? | D4: =INDEX(Criteria!$H$2:$H$97,MATCH($A4,Criteria!$A$2:$A$97,0)) -> Y | E4: =INDEX(Criteria!$I$2:$I$97,MATCH($A4,Criteria!$A$2:$A$97,0)) -> Make all functionality keyboard operable, remove keyboard traps, keep focus order logical and ensure the focus indicator is always visible and not obscured by sticky headers, banners or overlays. | F4: =INDEX(Criteria!$J$2:$J$97,MATCH($A4,Criteria!$A$2:$A$97,0)) -> WCAG 2.2 SC 2.1.1, 2.1.2, 2.4.3, 2.4.7, 2.4.11 | G4: =INDEX(Criteria!$L$2:$L$97,MATCH($A4,Criteria!$A$2:$A$97,0)) -> Mandatory (NZ) | H4: =INDEX(Criteria!$M$2:$M$97,MATCH($A4,Criteria!$A$2:$A$97,0)) -> All | J4: Yes | K4: =IF(J4="Yes",'Scoring (simple)'!$C$6,IF(J4="Partial",'Scoring (simple)'!$C$7,IF(J4="No",'Scoring (simple)'!$C$8,""))) -> 1 | L4: =IF(K4="",0,K4) -> 1 | M4: =IF(K4="",0,1) -> 1 | N4: =INDEX('Scoring (simple)'!$C$18:$C$27,MATCH(B4,'Scoring (simple)'!$B$18:$B$27,0))/COUNTIF($B$2:$B$20,B4) -> 6.6666667 | O4: =IF(OR(J4="Partial",J4="No"),E4,"") | P4: =IF(K4="",0,(1-K4)/SUMIFS($M$2:$M$20,$B$2:$B$20,B4)*INDEX('Scoring (simple)'!$C$18:$C$27,MATCH(B4,'Scoring (simple)'!$B$18:$B$27,0))) -> 0 | Q4: =IF(P4>0,P4+IF(AND(D4="Y",J4="No"),1000,0)+ROW()/100000,0) -> 0 | R4: =IF(INDEX(Criteria!$X$2:$X$97,MATCH($A4,Criteria!$A$2:$A$97,0))="",INDEX(Criteria!$W$2:$W$97,MATCH($A4,Criteria!$A$2:$A$97,0)),HYPERLINK(INDEX(Criteria!$X$2:$X$97,MATCH($A4,Criteria!$A$2:$A$97,0)),INDEX(Criteria!$W$2:$W$97,MATCH($A4,Criteria!$A$2:$A$97,0)))) -> WCAG 2.2 quick reference
A5: UXD-01 | B5: =INDEX(Criteria!$B$2:$B$97,MATCH($A5,Criteria!$A$2:$A$97,0)) -> Usability and design | C5: =INDEX(Criteria!$D$2:$D$97,MATCH($A5,Criteria!$A$2:$A$97,0)) -> Is the service responsive or adaptive, so content and controls scale and reflow correctly across phone, tablet and desktop screen sizes and orientations? | D5: =INDEX(Criteria!$H$2:$H$97,MATCH($A5,Criteria!$A$2:$A$97,0)) -> Y | E5: =INDEX(Criteria!$I$2:$I$97,MATCH($A5,Criteria!$A$2:$A$97,0)) -> Ensure the application is adaptive, so content and objects scale to the user's screen size and orientation, and test key tasks on the devices your users actually use. | F5: =INDEX(Criteria!$J$2:$J$97,MATCH($A5,Criteria!$A$2:$A$97,0)) -> OMB M-23-22 (design pillar); WCAG 2.2 SC 1.3.4, 1.4.10 | G5: =INDEX(Criteria!$L$2:$L$97,MATCH($A5,Criteria!$A$2:$A$97,0)) -> Good practice | H5: =INDEX(Criteria!$M$2:$M$97,MATCH($A5,Criteria!$A$2:$A$97,0)) -> All | J5: Yes | K5: =IF(J5="Yes",'Scoring (simple)'!$C$6,IF(J5="Partial",'Scoring (simple)'!$C$7,IF(J5="No",'Scoring (simple)'!$C$8,""))) -> 1 | L5: =IF(K5="",0,K5) -> 1 | M5: =IF(K5="",0,1) -> 1 | N5: =INDEX('Scoring (simple)'!$C$18:$C$27,MATCH(B5,'Scoring (simple)'!$B$18:$B$27,0))/COUNTIF($B$2:$B$20,B5) -> 7.5 | O5: =IF(OR(J5="Partial",J5="No"),E5,"") | P5: =IF(K5="",0,(1-K5)/SUMIFS($M$2:$M$20,$B$2:$B$20,B5)*INDEX('Scoring (simple)'!$C$18:$C$27,MATCH(B5,'Scoring (simple)'!$B$18:$B$27,0))) -> 0 | Q5: =IF(P5>0,P5+IF(AND(D5="Y",J5="No"),1000,0)+ROW()/100000,0) -> 0 | R5: =IF(INDEX(Criteria!$X$2:$X$97,MATCH($A5,Criteria!$A$2:$A$97,0))="",INDEX(Criteria!$W$2:$W$97,MATCH($A5,Criteria!$A$2:$A$97,0)),HYPERLINK(INDEX(Criteria!$X$2:$X$97,MATCH($A5,Criteria!$A$2:$A$97,0)),INDEX(Criteria!$W$2:$W$97,MATCH($A5,Criteria!$A$2:$A$97,0)))) -> GOV.UK: services that work on mobile
A6: UXD-02 | B6: =INDEX(Criteria!$B$2:$B$97,MATCH($A6,Criteria!$A$2:$A$97,0)) -> Usability and design | C6: =INDEX(Criteria!$D$2:$D$97,MATCH($A6,Criteria!$A$2:$A$97,0)) -> Has research with real users of this service (not proxies) informed its design or changes in the last 12 months? | D6: =INDEX(Criteria!$H$2:$H$97,MATCH($A6,Criteria!$A$2:$A$97,0)) -> N | E6: =INDEX(Criteria!$I$2:$I$97,MATCH($A6,Criteria!$A$2:$A$97,0)) -> Run regular user research with people who use the service, including those who struggle, and record how findings change the service. | F6: =INDEX(Criteria!$J$2:$J$97,MATCH($A6,Criteria!$A$2:$A$97,0)) -> GOV.UK Service Standard point 1; AU DSS 2.0 criterion 2; Digital Service Design Standard | G6: =INDEX(Criteria!$L$2:$L$97,MATCH($A6,Criteria!$A$2:$A$97,0)) -> Recommended (NZ) | H6: =INDEX(Criteria!$M$2:$M$97,MATCH($A6,Criteria!$A$2:$A$97,0)) -> All | J6: Partial | K6: =IF(J6="Yes",'Scoring (simple)'!$C$6,IF(J6="Partial",'Scoring (simple)'!$C$7,IF(J6="No",'Scoring (simple)'!$C$8,""))) -> 0.5 | L6: =IF(K6="",0,K6) -> 0.5 | M6: =IF(K6="",0,1) -> 1 | N6: =INDEX('Scoring (simple)'!$C$18:$C$27,MATCH(B6,'Scoring (simple)'!$B$18:$B$27,0))/COUNTIF($B$2:$B$20,B6) -> 7.5 | O6: =IF(OR(J6="Partial",J6="No"),E6,"") -> Run regular user research with people who use the service, including those who struggle, and record how findings change the service. | P6: =IF(K6="",0,(1-K6)/SUMIFS($M$2:$M$20,$B$2:$B$20,B6)*INDEX('Scoring (simple)'!$C$18:$C$27,MATCH(B6,'Scoring (simple)'!$B$18:$B$27,0))) -> 3.75 | Q6: =IF(P6>0,P6+IF(AND(D6="Y",J6="No"),1000,0)+ROW()/100000,0) -> 3.75006 | R6: =IF(INDEX(Criteria!$X$2:$X$97,MATCH($A6,Criteria!$A$2:$A$97,0))="",INDEX(Criteria!$W$2:$W$97,MATCH($A6,Criteria!$A$2:$A$97,0)),HYPERLINK(INDEX(Criteria!$X$2:$X$97,MATCH($A6,Criteria!$A$2:$A$97,0)),INDEX(Criteria!$W$2:$W$97,MATCH($A6,Criteria!$A$2:$A$97,0)))) -> GOV.UK: understand users and needs
A7: CON-01 | B7: =INDEX(Criteria!$B$2:$B$97,MATCH($A7,Criteria!$A$2:$A$97,0)) -> Content and tone of voice | C7: =INDEX(Criteria!$D$2:$D$97,MATCH($A7,Criteria!$A$2:$A$97,0)) -> Is content written in plain language appropriate to the intended audience, and has it been checked (for example readability testing or user testing)? | D7: =INDEX(Criteria!$H$2:$H$97,MATCH($A7,Criteria!$A$2:$A$97,0)) -> N | E7: =INDEX(Criteria!$I$2:$I$97,MATCH($A7,Criteria!$A$2:$A$97,0)) -> Write and review all public content in plain language, test it with users, and follow the agency's Plain Language Act processes. | F7: =INDEX(Criteria!$J$2:$J$97,MATCH($A7,Criteria!$A$2:$A$97,0)) -> Plain Language Act 2022 | G7: =INDEX(Criteria!$L$2:$L$97,MATCH($A7,Criteria!$A$2:$A$97,0)) -> Mandatory (NZ) | H7: =INDEX(Criteria!$M$2:$M$97,MATCH($A7,Criteria!$A$2:$A$97,0)) -> Public-facing | J7: No | K7: =IF(J7="Yes",'Scoring (simple)'!$C$6,IF(J7="Partial",'Scoring (simple)'!$C$7,IF(J7="No",'Scoring (simple)'!$C$8,""))) -> 0 | L7: =IF(K7="",0,K7) -> 0 | M7: =IF(K7="",0,1) -> 1 | N7: =INDEX('Scoring (simple)'!$C$18:$C$27,MATCH(B7,'Scoring (simple)'!$B$18:$B$27,0))/COUNTIF($B$2:$B$20,B7) -> 8 | O7: =IF(OR(J7="Partial",J7="No"),E7,"") -> Write and review all public content in plain language, test it with users, and follow the agency's Plain Language Act processes. | P7: =IF(K7="",0,(1-K7)/SUMIFS($M$2:$M$20,$B$2:$B$20,B7)*INDEX('Scoring (simple)'!$C$18:$C$27,MATCH(B7,'Scoring (simple)'!$B$18:$B$27,0))) -> 8 | Q7: =IF(P7>0,P7+IF(AND(D7="Y",J7="No"),1000,0)+ROW()/100000,0) -> 8.00007 | R7: =IF(INDEX(Criteria!$X$2:$X$97,MATCH($A7,Criteria!$A$2:$A$97,0))="",INDEX(Criteria!$W$2:$W$97,MATCH($A7,Criteria!$A$2:$A$97,0)),HYPERLINK(INDEX(Criteria!$X$2:$X$97,MATCH($A7,Criteria!$A$2:$A$97,0)),INDEX(Criteria!$W$2:$W$97,MATCH($A7,Criteria!$A$2:$A$97,0)))) -> Plain Language Act 2022
A8: BRD-01 | B8: =INDEX(Criteria!$B$2:$B$97,MATCH($A8,Criteria!$A$2:$A$97,0)) -> Brand and visual consistency | C8: =INDEX(Criteria!$D$2:$D$97,MATCH($A8,Criteria!$A$2:$A$97,0)) -> Does the service apply the organisation's brand guidelines - logos, font types, colour palette, iconography and styling? | D8: =INDEX(Criteria!$H$2:$H$97,MATCH($A8,Criteria!$A$2:$A$97,0)) -> N | E8: =INDEX(Criteria!$I$2:$I$97,MATCH($A8,Criteria!$A$2:$A$97,0)) -> Apply the organisation's brand guidelines, including font types, colour palette and styling, to minimise experience inconsistency across applications. | F8: =INDEX(Criteria!$J$2:$J$97,MATCH($A8,Criteria!$A$2:$A$97,0)) -> Organisation brand guidelines; OMB M-23-22 (branding pillar) | G8: =INDEX(Criteria!$L$2:$L$97,MATCH($A8,Criteria!$A$2:$A$97,0)) -> Good practice | H8: =INDEX(Criteria!$M$2:$M$97,MATCH($A8,Criteria!$A$2:$A$97,0)) -> All | J8: Yes | K8: =IF(J8="Yes",'Scoring (simple)'!$C$6,IF(J8="Partial",'Scoring (simple)'!$C$7,IF(J8="No",'Scoring (simple)'!$C$8,""))) -> 1 | L8: =IF(K8="",0,K8) -> 1 | M8: =IF(K8="",0,1) -> 1 | N8: =INDEX('Scoring (simple)'!$C$18:$C$27,MATCH(B8,'Scoring (simple)'!$B$18:$B$27,0))/COUNTIF($B$2:$B$20,B8) -> 6 | O8: =IF(OR(J8="Partial",J8="No"),E8,"") | P8: =IF(K8="",0,(1-K8)/SUMIFS($M$2:$M$20,$B$2:$B$20,B8)*INDEX('Scoring (simple)'!$C$18:$C$27,MATCH(B8,'Scoring (simple)'!$B$18:$B$27,0))) -> 0 | Q8: =IF(P8>0,P8+IF(AND(D8="Y",J8="No"),1000,0)+ROW()/100000,0) -> 0 | R8: =IF(INDEX(Criteria!$X$2:$X$97,MATCH($A8,Criteria!$A$2:$A$97,0))="",INDEX(Criteria!$W$2:$W$97,MATCH($A8,Criteria!$A$2:$A$97,0)),HYPERLINK(INDEX(Criteria!$X$2:$X$97,MATCH($A8,Criteria!$A$2:$A$97,0)),INDEX(Criteria!$W$2:$W$97,MATCH($A8,Criteria!$A$2:$A$97,0)))) -> Use your organisation's brand guidelines
A9: SEC-01 | B9: =INDEX(Criteria!$B$2:$B$97,MATCH($A9,Criteria!$A$2:$A$97,0)) -> Security and privacy | C9: =INDEX(Criteria!$D$2:$D$97,MATCH($A9,Criteria!$A$2:$A$97,0)) -> Has the service completed a security risk assessment and certification and accreditation (C&A) in line with the NZISM, and is it reviewed after significant change? | D9: =INDEX(Criteria!$H$2:$H$97,MATCH($A9,Criteria!$A$2:$A$97,0)) -> Y | E9: =INDEX(Criteria!$I$2:$I$97,MATCH($A9,Criteria!$A$2:$A$97,0)) -> Complete a security risk assessment and certification and accreditation before go-live, and refresh it after significant change or on a set cycle. | F9: =INDEX(Criteria!$J$2:$J$97,MATCH($A9,Criteria!$A$2:$A$97,0)) -> NZ Information Security Manual (NZISM); Protective Security Requirements | G9: =INDEX(Criteria!$L$2:$L$97,MATCH($A9,Criteria!$A$2:$A$97,0)) -> Mandatory (NZ) | H9: =INDEX(Criteria!$M$2:$M$97,MATCH($A9,Criteria!$A$2:$A$97,0)) -> All | J9: Yes | K9: =IF(J9="Yes",'Scoring (simple)'!$C$6,IF(J9="Partial",'Scoring (simple)'!$C$7,IF(J9="No",'Scoring (simple)'!$C$8,""))) -> 1 | L9: =IF(K9="",0,K9) -> 1 | M9: =IF(K9="",0,1) -> 1 | N9: =INDEX('Scoring (simple)'!$C$18:$C$27,MATCH(B9,'Scoring (simple)'!$B$18:$B$27,0))/COUNTIF($B$2:$B$20,B9) -> 4.6666667 | O9: =IF(OR(J9="Partial",J9="No"),E9,"") | P9: =IF(K9="",0,(1-K9)/SUMIFS($M$2:$M$20,$B$2:$B$20,B9)*INDEX('Scoring (simple)'!$C$18:$C$27,MATCH(B9,'Scoring (simple)'!$B$18:$B$27,0))) -> 0 | Q9: =IF(P9>0,P9+IF(AND(D9="Y",J9="No"),1000,0)+ROW()/100000,0) -> 0 | R9: =IF(INDEX(Criteria!$X$2:$X$97,MATCH($A9,Criteria!$A$2:$A$97,0))="",INDEX(Criteria!$W$2:$W$97,MATCH($A9,Criteria!$A$2:$A$97,0)),HYPERLINK(INDEX(Criteria!$X$2:$X$97,MATCH($A9,Criteria!$A$2:$A$97,0)),INDEX(Criteria!$W$2:$W$97,MATCH($A9,Criteria!$A$2:$A$97,0)))) -> NZ Information Security Manual
A10: SEC-02 | B10: =INDEX(Criteria!$B$2:$B$97,MATCH($A10,Criteria!$A$2:$A$97,0)) -> Security and privacy | C10: =INDEX(Criteria!$D$2:$D$97,MATCH($A10,Criteria!$A$2:$A$97,0)) -> Has the application been verified against the OWASP Application Security Verification Standard at a level appropriate to its risk (Level 1 minimum, Level 2 if it handles personal information)? | D10: =INDEX(Criteria!$H$2:$H$97,MATCH($A10,Criteria!$A$2:$A$97,0)) -> N | E10: =INDEX(Criteria!$I$2:$I$97,MATCH($A10,Criteria!$A$2:$A$97,0)) -> Verify the application against OWASP ASVS 5.0 at the appropriate level and track gaps to remediation. | F10: =INDEX(Criteria!$J$2:$J$97,MATCH($A10,Criteria!$A$2:$A$97,0)) -> OWASP ASVS 5.0.0 (chapters V1-V17, at the level chosen) | G10: =INDEX(Criteria!$L$2:$L$97,MATCH($A10,Criteria!$A$2:$A$97,0)) -> Good practice | H10: =INDEX(Criteria!$M$2:$M$97,MATCH($A10,Criteria!$A$2:$A$97,0)) -> All | J10: Partial | K10: =IF(J10="Yes",'Scoring (simple)'!$C$6,IF(J10="Partial",'Scoring (simple)'!$C$7,IF(J10="No",'Scoring (simple)'!$C$8,""))) -> 0.5 | L10: =IF(K10="",0,K10) -> 0.5 | M10: =IF(K10="",0,1) -> 1 | N10: =INDEX('Scoring (simple)'!$C$18:$C$27,MATCH(B10,'Scoring (simple)'!$B$18:$B$27,0))/COUNTIF($B$2:$B$20,B10) -> 4.6666667 | O10: =IF(OR(J10="Partial",J10="No"),E10,"") -> Verify the application against OWASP ASVS 5.0 at the appropriate level and track gaps to remediation. | P10: =IF(K10="",0,(1-K10)/SUMIFS($M$2:$M$20,$B$2:$B$20,B10)*INDEX('Scoring (simple)'!$C$18:$C$27,MATCH(B10,'Scoring (simple)'!$B$18:$B$27,0))) -> 2.3333333 | Q10: =IF(P10>0,P10+IF(AND(D10="Y",J10="No"),1000,0)+ROW()/100000,0) -> 2.3334333 | R10: =IF(INDEX(Criteria!$X$2:$X$97,MATCH($A10,Criteria!$A$2:$A$97,0))="",INDEX(Criteria!$W$2:$W$97,MATCH($A10,Criteria!$A$2:$A$97,0)),HYPERLINK(INDEX(Criteria!$X$2:$X$97,MATCH($A10,Criteria!$A$2:$A$97,0)),INDEX(Criteria!$W$2:$W$97,MATCH($A10,Criteria!$A$2:$A$97,0)))) -> OWASP ASVS project page
A11: SEC-07 | B11: =INDEX(Criteria!$B$2:$B$97,MATCH($A11,Criteria!$A$2:$A$97,0)) -> Security and privacy | C11: =INDEX(Criteria!$D$2:$D$97,MATCH($A11,Criteria!$A$2:$A$97,0)) -> Is a privacy statement available from every page, explaining what personal information is collected, why, who it's shared with, and how to access and correct it? | D11: =INDEX(Criteria!$H$2:$H$97,MATCH($A11,Criteria!$A$2:$A$97,0)) -> Y | E11: =INDEX(Criteria!$I$2:$I$97,MATCH($A11,Criteria!$A$2:$A$97,0)) -> Publish a clear privacy statement linked from every page that meets Privacy Act 2020 information privacy principle 3 and the Web Usability Standard. | F11: =INDEX(Criteria!$J$2:$J$97,MATCH($A11,Criteria!$A$2:$A$97,0)) -> Privacy Act 2020 IPP 3; Web Usability Standard 1.4 s2.5 (Privacy) | G11: =INDEX(Criteria!$L$2:$L$97,MATCH($A11,Criteria!$A$2:$A$97,0)) -> Mandatory (NZ) | H11: =INDEX(Criteria!$M$2:$M$97,MATCH($A11,Criteria!$A$2:$A$97,0)) -> All | J11: Yes | K11: =IF(J11="Yes",'Scoring (simple)'!$C$6,IF(J11="Partial",'Scoring (simple)'!$C$7,IF(J11="No",'Scoring (simple)'!$C$8,""))) -> 1 | L11: =IF(K11="",0,K11) -> 1 | M11: =IF(K11="",0,1) -> 1 | N11: =INDEX('Scoring (simple)'!$C$18:$C$27,MATCH(B11,'Scoring (simple)'!$B$18:$B$27,0))/COUNTIF($B$2:$B$20,B11) -> 4.6666667 | O11: =IF(OR(J11="Partial",J11="No"),E11,"") | P11: =IF(K11="",0,(1-K11)/SUMIFS($M$2:$M$20,$B$2:$B$20,B11)*INDEX('Scoring (simple)'!$C$18:$C$27,MATCH(B11,'Scoring (simple)'!$B$18:$B$27,0))) -> 0 | Q11: =IF(P11>0,P11+IF(AND(D11="Y",J11="No"),1000,0)+ROW()/100000,0) -> 0 | R11: =IF(INDEX(Criteria!$X$2:$X$97,MATCH($A11,Criteria!$A$2:$A$97,0))="",INDEX(Criteria!$W$2:$W$97,MATCH($A11,Criteria!$A$2:$A$97,0)),HYPERLINK(INDEX(Criteria!$X$2:$X$97,MATCH($A11,Criteria!$A$2:$A$97,0)),INDEX(Criteria!$W$2:$W$97,MATCH($A11,Criteria!$A$2:$A$97,0)))) -> NZ Web Usability Standard 1.4
A12: OPS-01 | B12: =INDEX(Criteria!$B$2:$B$97,MATCH($A12,Criteria!$A$2:$A$97,0)) -> Reliability, observability and service levels | C12: =INDEX(Criteria!$D$2:$D$97,MATCH($A12,Criteria!$A$2:$A$97,0)) -> Are availability and performance targets (service levels or SLOs) defined for the service and agreed with the business owner? | D12: =INDEX(Criteria!$H$2:$H$97,MATCH($A12,Criteria!$A$2:$A$97,0)) -> N | E12: =INDEX(Criteria!$I$2:$I$97,MATCH($A12,Criteria!$A$2:$A$97,0)) -> Define and agree availability, response time and support targets that reflect how critical the service is to users, and measure against them. | F12: =INDEX(Criteria!$J$2:$J$97,MATCH($A12,Criteria!$A$2:$A$97,0)) -> AU Digital Performance Standard criterion 2; GOV.UK Service Standard point 14 | G12: =INDEX(Criteria!$L$2:$L$97,MATCH($A12,Criteria!$A$2:$A$97,0)) -> Good practice | H12: =INDEX(Criteria!$M$2:$M$97,MATCH($A12,Criteria!$A$2:$A$97,0)) -> All | J12: No | K12: =IF(J12="Yes",'Scoring (simple)'!$C$6,IF(J12="Partial",'Scoring (simple)'!$C$7,IF(J12="No",'Scoring (simple)'!$C$8,""))) -> 0 | L12: =IF(K12="",0,K12) -> 0 | M12: =IF(K12="",0,1) -> 1 | N12: =INDEX('Scoring (simple)'!$C$18:$C$27,MATCH(B12,'Scoring (simple)'!$B$18:$B$27,0))/COUNTIF($B$2:$B$20,B12) -> 4.3333333 | O12: =IF(OR(J12="Partial",J12="No"),E12,"") -> Define and agree availability, response time and support targets that reflect how critical the service is to users, and measure against them. | P12: =IF(K12="",0,(1-K12)/SUMIFS($M$2:$M$20,$B$2:$B$20,B12)*INDEX('Scoring (simple)'!$C$18:$C$27,MATCH(B12,'Scoring (simple)'!$B$18:$B$27,0))) -> 4.3333333 | Q12: =IF(P12>0,P12+IF(AND(D12="Y",J12="No"),1000,0)+ROW()/100000,0) -> 4.3334533 | R12: =IF(INDEX(Criteria!$X$2:$X$97,MATCH($A12,Criteria!$A$2:$A$97,0))="",INDEX(Criteria!$W$2:$W$97,MATCH($A12,Criteria!$A$2:$A$97,0)),HYPERLINK(INDEX(Criteria!$X$2:$X$97,MATCH($A12,Criteria!$A$2:$A$97,0)),INDEX(Criteria!$W$2:$W$97,MATCH($A12,Criteria!$A$2:$A$97,0)))) -> AU guide: measuring service availability
A13: OPS-02 | B13: =INDEX(Criteria!$B$2:$B$97,MATCH($A13,Criteria!$A$2:$A$97,0)) -> Reliability, observability and service levels | C13: =INDEX(Criteria!$D$2:$D$97,MATCH($A13,Criteria!$A$2:$A$97,0)) -> Is there proactive monitoring and alerting (for example synthetic checks of key user journeys) so the team learns of problems before users report them? | D13: =INDEX(Criteria!$H$2:$H$97,MATCH($A13,Criteria!$A$2:$A$97,0)) -> N | E13: =INDEX(Criteria!$I$2:$I$97,MATCH($A13,Criteria!$A$2:$A$97,0)) -> Deploy proactive monitoring and alerting to minimise issue triage and resolution time following service degradation or outage. | F13: =INDEX(Criteria!$J$2:$J$97,MATCH($A13,Criteria!$A$2:$A$97,0)) -> AU Digital Performance Standard criteria 1 and 2 | G13: =INDEX(Criteria!$L$2:$L$97,MATCH($A13,Criteria!$A$2:$A$97,0)) -> Good practice | H13: =INDEX(Criteria!$M$2:$M$97,MATCH($A13,Criteria!$A$2:$A$97,0)) -> All | J13: Yes | K13: =IF(J13="Yes",'Scoring (simple)'!$C$6,IF(J13="Partial",'Scoring (simple)'!$C$7,IF(J13="No",'Scoring (simple)'!$C$8,""))) -> 1 | L13: =IF(K13="",0,K13) -> 1 | M13: =IF(K13="",0,1) -> 1 | N13: =INDEX('Scoring (simple)'!$C$18:$C$27,MATCH(B13,'Scoring (simple)'!$B$18:$B$27,0))/COUNTIF($B$2:$B$20,B13) -> 4.3333333 | O13: =IF(OR(J13="Partial",J13="No"),E13,"") | P13: =IF(K13="",0,(1-K13)/SUMIFS($M$2:$M$20,$B$2:$B$20,B13)*INDEX('Scoring (simple)'!$C$18:$C$27,MATCH(B13,'Scoring (simple)'!$B$18:$B$27,0))) -> 0 | Q13: =IF(P13>0,P13+IF(AND(D13="Y",J13="No"),1000,0)+ROW()/100000,0) -> 0 | R13: =IF(INDEX(Criteria!$X$2:$X$97,MATCH($A13,Criteria!$A$2:$A$97,0))="",INDEX(Criteria!$W$2:$W$97,MATCH($A13,Criteria!$A$2:$A$97,0)),HYPERLINK(INDEX(Criteria!$X$2:$X$97,MATCH($A13,Criteria!$A$2:$A$97,0)),INDEX(Criteria!$W$2:$W$97,MATCH($A13,Criteria!$A$2:$A$97,0)))) -> AU guide: service monitoring framework
... A20: MSR-07 | B20: =INDEX(Criteria!$B$2:$B$97,MATCH($A20,Criteria!$A$2:$A$97,0)) -> Measurement and continuous improvement | C20: =INDEX(Criteria!$D$2:$D$97,MATCH($A20,Criteria!$A$2:$A$97,0)) -> Is there a regular, resourced improvement cycle where insights from research, analytics, feedback, incidents and health checks are turned into prioritised changes that are released and their impact measured? | D20: =INDEX(Criteria!$H$2:$H$97,MATCH($A20,Criteria!$A$2:$A$97,0)) -> N | E20: =INDEX(Criteria!$I$2:$I$97,MATCH($A20,Criteria!$A$2:$A$97,0)) -> Run a regular improvement cycle that turns insights from research, analytics, feedback, incidents and health checks into prioritised changes, releases them, and measures their impact. | F20: =INDEX(Criteria!$J$2:$J$97,MATCH($A20,Criteria!$A$2:$A$97,0)) -> GOV.UK Service Standard point 8; AU Digital Service Standard 2.0 criterion 10 (keep it relevant) | G20: =INDEX(Criteria!$L$2:$L$97,MATCH($A20,Criteria!$A$2:$A$97,0)) -> Good practice | H20: =INDEX(Criteria!$M$2:$M$97,MATCH($A20,Criteria!$A$2:$A$97,0)) -> All | J20: No | K20: =IF(J20="Yes",'Scoring (simple)'!$C$6,IF(J20="Partial",'Scoring (simple)'!$C$7,IF(J20="No",'Scoring (simple)'!$C$8,""))) -> 0 | L20: =IF(K20="",0,K20) -> 0 | M20: =IF(K20="",0,1) -> 1 | N20: =INDEX('Scoring (simple)'!$C$18:$C$27,MATCH(B20,'Scoring (simple)'!$B$18:$B$27,0))/COUNTIF($B$2:$B$20,B20) -> 2.5 | O20: =IF(OR(J20="Partial",J20="No"),E20,"") -> Run a regular improvement cycle that turns insights from research, analytics, feedback, incidents and health checks into prioritised changes, releases them, and measures their impact. | P20: =IF(K20="",0,(1-K20)/SUMIFS($M$2:$M$20,$B$2:$B$20,B20)*INDEX('Scoring (simple)'!$C$18:$C$27,MATCH(B20,'Scoring (simple)'!$B$18:$B$27,0))) -> 2.5 | Q20: =IF(P20>0,P20+IF(AND(D20="Y",J20="No"),1000,0)+ROW()/100000,0) -> 2.5002 | R20: =IF(INDEX(Criteria!$X$2:$X$97,MATCH($A20,Criteria!$A$2:$A$97,0))="",INDEX(Criteria!$W$2:$W$97,MATCH($A20,Criteria!$A$2:$A$97,0)),HYPERLINK(INDEX(Criteria!$X$2:$X$97,MATCH($A20,Criteria!$A$2:$A$97,0)),INDEX(Criteria!$W$2:$W$97,MATCH($A20,Criteria!$A$2:$A$97,0)))) -> GOV.UK Service Standard (14 points)
A22: Notes
A23: Rows are the criteria with weight 3 on the Criteria tab. Question, recommendation and source text is pulled live from the Criteria tab by ID (grey cells).
A24: From v1.10 the simple set covers all 10 categories: SEC-07 (privacy statement) was raised to weight 3, and LEG-09, CMG-07, CMG-08, MSR-06 and MSR-07 were added at weight 3. See the Version tab.
A25: Max points shows what each question is worth when every question in its category is answered (N/A answers redistribute points within the category).

Sheet Scoring (simple)
B1: Scoring - simple criteria
B2: Yellow cells are editable. Results use the Answer column on the Criteria (simple) tab. Category points are the same as the detailed set (all 10 categories are represented from v1.10).
B4: Parameters
B5: Answer | C5: Points
B6: Yes | C6: 1
B7: Partial | C7: 0.5
B8: No | C8: 0
B10: Overall score cap when any critical criterion is 'No' | C10: 60 | E10: Proposed defaults - validate with test assessments before use.
B11: Rating threshold - Healthy (score at or above) | C11: 85
B12: Rating threshold - Good, with gaps (at or above) | C12: 70
B13: Rating threshold - Needs attention (at or above); below = At risk | C13: 50
B16: Category results
B17: Category | C17: Points (of 100) | D17: Questions | E17: Earned | F17: Available | G17: Category % | H17: Score | I17: What good looks like
B18: Accessibility | C18: 20 | D18: =COUNTIF('Criteria (simple)'!$B$2:$B$20,B18) -> 3 | E18: =SUMIFS('Criteria (simple)'!$L$2:$L$20,'Criteria (simple)'!$B$2:$B$20,B18) -> 2.5 | F18: =SUMIFS('Criteria (simple)'!$M$2:$M$20,'Criteria (simple)'!$B$2:$B$20,B18) -> 3 | G18: =IF(F18=0,"",E18/F18) -> 0.83333333 | H18: =IF(F18=0,"",G18*C18) -> 16.666667 | I18: Disabled people, including blind and low vision users, can perceive, operate and complete the service.
B19: Usability and design | C19: 15 | D19: =COUNTIF('Criteria (simple)'!$B$2:$B$20,B19) -> 2 | E19: =SUMIFS('Criteria (simple)'!$L$2:$L$20,'Criteria (simple)'!$B$2:$B$20,B19) -> 1.5 | F19: =SUMIFS('Criteria (simple)'!$M$2:$M$20,'Criteria (simple)'!$B$2:$B$20,B19) -> 2 | G19: =IF(F19=0,"",E19/F19) -> 0.75 | H19: =IF(F19=0,"",G19*C19) -> 11.25 | I19: The service is easy to use, works across devices and is designed around user needs.
B20: Content and tone of voice | C20: 8 | D20: =COUNTIF('Criteria (simple)'!$B$2:$B$20,B20) -> 1 | E20: =SUMIFS('Criteria (simple)'!$L$2:$L$20,'Criteria (simple)'!$B$2:$B$20,B20) -> 0 | F20: =SUMIFS('Criteria (simple)'!$M$2:$M$20,'Criteria (simple)'!$B$2:$B$20,B20) -> 1 | G20: =IF(F20=0,"",E20/F20) -> 0 | H20: =IF(F20=0,"",G20*C20) -> 0 | I20: Content is plain, accurate, consistent and written in the organisation's voice.
B21: Brand and visual consistency | C21: 6 | D21: =COUNTIF('Criteria (simple)'!$B$2:$B$20,B21) -> 1 | E21: =SUMIFS('Criteria (simple)'!$L$2:$L$20,'Criteria (simple)'!$B$2:$B$20,B21) -> 1 | F21: =SUMIFS('Criteria (simple)'!$M$2:$M$20,'Criteria (simple)'!$B$2:$B$20,B21) -> 1 | G21: =IF(F21=0,"",E21/F21) -> 1 | H21: =IF(F21=0,"",G21*C21) -> 6 | I21: The service looks and feels consistent with the organisation and NZ Government identity.
B22: Security and privacy | C22: 14 | D22: =COUNTIF('Criteria (simple)'!$B$2:$B$20,B22) -> 3 | E22: =SUMIFS('Criteria (simple)'!$L$2:$L$20,'Criteria (simple)'!$B$2:$B$20,B22) -> 2.5 | F22: =SUMIFS('Criteria (simple)'!$M$2:$M$20,'Criteria (simple)'!$B$2:$B$20,B22) -> 3 | G22: =IF(F22=0,"",E22/F22) -> 0.83333333 | H22: =IF(F22=0,"",G22*C22) -> 11.666667 | I22: The service protects users and their information and meets NZ security and privacy obligations.
B23: Reliability, observability and service levels | C23: 13 | D23: =COUNTIF('Criteria (simple)'!$B$2:$B$20,B23) -> 3 | E23: =SUMIFS('Criteria (simple)'!$L$2:$L$20,'Criteria (simple)'!$B$2:$B$20,B23) -> 1.5 | F23: =SUMIFS('Criteria (simple)'!$M$2:$M$20,'Criteria (simple)'!$B$2:$B$20,B23) -> 3 | G23: =IF(F23=0,"",E23/F23) -> 0.5 | H23: =IF(F23=0,"",G23*C23) -> 6.5 | I23: The service is available, monitored, and issues are found and fixed quickly.
B24: Support and contact channels | C24: 8 | D24: =COUNTIF('Criteria (simple)'!$B$2:$B$20,B24) -> 1 | E24: =SUMIFS('Criteria (simple)'!$L$2:$L$20,'Criteria (simple)'!$B$2:$B$20,B24) -> 1 | F24: =SUMIFS('Criteria (simple)'!$M$2:$M$20,'Criteria (simple)'!$B$2:$B$20,B24) -> 1 | G24: =IF(F24=0,"",E24/F24) -> 1 | H24: =IF(F24=0,"",G24*C24) -> 8 | I24: People can get help, in the channel that works for them, when they need it.
B25: Legal and regulatory | C25: 6 | D25: =COUNTIF('Criteria (simple)'!$B$2:$B$20,B25) -> 1 | E25: =SUMIFS('Criteria (simple)'!$L$2:$L$20,'Criteria (simple)'!$B$2:$B$20,B25) -> 0.5 | F25: =SUMIFS('Criteria (simple)'!$M$2:$M$20,'Criteria (simple)'!$B$2:$B$20,B25) -> 1 | G25: =IF(F25=0,"",E25/F25) -> 0.5 | H25: =IF(F25=0,"",G25*C25) -> 3 | I25: The service meets NZ legal and public sector obligations about access to services and information.
B26: Content management and governance | C26: 5 | D26: =COUNTIF('Criteria (simple)'!$B$2:$B$20,B26) -> 2 | E26: =SUMIFS('Criteria (simple)'!$L$2:$L$20,'Criteria (simple)'!$B$2:$B$20,B26) -> 2 | F26: =SUMIFS('Criteria (simple)'!$M$2:$M$20,'Criteria (simple)'!$B$2:$B$20,B26) -> 2 | G26: =IF(F26=0,"",E26/F26) -> 1 | H26: =IF(F26=0,"",G26*C26) -> 5 | I26: The service and its content have clear ownership, workflows and ongoing funding.
B27: Measurement and continuous improvement | C27: 5 | D27: =COUNTIF('Criteria (simple)'!$B$2:$B$20,B27) -> 2 | E27: =SUMIFS('Criteria (simple)'!$L$2:$L$20,'Criteria (simple)'!$B$2:$B$20,B27) -> 0.5 | F27: =SUMIFS('Criteria (simple)'!$M$2:$M$20,'Criteria (simple)'!$B$2:$B$20,B27) -> 2 | G27: =IF(F27=0,"",E27/F27) -> 0.25 | H27: =IF(F27=0,"",G27*C27) -> 1.25 | I27: Performance and satisfaction are measured and used to improve the service.
B28: Total | C28: =SUM(C18:C27) -> 100 | D28: =SUM(D18:D27) -> 19 | I28: =IF(C28=100,"Category points total 100 - OK","CHECK: category points must total 100") -> Category points total 100 - OK
B30: Overall result
B31: Raw score (out of 100, rescaled for N/A categories) | C31: =IF(SUMIFS(C18:C27,F18:F27,">0")=0,"",SUM(H18:H27)/SUMIFS(C18:C27,F18:F27,">0")*100) -> 69.333333
B32: Critical criteria answered 'No' | C32: =COUNTIFS('Criteria (simple)'!$D$2:$D$20,"Y",'Criteria (simple)'!$J$2:$J$20,"No") -> 0
B33: Final score (after critical cap) | C33: =IF(C31="","",IF(C32>0,MIN(C31,C10),C31)) -> 69.333333
B34: Rating | C34: =IF(C33="","",IF(C33>=C11,"Healthy",IF(C33>=C12,"Good, with gaps",IF(C33>=C13,"Needs attention","At risk")))) -> Needs attention
B35: Criteria answered | C35: =COUNTIF('Criteria (simple)'!$J$2:$J$20,"Yes")+COUNTIF('Criteria (simple)'!$J$2:$J$20,"Partial")+COUNTIF('Criteria (simple)'!$J$2:$J$20,"No") -> 19
B36: Criteria N/A | C36: =COUNTIF('Criteria (simple)'!$J$2:$J$20,"N/A") -> 0
B37: Criteria not yet answered | C37: =COUNTBLANK('Criteria (simple)'!$J$2:$J$20) -> 0
B40: Key recommendations (top 5 by points lost; critical failures first)
B41: Rank | C41: ID | D41: Points lost | E41: Recommendation
B42: 1 | C42: =IF(LARGE('Criteria (simple)'!$Q$2:$Q$20,1)=0,"",INDEX('Criteria (simple)'!$A$2:$A$20,MATCH(LARGE('Criteria (simple)'!$Q$2:$Q$20,1),'Criteria (simple)'!$Q$2:$Q$20,0))) -> CON-01 | D42: =IF(C42="","",INDEX('Criteria (simple)'!$P$2:$P$20,MATCH(C42,'Criteria (simple)'!$A$2:$A$20,0))) -> 8 | E42: =IF(C42="","",INDEX('Criteria (simple)'!$E$2:$E$20,MATCH(C42,'Criteria (simple)'!$A$2:$A$20,0))) -> Write and review all public content in plain language, test it with users, and follow the agency's Plain Language Act processes.
B43: 2 | C43: =IF(LARGE('Criteria (simple)'!$Q$2:$Q$20,2)=0,"",INDEX('Criteria (simple)'!$A$2:$A$20,MATCH(LARGE('Criteria (simple)'!$Q$2:$Q$20,2),'Criteria (simple)'!$Q$2:$Q$20,0))) -> OPS-01 | D43: =IF(C43="","",INDEX('Criteria (simple)'!$P$2:$P$20,MATCH(C43,'Criteria (simple)'!$A$2:$A$20,0))) -> 4.3333333 | E43: =IF(C43="","",INDEX('Criteria (simple)'!$E$2:$E$20,MATCH(C43,'Criteria (simple)'!$A$2:$A$20,0))) -> Define and agree availability, response time and support targets that reflect how critical the service is to users, and measure against them.
B44: 3 | C44: =IF(LARGE('Criteria (simple)'!$Q$2:$Q$20,3)=0,"",INDEX('Criteria (simple)'!$A$2:$A$20,MATCH(LARGE('Criteria (simple)'!$Q$2:$Q$20,3),'Criteria (simple)'!$Q$2:$Q$20,0))) -> UXD-02 | D44: =IF(C44="","",INDEX('Criteria (simple)'!$P$2:$P$20,MATCH(C44,'Criteria (simple)'!$A$2:$A$20,0))) -> 3.75 | E44: =IF(C44="","",INDEX('Criteria (simple)'!$E$2:$E$20,MATCH(C44,'Criteria (simple)'!$A$2:$A$20,0))) -> Run regular user research with people who use the service, including those who struggle, and record how findings change the service.
B45: 4 | C45: =IF(LARGE('Criteria (simple)'!$Q$2:$Q$20,4)=0,"",INDEX('Criteria (simple)'!$A$2:$A$20,MATCH(LARGE('Criteria (simple)'!$Q$2:$Q$20,4),'Criteria (simple)'!$Q$2:$Q$20,0))) -> ACC-02 | D45: =IF(C45="","",INDEX('Criteria (simple)'!$P$2:$P$20,MATCH(C45,'Criteria (simple)'!$A$2:$A$20,0))) -> 3.3333333 | E45: =IF(C45="","",INDEX('Criteria (simple)'!$E$2:$E$20,MATCH(C45,'Criteria (simple)'!$A$2:$A$20,0))) -> Test every key task with at least one desktop and one mobile screen reader, ideally including blind and low vision users, and fix issues that stop tasks being completed.
B46: 5 | C46: =IF(LARGE('Criteria (simple)'!$Q$2:$Q$20,5)=0,"",INDEX('Criteria (simple)'!$A$2:$A$20,MATCH(LARGE('Criteria (simple)'!$Q$2:$Q$20,5),'Criteria (simple)'!$Q$2:$Q$20,0))) -> LEG-09 | D46: =IF(C46="","",INDEX('Criteria (simple)'!$P$2:$P$20,MATCH(C46,'Criteria (simple)'!$A$2:$A$20,0))) -> 3 | E46: =IF(C46="","",INDEX('Criteria (simple)'!$E$2:$E$20,MATCH(C46,'Criteria (simple)'!$A$2:$A$20,0))) -> Create and maintain a register of the legislation the service is subject to - including service-specific Acts such as the Planning Act and Natural Environment Act, and cross-cutting obligations on equal access, legal basis, public records and information access - have it reviewed by legal advisors, and re-check it when legislation or the service changes.

Sheet Materiality
B1: Materiality assessment
B2: How much this application matters to its users and the organisation, rated 1 (Immaterial) to 5 (Critical). Scored separately and reported alongside - never inside - the UX health score. Answer each factor 1-5 in the yellow column.
A4: ID | B4: Factor | C4: Question | D4: 1 Immaterial | E4: 2 Low | F4: 3 Moderate | G4: 4 High | H4: 5 Critical | I4: Weight | J4: Floor trigger | K4: Answer (1-5) | L4: Weighted
A5: MAT-01 | B5: User dependence | C5: How dependent are users on the information or service provided in this application? | D5: Information or service is readily available elsewhere; using this app is optional. | E5: Available elsewhere with little extra effort. | F5: Alternatives exist but are noticeably slower, harder or less complete. | G5: Few practical alternatives; users rely on this app for important tasks. | H5: Only available in this app, and users need it to complete a necessary or legally required task. | I5: 3 | J5: Y | K5: 4 | L5: =IF(K5="","",K5*I5) -> 12
A6: MAT-02 | B6: Organisation dependence | C6: How dependent is the organisation on this application, and how would an outage of several hours be received? | D6: An outage of several days would be tolerated with little impact. | E6: An outage of a day would cause internal inconvenience only. | F6: An outage of several hours would disrupt business processes. | G6: An outage of several hours could lead to complaints from a small group of high-touch users or stakeholders. | H6: An outage of several hours could attract media attention, Ministerial interest or a breach of statutory obligations. | I6: 3 | J6: Y | K6: 3 | L6: =IF(K6="","",K6*I6) -> 9
A7: MAT-03 | B7: Relative importance | C7: How important is this application to its users compared with the organisation's other applications? | D7: One of many minor applications; rarely front of mind. | E7: Below average importance. | F7: Similar importance to most of the organisation's applications. | G7: One of the organisation's more important applications. | H7: A flagship or primary channel for the organisation's users. | I7: 2 | J7: N | K7: 4 | L7: =IF(K7="","",K7*I7) -> 8
A8: MAT-04 | B8: Scope of user base | C8: How broad is the user base - one user group, or several? | D8: A single small internal team. | E8: One user group (internal or external). | F8: Two or three distinct user groups. | G8: Several user groups, including external users. | H8: Many user groups, including the general public or sector-wide users. | I8: 2 | J8: N | K8: 3 | L8: =IF(K8="","",K8*I8) -> 6
A9: MAT-05 | B9: Scale of user base | C9: Roughly how many people use the application? | D9: Fewer than 10. | E9: 10 to 99. | F9: 100 to 999. | G9: 1,000 to 9,999. | H9: 10,000 or more. | I9: 2 | J9: N | K9: 4 | L9: =IF(K9="","",K9*I9) -> 8
A10: MAT-06 | B10: Frequency of access | C10: How often are typical users expected to use the application? | D10: Annually or less often. | E10: Quarterly. | F10: Monthly. | G10: Weekly. | H10: Daily or more often. | I10: 1 | J10: N | K10: 2 | L10: =IF(K10="","",K10*I10) -> 2
A11: MAT-07 | B11: Consequence of failure or error | C11: What is the consequence for users if the application fails, is unavailable or gives wrong information? | D11: Minor inconvenience only. | E11: Delay or extra effort, easily recovered. | F11: Significant delay, cost or rework for users. | G11: Financial, legal or reputational harm to users, or a missed obligation. | H11: Serious harm - safety, rights, entitlements or statutory deadlines - that may be hard to reverse. | I11: 3 | J11: Y | K11: 4 | L11: =IF(K11="","",K11*I11) -> 12
A12: MAT-08 | B12: Time sensitivity | C12: How time-critical are the tasks users complete in the application? | D12: Can wait weeks without impact. | E12: Can wait days. | F12: Should be completed within a day or two. | G12: Same-day completion often needed. | H12: Time-critical or tied to statutory deadlines; delays have consequences. | I12: 1 | J12: N | K12: 3 | L12: =IF(K12="","",K12*I12) -> 3
A13: MAT-09 | B13: Users at risk of exclusion | C13: To what extent does the application serve people who may be disadvantaged if it doesn't work well for them (for example disabled people, people with limited digital access, or people in difficult circumstances)? | D13: Not at all - users are a small, digitally capable professional group. | E13: A few such users. | F13: A meaningful minority of users. | G13: A large share of users. | H13: Primarily serves people at risk of exclusion or in difficult circumstances. | I13: 2 | J13: N | K13: 3 | L13: =IF(K13="","",K13*I13) -> 6
A14: MAT-10 | B14: Sensitivity of information | C14: How sensitive is the information the application collects, stores or displays? | D14: Public information only. | E14: Low-sensitivity internal or contact information. | F14: Personal information. | G14: Sensitive personal or commercially sensitive information. | H14: Highly sensitive information (for example health, financial, identity or classified information). | I14: 1 | J14: N | K14: 3 | L14: =IF(K14="","",K14*I14) -> 3
B17: Parameters
C18: Minimum rating when any floor-trigger factor is answered 5 | D18: 4
C19: Floor triggers (Y in column J): user dependence, organisation dependence and consequence of failure. A 5 on any of these means the application can't be rated below the floor, however low the other factors are.
B21: Materiality result
C22: Factors answered | D22: =COUNT(K5:K14) -> 10
C23: Weighted average (1-5) | D23: =IF(COUNT(K5:K14)=0,"",SUMPRODUCT(I5:I14,K5:K14)/SUMIFS(I5:I14,K5:K14,">0")) -> 3.45
C24: Floor-trigger factors answered 5 | D24: =COUNTIFS(J5:J14,"Y",K5:K14,5) -> 0
C25: Materiality rating (1-5) | D25: =IF(D23="","",IF(D24>0,MAX(ROUND(D23,0),$D$18),ROUND(D23,0))) -> 3
C26: Materiality label | D26: =IF(D25="","",INDEX($C$31:$C$35,D25)) -> Moderate
C27: What this means | D27: =IF(D25="","",INDEX($D$31:$D$35,D25)) -> A meaningful service for its users or the organisation. Planned support and monitoring; fix significant issues promptly.
C28: Suggested service tier | D28: =IF(D25="","",INDEX('Service tiers'!$B$12:$B$16,D25)) -> Silver
C29: Agreed service tier (if overridden) | E29: Record the reason for any override.
B30: Rating | C30: Label | D30: Meaning and suggested support posture
B31: 1 | C31: Immaterial | D31: Little dependence on the application. Light-touch support and periodic health checks are proportionate.
B32: 2 | C32: Low | D32: Some users rely on it occasionally, with easy alternatives. Standard support; fix issues in the normal release cycle.
B33: 3 | C33: Moderate | D33: A meaningful service for its users or the organisation. Planned support and monitoring; fix significant issues promptly.
B34: 4 | C34: High | D34: Users or the organisation depend on it. Business-hours (or better) support, proactive monitoring, and prompt remediation of health check findings.
B35: 5 | C35: Critical | D35: Users must use it to complete necessary tasks and failure has serious consequences. Highest support tier, 24/7 monitoring, and priority remediation of all critical and high findings.

Sheet Service tiers
A1: Service tiers - proposed definitions
A2: Proposed for MCERT, which has no agreed tier definitions yet. The suggested tier follows from the materiality rating; the service owner can override it with reasons. All targets are starting proposals to confirm with the CDO, operations, suppliers and governance before they are used in contracts or SLAs.
A4: Tier | B4: Materiality rating | C4: When to use | D4: Availability target | E4: Support hours | F4: Priority 1 incident: response / restore | G4: Priority 2 incident: response / restore | H4: Recovery time objective (RTO) | I4: Recovery point objective (RPO) | J4: Monitoring and alerting | K4: Planned maintenance | L4: UX health check frequency | M4: Target UX health rating | N4: Remediation of health check findings | O4: Performance reporting
A5: Platinum | B5: 5 Critical | C5: Users must use the application to complete necessary tasks; failure has serious consequences or could attract media or Ministerial attention. | D5: 99.9% monthly, measured on key user journeys (about 45 minutes unplanned downtime a month) | E5: 24/7, including on-call | F5: 15 minutes / 2 hours (workaround or restore), 24/7 | G5: 1 hour / 8 hours | H5: 4 hours | I5: 15 minutes | J5: 24/7 synthetic monitoring of key journeys at least every 5 minutes, with paging and a public status page | K5: Outside business hours, with at least 5 business days' notice to users | L5: Every 6 months and after any major change | M5: Healthy (85+) with no critical criteria answered 'No' | N5: Critical findings within 1 month; high within 3 months | O5: Monthly to the service owner; quarterly to governance
A6: Gold | B6: 4 High | C6: Users or the organisation depend on the application; an outage of several hours could bring complaints from high-touch users or stakeholders. | D6: 99.5% monthly (about 3.5 hours unplanned downtime a month) | E6: Extended hours (7am-7pm business days), with on-call for Priority 1 | F6: 30 minutes / 4 hours | G6: 2 business hours / 1 business day | H6: 8 hours | I6: 1 hour | J6: Synthetic monitoring of key journeys with alerts routed to the on-call team | K6: Outside business hours where possible, with at least 5 business days' notice | L6: Annually and after any major change | M6: Good, with gaps (70+) with no critical criteria answered 'No' | N6: Critical findings within 3 months; high within 6 months | O6: Monthly to the service owner; quarterly to governance
A7: Silver | B7: 3 Moderate | C7: A meaningful service for its users or the organisation, with workarounds available during an outage. | D7: 99.0% during business hours | E7: Business hours (8am-5pm business days) | F7: 2 business hours / 1 business day | G7: 1 business day / 5 business days | H7: 24 hours | I7: 24 hours | J7: Uptime monitoring with alerts during business hours | K7: With at least 2 business days' notice | L7: Annually | M7: Needs attention (50+) with no critical criteria answered 'No' | N7: Critical findings within 6 months; high planned into the next release cycle | O7: Quarterly to the service owner
A8: Bronze | B8: 1-2 Immaterial or Low | C8: Optional or low-use application with easy alternatives; little impact if unavailable for several days. | D8: Best effort during business hours | E8: Business hours, best effort | F8: Next business day / 5 business days | G8: 5 business days / next planned release | H8: 5 business days | I8: 24 hours | J8: Basic uptime monitoring | K8: Any time, with notice where practical | L8: Every 2 years, or after major change | M8: No critical criteria answered 'No' | N8: Critical findings within 12 months, or risk formally accepted by the service owner | O8: Annually to the service owner
A10: Rating to tier
A11: Materiality rating | B11: Suggested tier
A12: 1 | B12: Bronze
A13: 2 | B13: Bronze
A14: 3 | B14: Silver
A15: 4 | B15: Gold
A16: 5 | B16: Platinum
A18: Notes
A19: Targets are measured monthly unless stated. Business hours are 8am-5pm, Monday to Friday, excluding public holidays.
A20: Priority 1 = service unavailable or a key task can't be completed by most users. Priority 2 = major function degraded or a workaround is needed.
A21: 'Restore' means service restored or a workaround in place; the underlying fix can follow under problem management.
A22: Target UX health rating sets the minimum expected result from the health check for each tier; services below it should have a remediation plan agreed by the service owner.
A23: Supplier contracts and hosting arrangements should be aligned to the tier (see OPS-06).

Sheet Report (simple)
B1: UX Health Check report - preview
B2: Service name | C2: [Enter service name]
B3: Assessment date | C3: [Enter date]
B4: Preview of the app's report layout, built from the Criteria (simple), Scoring (simple) and Materiality tabs. The UX health score and the materiality rating are separate measures and are never combined.
B6: 1. UX health score | K6: Thresholds (from Scoring (simple))
B7: Score (out of 100) | C7: ='Scoring (simple)'!C33 -> 69.333333 | F7: ="Green "&K7&"+ Healthy | Yellow "&K9&"-"&(K7-1)&" Good, with gaps | Amber "&K8&"-"&(K9-1)&" Needs attention | Red below "&K8&" or any critical failure" -> Green 85+ Healthy | Yellow 70-84 Good, with gaps | Amber 50-69 Needs attention | Red below 50 or any critical failure | K7: ='Scoring (simple)'!C11 -> 85
B8: Rating | C8: ='Scoring (simple)'!C34 -> Needs attention | K8: ='Scoring (simple)'!C13 -> 50
B9: Critical criteria answered 'No' | C9: ='Scoring (simple)'!C32 -> 0 | K9: ='Scoring (simple)'!C12 -> 70
B10: Questions answered / N/A / unanswered | C10: ='Scoring (simple)'!C35&" / "&'Scoring (simple)'!C36&" / "&'Scoring (simple)'!C37 -> 19 / 0 / 0
B12: 2. Materiality (reported separately - not part of the score)
B13: Materiality rating (1-5) | C13: =Materiality!$D$25 -> 3 | F13: Green 1 | Yellow-green 2 | Yellow 3 | Orange 4 | Red 5
B14: Materiality label | C14: =Materiality!$D$26 -> Moderate
B15: What this means | C15: =Materiality!$D$27 -> A meaningful service for its users or the organisation. Planned support and monitoring; fix significant issues promptly.
B16: Weighted average of factors | C16: =Materiality!$D$23 -> 3.45
B17: Floor-trigger factors rated 5 | C17: =Materiality!$D$24 -> 0
B18: Service tier (agreed, else suggested) | C18: =IF(Materiality!$D$29<>"",Materiality!$D$29&" (agreed)",Materiality!$D$28&" (suggested)") -> Silver (suggested)
B19: Tier target UX health rating | C19: =IFERROR(INDEX('Service tiers'!$M$5:$M$8,MATCH(IF(Materiality!$D$29<>"",Materiality!$D$29,Materiality!$D$28),'Service tiers'!$A$5:$A$8,0)),"") -> Needs attention (50+) with no critical criteria answered 'No'
B22: 3. Key recommendations
B23: Rank | C23: ID | D23: Recommendation | G23: Supporting link
B24: 1 | C24: ='Scoring (simple)'!C42 -> CON-01 | D24: ='Scoring (simple)'!E42 -> Write and review all public content in plain language, test it with users, and follow the agency's Plain Language Act processes. | G24: =IF(C24="","",IF(INDEX(Criteria!$X$2:$X$97,MATCH(C24,Criteria!$A$2:$A$97,0))="",INDEX(Criteria!$W$2:$W$97,MATCH(C24,Criteria!$A$2:$A$97,0)),HYPERLINK(INDEX(Criteria!$X$2:$X$97,MATCH(C24,Criteria!$A$2:$A$97,0)),INDEX(Criteria!$W$2:$W$97,MATCH(C24,Criteria!$A$2:$A$97,0))))) -> Plain Language Act 2022
B25: 2 | C25: ='Scoring (simple)'!C43 -> OPS-01 | D25: ='Scoring (simple)'!E43 -> Define and agree availability, response time and support targets that reflect how critical the service is to users, and measure against them. | G25: =IF(C25="","",IF(INDEX(Criteria!$X$2:$X$97,MATCH(C25,Criteria!$A$2:$A$97,0))="",INDEX(Criteria!$W$2:$W$97,MATCH(C25,Criteria!$A$2:$A$97,0)),HYPERLINK(INDEX(Criteria!$X$2:$X$97,MATCH(C25,Criteria!$A$2:$A$97,0)),INDEX(Criteria!$W$2:$W$97,MATCH(C25,Criteria!$A$2:$A$97,0))))) -> AU guide: measuring service availability
B26: 3 | C26: ='Scoring (simple)'!C44 -> UXD-02 | D26: ='Scoring (simple)'!E44 -> Run regular user research with people who use the service, including those who struggle, and record how findings change the service. | G26: =IF(C26="","",IF(INDEX(Criteria!$X$2:$X$97,MATCH(C26,Criteria!$A$2:$A$97,0))="",INDEX(Criteria!$W$2:$W$97,MATCH(C26,Criteria!$A$2:$A$97,0)),HYPERLINK(INDEX(Criteria!$X$2:$X$97,MATCH(C26,Criteria!$A$2:$A$97,0)),INDEX(Criteria!$W$2:$W$97,MATCH(C26,Criteria!$A$2:$A$97,0))))) -> GOV.UK: understand users and needs
B27: 4 | C27: ='Scoring (simple)'!C45 -> ACC-02 | D27: ='Scoring (simple)'!E45 -> Test every key task with at least one desktop and one mobile screen reader, ideally including blind and low vision users, and fix issues that stop tasks being completed. | G27: =IF(C27="","",IF(INDEX(Criteria!$X$2:$X$97,MATCH(C27,Criteria!$A$2:$A$97,0))="",INDEX(Criteria!$W$2:$W$97,MATCH(C27,Criteria!$A$2:$A$97,0)),HYPERLINK(INDEX(Criteria!$X$2:$X$97,MATCH(C27,Criteria!$A$2:$A$97,0)),INDEX(Criteria!$W$2:$W$97,MATCH(C27,Criteria!$A$2:$A$97,0))))) -> W3C accessibility evaluation methodology
B28: 5 | C28: ='Scoring (simple)'!C46 -> LEG-09 | D28: ='Scoring (simple)'!E46 -> Create and maintain a register of the legislation the service is subject to - including service-specific Acts such as the Planning Act and Natural Environment Act, and cross-cutting obligations on equal access, legal basis, public records and information access - have it reviewed by legal advisors, and re-check it when legislation or the service changes. | G28: =IF(C28="","",IF(INDEX(Criteria!$X$2:$X$97,MATCH(C28,Criteria!$A$2:$A$97,0))="",INDEX(Criteria!$W$2:$W$97,MATCH(C28,Criteria!$A$2:$A$97,0)),HYPERLINK(INDEX(Criteria!$X$2:$X$97,MATCH(C28,Criteria!$A$2:$A$97,0)),INDEX(Criteria!$W$2:$W$97,MATCH(C28,Criteria!$A$2:$A$97,0))))) -> Planning and Natural Environment Acts overview
B30: 4. Category results
B31: Category | C31: Questions (answered/asked) | D31: Score | E31: Out of | F31: Category %
B32: ='Scoring (simple)'!B18 -> Accessibility | C32: =COUNTIFS('Criteria (simple)'!$B$2:$B$20,B32,'Criteria (simple)'!$J$2:$J$20,"<>")&"/"&'Scoring (simple)'!D18 -> 3/3 | D32: ='Scoring (simple)'!H18 -> 16.666667 | E32: ='Scoring (simple)'!C18 -> 20 | F32: ='Scoring (simple)'!G18 -> 0.83333333
B33: ='Scoring (simple)'!B19 -> Usability and design | C33: =COUNTIFS('Criteria (simple)'!$B$2:$B$20,B33,'Criteria (simple)'!$J$2:$J$20,"<>")&"/"&'Scoring (simple)'!D19 -> 2/2 | D33: ='Scoring (simple)'!H19 -> 11.25 | E33: ='Scoring (simple)'!C19 -> 15 | F33: ='Scoring (simple)'!G19 -> 0.75
B34: ='Scoring (simple)'!B20 -> Content and tone of voice | C34: =COUNTIFS('Criteria (simple)'!$B$2:$B$20,B34,'Criteria (simple)'!$J$2:$J$20,"<>")&"/"&'Scoring (simple)'!D20 -> 1/1 | D34: ='Scoring (simple)'!H20 -> 0 | E34: ='Scoring (simple)'!C20 -> 8 | F34: ='Scoring (simple)'!G20 -> 0
B35: ='Scoring (simple)'!B21 -> Brand and visual consistency | C35: =COUNTIFS('Criteria (simple)'!$B$2:$B$20,B35,'Criteria (simple)'!$J$2:$J$20,"<>")&"/"&'Scoring (simple)'!D21 -> 1/1 | D35: ='Scoring (simple)'!H21 -> 6 | E35: ='Scoring (simple)'!C21 -> 6 | F35: ='Scoring (simple)'!G21 -> 1
B36: ='Scoring (simple)'!B22 -> Security and privacy | C36: =COUNTIFS('Criteria (simple)'!$B$2:$B$20,B36,'Criteria (simple)'!$J$2:$J$20,"<>")&"/"&'Scoring (simple)'!D22 -> 3/3 | D36: ='Scoring (simple)'!H22 -> 11.666667 | E36: ='Scoring (simple)'!C22 -> 14 | F36: ='Scoring (simple)'!G22 -> 0.83333333
B37: ='Scoring (simple)'!B23 -> Reliability, observability and service levels | C37: =COUNTIFS('Criteria (simple)'!$B$2:$B$20,B37,'Criteria (simple)'!$J$2:$J$20,"<>")&"/"&'Scoring (simple)'!D23 -> 3/3 | D37: ='Scoring (simple)'!H23 -> 6.5 | E37: ='Scoring (simple)'!C23 -> 13 | F37: ='Scoring (simple)'!G23 -> 0.5
B38: ='Scoring (simple)'!B24 -> Support and contact channels | C38: =COUNTIFS('Criteria (simple)'!$B$2:$B$20,B38,'Criteria (simple)'!$J$2:$J$20,"<>")&"/"&'Scoring (simple)'!D24 -> 1/1 | D38: ='Scoring (simple)'!H24 -> 8 | E38: ='Scoring (simple)'!C24 -> 8 | F38: ='Scoring (simple)'!G24 -> 1
B39: ='Scoring (simple)'!B25 -> Legal and regulatory | C39: =COUNTIFS('Criteria (simple)'!$B$2:$B$20,B39,'Criteria (simple)'!$J$2:$J$20,"<>")&"/"&'Scoring (simple)'!D25 -> 1/1 | D39: ='Scoring (simple)'!H25 -> 3 | E39: ='Scoring (simple)'!C25 -> 6 | F39: ='Scoring (simple)'!G25 -> 0.5
B40: ='Scoring (simple)'!B26 -> Content management and governance | C40: =COUNTIFS('Criteria (simple)'!$B$2:$B$20,B40,'Criteria (simple)'!$J$2:$J$20,"<>")&"/"&'Scoring (simple)'!D26 -> 2/2 | D40: ='Scoring (simple)'!H26 -> 5 | E40: ='Scoring (simple)'!C26 -> 5 | F40: ='Scoring (simple)'!G26 -> 1
B41: ='Scoring (simple)'!B27 -> Measurement and continuous improvement | C41: =COUNTIFS('Criteria (simple)'!$B$2:$B$20,B41,'Criteria (simple)'!$J$2:$J$20,"<>")&"/"&'Scoring (simple)'!D27 -> 2/2 | D41: ='Scoring (simple)'!H27 -> 1.25 | E41: ='Scoring (simple)'!C27 -> 5 | F41: ='Scoring (simple)'!G27 -> 0.25
B43: Reading the two measures together
B44: The UX health score shows how well the application currently supports a good user experience. The materiality rating shows how much it matters if it doesn't. Use them side by side to prioritise, and compare the score with the target for the service tier: a High or Critical materiality application rated 'Needs attention' or 'At risk' should be remediated before a low-materiality application with the same score. Full per-question recommendations are in the Report recommendation column of Criteria (simple).

Sheet Sources
A1: Source | B1: Publisher | C1: Version / status (at 24 Oct 2026) | D1: NZ status | E1: Link | F1: Link check (24 Oct 2026) | G1: Licence / reuse note | H1: Used in
A2: NZ Government Web Accessibility Standard 1.2 | B2: GCDO (Government Digital Delivery Agency) | C2: In force from 17 Mar 2025; WCAG 2.2 Level AA with listed exceptions; s4 assessment and reporting. To be replaced by the Digital Accessibility Standard (expected early 2027). | D2: Mandatory (NZ) | E2: https://www.digital.govt.nz/standards-and-guidance/nz-government-web-standards/web-accessibility-standard-1-2 | F2: Fetched - live | G2: NZ Government content - check the site's copyright page before reusing text. | H2: ACC-01, ACC-12, ACC-15, CMG-02
A3: NZ Government Web Usability Standard 1.4 | B3: GCDO (Government Digital Delivery Agency) | C3: In force from 17 Mar 2025. s2.2 Government identity, s2.3 Contact information (NZ Relay at s2.3.3), s2.4 Copyright, s2.5 Privacy. Requirements expected to become guidance in the updated Digital Service Design Standard. | D3: Mandatory (NZ) | E3: https://www.digital.govt.nz/standards-and-guidance/nz-government-web-standards/web-usability-standard-1-4 | F3: Fetched - live | G3: NZ Government content - check the site's copyright page before reusing text. | H3: BRD-02, SEC-07, SUP-01, LEG-01
A4: NZ government logo markup | B4: GCDO (Government Digital Delivery Agency) | C4: Guidance supporting Web Usability Standard s2.2. | D4: Recommended (NZ) | E4: https://www.digital.govt.nz/standards-and-guidance/design-and-ux/usability/nz-government-logo-markup | F4: Fetched - live | G4: NZ Government content - check the site's copyright page before reusing text. | H4: BRD-02
A5: Digital Accessibility Standard (DAS) | B5: GCDO (Government Digital Delivery Agency) | C5: Draft. Public consultation 13 Jul - 7 Aug 2026; final standard expected early 2027; based on EN 301 549; will replace the Web Accessibility Standard. | D5: Recommended (NZ) - draft | E5: https://www.digital.govt.nz/standards-and-guidance/nz-government-web-standards/digital-accessibility-standard | F5: Fetched - live | G5: NZ Government content - check the site's copyright page before reusing text. | H5: ACC-01, ACC-13, CON-07, SUP-03
A6: Draft DAS - large print summary | B6: GCDO (Government Digital Delivery Agency) | C6: Consultation summary (Jul 2026). Source of the draft requirement to reply to accessibility questions within 3 days. | D6: Recommended (NZ) - draft | E6: https://www.digital.govt.nz/assets/Standards-guidance/NZ-government-web-standards/DAS/Digital-Accessibility-Standard-DAS-Large-print.pdf | F6: Search-indexed (automated fetch blocked) | G6: NZ Government content - check the site's copyright page before reusing text. | H6: SUP-03
A7: Centralised Web Accessibility Checker (CWAC) | B7: Department of Internal Affairs / GCDO | C7: Open-source automated WCAG 2.2 checker used for quarterly monitoring of government websites. | D7: Recommended (NZ) | E7: https://github.com/GOVTNZ/cwac | F7: Fetched - live | G7: Open source under GPL-3.0 (Crown copyright). | H7: ACC-14
A8: Digital Service Design Standard | B8: GCDO (Government Digital Delivery Agency) | C8: 2018 version: 12 principles. Proposed updated principles published in draft; refresh underway. | D8: Recommended (NZ) | E8: https://www.digital.govt.nz/standards-and-guidance/digital-service-design-standard | F8: Fetched - live | G8: NZ Government content - check the site's copyright page before reusing text. | H8: ACC-16, UXD-02, CON-06, CON-08, SUP-06, LEG-08, CMG-06
A9: Web Content Accessibility Guidelines (WCAG) 2.2 | B9: W3C | C9: W3C Recommendation (current version dated 12 Dec 2024). Also published as ISO/IEC 40500:2025. | D9: Mandatory (NZ) via WAS 1.2 | E9: https://www.w3.org/TR/WCAG22/ | F9: Fetched - live | G9: W3C Document License - may be quoted with attribution. | H9: ACC-01 to ACC-13, UXD-01, CON-05, BRD-03, SUP-02
A10: W3C Accessibility Guidelines (WCAG) 3.0 | B10: W3C | C10: Working Draft dated 10 Sep 2026. Not final; not yet referenced by NZ standards. | D10: Not applicable yet | E10: https://www.w3.org/TR/wcag-3.0/ | F10: Fetched - live | G10: W3C Document License. | H10: Watch only
A11: WCAG-EM (Evaluation Methodology) | B11: W3C | C11: WCAG-EM 2.0 published 23 Jul 2026 (covers apps and other digital products); WCAG-EM 1.0 still available. | D11: Good practice | E11: https://www.w3.org/WAI/test-evaluate/conformance/wcag-em/ | F11: Fetched - live | G11: W3C Document License. | H11: ACC-02
A12: Accessibility Maturity Model | B12: W3C | C12: W3C Group Note, 4 Nov 2025. | D12: Good practice | E12: https://www.w3.org/TR/maturity-model/ | F12: Fetched - live | G12: W3C Document License. | H12: ACC-17
... A55: Planning and environment Acts become law (news) | B55: Inside Government NZ | C55: News report dated 30 Sep 2026 confirming Royal assent; transitional consenting arrangements and phased implementation through 2027-2030. | D55: Context | E55: https://insidegovernment.co.nz/?p=37222 | F55: Fetched - live | G55: News - link only. | H55: LEG-09
A57: Link check key
A58: Fetched - live: the page was retrieved on 24 Oct 2026 and confirmed to be the named source.
A59: Search-indexed: the site blocks automated retrieval or returned no readable body; the exact URL was confirmed live through current search results.

Sheet Version
A1: Version | B1: Release date | C1: Status | D1: Prepared by | E1: Approved by | F1: Summary | G1: Changes in this version | H1: How the framework was developed | I1: Evidence base | J1: Structure and categories - rationale | K1: Weighting and scoring - rationale | L1: Critical criteria - rationale | M1: Simple set - rationale | N1: Link verification | O1: Licensing and reuse | P1: Known limitations and assumptions | Q1: Next review triggers
